Workbook

Sheet Stato patrimoniale
A1: ID | B1: Statistiche | C1: Nome | D1: Tipo | E1: Classe | F1: Area | G1: Settore | H1: Emittente | I1: Quantità | J1: Valuta | K1: ISIN | L1: Ticker | M1: Ticker Data | N1: Tassa | O1: Data_Acquisto | P1: Mercato | Q1: Intermediario | R1: Prezzo_Acquisto | S1: Commissioni | T1: Spese valuta | U1: Cambio | V1: Spese euro acquisto | W1: Costo | X1: Mercato | Y1: Intermediario | Z1: Prezzo | AA1: Variazione quantità | AB1: Cambio | AC1: Dividendi totali euro | AD1: Valore | AE1: Delta | AF1: Delta percentuale | AG1: Data_Vendita | AH1: Mercato | AI1: Intermediario | AJ1: Prezzo_Vendita | AK1: Commissioni | AL1: Spese valuta | AM1: Cambio | AN1: Spese euro vendita | AO1: Cedole nette | AP1: Ricavo | AQ1: Guadagno | AR1: Guadagno percentuale | AS1: Tassa plusvalenza | AT1: Guadagno netto
A2: 13 | B2: 1 | C2: CNH Industrial | D2: A | E2: Azioni | F2: Italia | G2: Auto | H2: Italia | I2: 18 | J2: EUR | K2: NL0010545661 | L2: CNHI.VI | M2: #VALUE! | N2: 0.26 | O2: 45133 | P2: Milano | Q2: Fineco-C | R2: 13.863 | S2: 0 | T2: 0 | U2: 1 | W2: =(I2/IF(OR(D2="O",D2="CE"),100,1)*R2*(1+S2)+T2)*U2+V2 -> 249.534 | X2: Milano | Y2: Fineco-C | Z2: 9.13 | AA2: =SUMIF(Operazioni!A:A,A2,Operazioni!C:C) -> 0 | AB2: =INDEX(Valute!B:B,MATCH(J2,Valute!A:A,0)) -> 1 | AC2: =SUMIF(Operazioni!A:A,A2,Operazioni!K:K) -> 5.8016 | AD2: =((I2+AA2)/IF(OR(D2="O",D2="CE"),100,1)*Z2)*AB2+AC2 -> 170.1416 | AE2: =AD2-W2 -> -79.3924 | AF2: =IF(W2<>0,AE2/W2,"") -> -0.31816265 | AG2: 45531 | AH2: Milano | AI2: Fineco-C | AJ2: 9.13 | AL2: 2.95 | AM2: 1 | AO2: =AC2*(1-N2) -> 4.293184 | AP2: =((I2+AA2)/IF(OR(D2="O",D2="CE"),100,1)*AJ2*(1-AK2)-AL2)*AM2-AN2+AC2 -> 167.1916 | AQ2: =AP2-W2 -> -82.3424 | AR2: =IF(W2<>0,AQ2/W2,"") -> -0.32998469 | AS2: =(AQ2-AC2)*N2 -> -22.91744 | AT2: =IF(W2<>0,(AQ2-AS2)/W2,"") -> -0.23814374
A3: 14 | B3: 1 | C3: Unicredit | D3: A | E3: Azioni | F3: Italia | G3: Banca | H3: Italia | I3: 11 | J3: EUR | K3: IT0005239360 | L3: UCG.MI | M3: #VALUE! | N3: 0.26 | O3: 45132 | P3: Milano | Q3: Fineco-C | R3: 22.418 | S3: 0 | T3: 0 | U3: 1 | W3: =(I3/IF(OR(D3="O",D3="CE"),100,1)*R3*(1+S3)+T3)*U3+V3 -> 246.598 | X3: Milano | Y3: Fineco-C | Z3: 45 | AA3: =SUMIF(Operazioni!A:A,A3,Operazioni!C:C) -> 0 | AB3: =INDEX(Valute!B:B,MATCH(J3,Valute!A:A,0)) -> 1 | AC3: =SUMIF(Operazioni!A:A,A3,Operazioni!K:K) -> 22.2148 | AD3: =((I3+AA3)/IF(OR(D3="O",D3="CE"),100,1)*Z3)*AB3+AC3 -> 517.2148 | AE3: =AD3-W3 -> 270.6168 | AF3: =IF(W3<>0,AE3/W3,"") -> 1.0974006 | AG3: 45691 | AH3: Milano | AI3: Fineco-C | AJ3: 45 | AL3: 2.95 | AM3: 1 | AO3: =AC3*(1-N3) -> 16.438952 | AP3: =((I3+AA3)/IF(OR(D3="O",D3="CE"),100,1)*AJ3*(1-AK3)-AL3)*AM3-AN3+AC3 -> 514.2648 | AQ3: =AP3-W3 -> 267.6668 | AR3: =IF(W3<>0,AQ3/W3,"") -> 1.0854378 | AS3: =(AQ3-AC3)*N3 -> 63.81752 | AT3: =IF(W3<>0,(AQ3-AS3)/W3,"") -> 0.82664612
A4: 15 | B4: 1 | C4: Poste Italiane | D4: A | E4: Azioni | F4: Italia | G4: Distribuzione | H4: Italia | I4: 25 | J4: EUR | K4: IT0003796171 | L4: PST.MI | M4: #VALUE! | N4: 0.26 | O4: 45133 | P4: Milano | Q4: Fineco-C | R4: 10.278 | S4: 0 | T4: 0 | U4: 1 | W4: =(I4/IF(OR(D4="O",D4="CE"),100,1)*R4*(1+S4)+T4)*U4+V4 -> 256.95 | X4: Milano | Y4: Fineco-C | Z4: {=_FV(M4,"Price",TRUE)} -> 25.39 | AA4: =SUMIF(Operazioni!A:A,A4,Operazioni!C:C) -> 0 | AB4: =INDEX(Valute!B:B,MATCH(J4,Valute!A:A,0)) -> 1 | AC4: =SUMIF(Operazioni!A:A,A4,Operazioni!K:K) -> 34.7874 | AD4: =((I4+AA4)/IF(OR(D4="O",D4="CE"),100,1)*Z4)*AB4+AC4 -> 669.5374 | AE4: =AD4-W4 -> 412.5874 | AF4: =IF(W4<>0,AE4/W4,"") -> 1.6057108 | AG4: 45992 | AH4: Milano | AI4: Fineco-C | AJ4: 20.56 | AL4: 2.95 | AM4: 1 | AO4: =AC4*(1-N4) -> 25.742676 | AP4: =((I4+AA4)/IF(OR(D4="O",D4="CE"),100,1)*AJ4*(1-AK4)-AL4)*AM4-AN4+AC4 -> 545.8374 | AQ4: =AP4-W4 -> 288.8874 | AR4: =IF(W4<>0,AQ4/W4,"") -> 1.1242942 | AS4: =(AQ4-AC4)*N4 -> 66.066 | AT4: =IF(W4<>0,(AQ4-AS4)/W4,"") -> 0.86717805
A5: 16 | B5: 1 | C5: STMicroElectronics | D5: A | E5: Azioni | F5: Italia | G5: Tecnologia | H5: Italia | I5: 5 | J5: EUR | K5: NL0000226223 | L5: STMMI.MI | M5: #VALUE! | N5: 0.26 | O5: 45132 | P5: Milano | Q5: Fineco-C | R5: 46.09 | S5: 0 | T5: 0 | U5: 1 | W5: =(I5/IF(OR(D5="O",D5="CE"),100,1)*R5*(1+S5)+T5)*U5+V5 -> 230.45 | X5: Milano | Y5: Fineco-C | Z5: 27.8 | AA5: =SUMIF(Operazioni!A:A,A5,Operazioni!C:C) -> 0 | AB5: =INDEX(Valute!B:B,MATCH(J5,Valute!A:A,0)) -> 1 | AC5: =SUMIF(Operazioni!A:A,A5,Operazioni!K:K) -> 0.7992 | AD5: =((I5+AA5)/IF(OR(D5="O",D5="CE"),100,1)*Z5)*AB5+AC5 -> 139.7992 | AE5: =AD5-W5 -> -90.6508 | AF5: =IF(W5<>0,AE5/W5,"") -> -0.39336429 | AG5: 45531 | AH5: Milano | AI5: Fineco-C | AJ5: 27.8 | AL5: 2.95 | AM5: 1 | AO5: =AC5*(1-N5) -> 0.591408 | AP5: =((I5+AA5)/IF(OR(D5="O",D5="CE"),100,1)*AJ5*(1-AK5)-AL5)*AM5-AN5+AC5 -> 136.8492 | AQ5: =AP5-W5 -> -93.6008 | AR5: =IF(W5<>0,AQ5/W5,"") -> -0.40616533 | AS5: =(AQ5-AC5)*N5 -> -24.544 | AT5: =IF(W5<>0,(AQ5-AS5)/W5,"") -> -0.29966066
A6: 17 | B6: 1 | C6: Intesa San Paolo | D6: A | E6: Azioni | F6: Italia | G6: Banca | H6: Italia | I6: 100 | J6: EUR | K6: IT0000072618 | L6: ISP.MI | M6: #VALUE! | N6: 0.26 | O6: 45132 | P6: Milano | Q6: Fineco-C | R6: 2.5545 | S6: 0 | T6: 0 | U6: 1 | W6: =(I6/IF(OR(D6="O",D6="CE"),100,1)*R6*(1+S6)+T6)*U6+V6 -> 255.45 | X6: Milano | Y6: Fineco-C | Z6: 5.109 | AA6: =SUMIF(Operazioni!A:A,A6,Operazioni!C:C) -> 0 | AB6: =INDEX(Valute!B:B,MATCH(J6,Valute!A:A,0)) -> 1 | AC6: =SUMIF(Operazioni!A:A,A6,Operazioni!K:K) -> 47.138 | AD6: =((I6+AA6)/IF(OR(D6="O",D6="CE"),100,1)*Z6)*AB6+AC6 -> 558.038 | AE6: =AD6-W6 -> 302.588 | AF6: =IF(W6<>0,AE6/W6,"") -> 1.1845293 | AG6: 45862 | AH6: Milano | AI6: Fineco-C | AJ6: 5.109 | AL6: 2.95 | AM6: 1 | AO6: =AC6*(1-N6) -> 34.88212 | AP6: =((I6+AA6)/IF(OR(D6="O",D6="CE"),100,1)*AJ6*(1-AK6)-AL6)*AM6-AN6+AC6 -> 555.088 | AQ6: =AP6-W6 -> 299.638 | AR6: =IF(W6<>0,AQ6/W6,"") -> 1.172981 | AS6: =(AQ6-AC6)*N6 -> 65.65 | AT6: =IF(W6<>0,(AQ6-AS6)/W6,"") -> 0.91598356
A7: 18 | B7: 1 | C7: Leonardo | D7: A | E7: Azioni | F7: Italia | G7: Industria | H7: Italia | I7: 21 | J7: EUR | K7: IT0003856405 | L7: LDO.MI | M7: #VALUE! | N7: 0.26 | O7: 45133 | P7: Milano | Q7: Fineco-C | R7: 11.64 | S7: 0 | T7: 0 | U7: 1 | W7: =(I7/IF(OR(D7="O",D7="CE"),100,1)*R7*(1+S7)+T7)*U7+V7 -> 244.44 | X7: Milano | Y7: Fineco-C | Z7: 23.95 | AA7: =SUMIF(Operazioni!A:A,A7,Operazioni!C:C) -> 0 | AB7: =INDEX(Valute!B:B,MATCH(J7,Valute!A:A,0)) -> 1 | AC7: =SUMIF(Operazioni!A:A,A7,Operazioni!K:K) -> 0 | AD7: =((I7+AA7)/IF(OR(D7="O",D7="CE"),100,1)*Z7)*AB7+AC7 -> 502.95 | AE7: =AD7-W7 -> 258.51 | AF7: =IF(W7<>0,AE7/W7,"") -> 1.0575601 | AG7: 45446 | AH7: Milano | AI7: Fineco-C | AJ7: 23.95 | AL7: 2.95 | AM7: 1 | AO7: =AC7*(1-N7) -> 0 | AP7: =((I7+AA7)/IF(OR(D7="O",D7="CE"),100,1)*AJ7*(1-AK7)-AL7)*AM7-AN7+AC7 -> 500 | AQ7: =AP7-W7 -> 255.56 | AR7: =IF(W7<>0,AQ7/W7,"") -> 1.0454917 | AS7: =(AQ7-AC7)*N7 -> 66.4456 | AT7: =IF(W7<>0,(AQ7-AS7)/W7,"") -> 0.77366388
A8: 19 | B8: 1 | C8: Enel | D8: A | E8: Azioni | F8: Italia | G8: Energia | H8: Italia | I8: 40 | J8: EUR | K8: IT0003128367 | L8: ENEL.MI | M8: #VALUE! | N8: 0.26 | O8: 45133 | P8: Milano | Q8: Fineco-C | R8: 6.313 | S8: 0 | T8: 0 | U8: 1 | W8: =(I8/IF(OR(D8="O",D8="CE"),100,1)*R8*(1+S8)+T8)*U8+V8 -> 252.52 | X8: Milano | Y8: Fineco-C | Z8: {=_FV(M8,"Price",TRUE)} -> 9.862 | AA8: =SUMIF(Operazioni!A:A,A8,Operazioni!C:C) -> 0 | AB8: =INDEX(Valute!B:B,MATCH(J8,Valute!A:A,0)) -> 1 | AC8: =SUMIF(Operazioni!A:A,A8,Operazioni!K:K) -> 34.632 | AD8: =((I8+AA8)/IF(OR(D8="O",D8="CE"),100,1)*Z8)*AB8+AC8 -> 429.112 | AE8: =AD8-W8 -> 176.592 | AF8: =IF(W8<>0,AE8/W8,"") -> 0.69931887 | AO8: =AC8*(1-N8) -> 25.62768 | AP8: =((I8+AA8)/IF(OR(D8="O",D8="CE"),100,1)*AJ8*(1-AK8)-AL8)*AM8-AN8+AC8 -> 34.632 | AQ8: =AP8-W8 -> -217.888 | AR8: =IF(W8<>0,AQ8/W8,"") -> -0.86285443 | AS8: =(AQ8-AC8)*N8 -> -65.6552 | AT8: =IF(W8<>0,(AQ8-AS8)/W8,"") -> -0.60285443
A9: 20 | B9: 1 | C9: Eni | D9: A | E9: Azioni | F9: Italia | G9: Energia | H9: Italia | I9: 19 | J9: EUR | K9: IT0003132476 | L9: ENI.MI | M9: #VALUE! | N9: 0.26 | O9: 45132 | P9: Milano | Q9: Fineco-C | R9: 13.947 | S9: 0 | T9: 0 | U9: 1 | W9: =(I9/IF(OR(D9="O",D9="CE"),100,1)*R9*(1+S9)+T9)*U9+V9 -> 264.993 | X9: Milano | Y9: Fineco-C | Z9: {=_FV(M9,"Price",TRUE)} -> 23.185 | AA9: =SUMIF(Operazioni!A:A,A9,Operazioni!C:C) -> 0 | AB9: =INDEX(Valute!B:B,MATCH(J9,Valute!A:A,0)) -> 1 | AC9: =SUMIF(Operazioni!A:A,A9,Operazioni!K:K) -> 39.035 | AD9: =((I9+AA9)/IF(OR(D9="O",D9="CE"),100,1)*Z9)*AB9+AC9 -> 479.55 | AE9: =AD9-W9 -> 214.557 | AF9: =IF(W9<>0,AE9/W9,"") -> 0.80967045 | AO9: =AC9*(1-N9) -> 28.8859 | AP9: =((I9+AA9)/IF(OR(D9="O",D9="CE"),100,1)*AJ9*(1-AK9)-AL9)*AM9-AN9+AC9 -> 39.035 | AQ9: =AP9-W9 -> -225.958 | AR9: =IF(W9<>0,AQ9/W9,"") -> -0.85269422 | AS9: =(AQ9-AC9)*N9 -> -68.89818 | AT9: =IF(W9<>0,(AQ9-AS9)/W9,"") -> -0.59269422
A10: 21 | B10: 1 | C10: Apple | D10: A | E10: Azioni | F10: US | G10: Tecnologia | H10: US | I10: 2 | J10: USD | K10: US0378331005 | L10: AAPL | M10: #VALUE! | N10: 0.26 | O10: 44498 | P10: Nasdaq | Q10: Fineco-C | R10: 155.27 | S10: 0.003 | T10: 0 | U10: 0.864 | V10: 12.95 | W10: =(I10/IF(OR(D10="O",D10="CE"),100,1)*R10*(1+S10)+T10)*U10+V10 -> 282.06148 | X10: Nasdaq | Y10: Fineco-C | Z10: {=_FV(M10,"Price",TRUE)} -> 308.82 | AA10: =SUMIF(Operazioni!A:A,A10,Operazioni!C:C) -> 0 | AB10: =INDEX(Valute!B:B,MATCH(J10,Valute!A:A,0)) -> 0.86002565 | AC10: =SUMIF(Operazioni!A:A,A10,Operazioni!K:K) -> 5.6018 | AD10: =((I10+AA10)/IF(OR(D10="O",D10="CE"),100,1)*Z10)*AB10+AC10 -> 536.78804 | AE10: =AD10-W10 -> 254.72656 | AF10: =IF(W10<>0,AE10/W10,"") -> 0.9030888 | AO10: =AC10*(1-N10) -> 4.145332 | AP10: =((I10+AA10)/IF(OR(D10="O",D10="CE"),100,1)*AJ10*(1-AK10)-AL10)*AM10-AN10+AC10 -> 5.6018 | AQ10: =AP10-W10 -> -276.45968 | AR10: =IF(W10<>0,AQ10/W10,"") -> -0.98013979 | AS10: =(AQ10-AC10)*N10 -> -73.335985 | AT10: =IF(W10<>0,(AQ10-AS10)/W10,"") -> -0.72013979
A11: 22 | B11: 1 | C11: Amazon | D11: A | E11: Azioni | F11: US | G11: Tecnologia | H11: US | I11: 2 | J11: USD | K11: US0231351067 | L11: AMZN | M11: #VALUE! | N11: 0.26 | O11: 45044 | P11: Nasdaq | Q11: Fineco-C | R11: 112.3447 | S11: 0.003 | T11: 0 | U11: 0.9089 | V11: 12.95 | W11: =(I11/IF(OR(D11="O",D11="CE"),100,1)*R11*(1+S11)+T11)*U11+V11 -> 217.78286 | X11: Nasdaq | Y11: Fineco-C | Z11: {=_FV(M11,"Price",TRUE)} -> 266.32 | AA11: =SUMIF(Operazioni!A:A,A11,Operazioni!C:C) -> 0 | AB11: =INDEX(Valute!B:B,MATCH(J11,Valute!A:A,0)) -> 0.86002565 | AC11: =SUMIF(Operazioni!A:A,A11,Operazioni!K:K) -> 0 | AD11: =((I11+AA11)/IF(OR(D11="O",D11="CE"),100,1)*Z11)*AB11+AC11 -> 458.08406 | AE11: =AD11-W11 -> 240.30121 | AF11: =IF(W11<>0,AE11/W11,"") -> 1.1033982 | AG11: 45992 | AH11: Nasdaq | AI11: Fineco | AJ11: 228.5254 | AL11: 10 | AM11: 0.8572 | AO11: =AC11*(1-N11) -> 0 | AP11: =((I11+AA11)/IF(OR(D11="O",D11="CE"),100,1)*AJ11*(1-AK11)-AL11)*AM11-AN11+AC11 -> 383.21195 | AQ11: =AP11-W11 -> 165.42909 | AR11: =IF(W11<>0,AQ11/W11,"") -> 0.75960566 | AS11: =(AQ11-AC11)*N11 -> 43.011563 | AT11: =IF(W11<>0,(AQ11-AS11)/W11,"") -> 0.56210819
A12: 32 | B12: 1 | C12: Microsoft | D12: A | E12: Azioni | F12: US | G12: Tecnologia | H12: US | I12: 10 | J12: USD | K12: US5949181045 | L12: MSFT | M12: #VALUE! | N12: 0.26 | O12: 42006 | P12: Nasdaq | Q12: Fineco-C | R12: 173.18 | S12: 0 | T12: 0 | U12: 1 | W12: =(I12/IF(OR(D12="O",D12="CE"),100,1)*R12*(1+S12)+T12)*U12+V12 -> 1731.8 | X12: Nasdaq | Y12: Fineco-C | Z12: 378.7 | AA12: =SUMIF(Operazioni!A:A,A12,Operazioni!C:C) -> 0 | AB12: =INDEX(Valute!B:B,MATCH(J12,Valute!A:A,0)) -> 0.86002565 | AC12: =SUMIF(Operazioni!A:A,A12,Operazioni!K:K) -> 0 | AD12: =((I12+AA12)/IF(OR(D12="O",D12="CE"),100,1)*Z12)*AB12+AC12 -> 3256.9171 | AE12: =AD12-W12 -> 1525.1171 | AF12: =IF(W12<>0,AE12/W12,"") -> 0.88065431 | AG12: 45301 | AH12: Nasdaq | AI12: Fineco-C | AJ12: 378.7 | AL12: 23.53 | AM12: 0.9116 | AO12: =AC12*(1-N12) -> 0 | AP12: =((I12+AA12)/IF(OR(D12="O",D12="CE"),100,1)*AJ12*(1-AK12)-AL12)*AM12-AN12+AC12 -> 3430.7793 | AQ12: =AP12-W12 -> 1698.9793 | AR12: =IF(W12<>0,AQ12/W12,"") -> 0.98104819 | AS12: =(AQ12-AC12)*N12 -> 441.73461 | AT12: =IF(W12<>0,(AQ12-AS12)/W12,"") -> 0.72597566
A13: 30 | B13: 1 | C13: Microsoft | D13: A | E13: Azioni | F13: US | G13: Tecnologia | H13: US | I13: 17 | J13: USD | K13: US5949181045 | L13: MSFT | M13: #VALUE! | N13: 0.26 | O13: 45279 | P13: Nasdaq | Q13: Fineco-C | R13: 173.18 | S13: 0 | T13: 0 | U13: 1 | W13: =(I13/IF(OR(D13="O",D13="CE"),100,1)*R13*(1+S13)+T13)*U13+V13 -> 2944.06 | X13: Nasdaq | Y13: Fineco-C | Z13: {=_FV(M13,"Price",TRUE)} -> 418.57 | AA13: =SUMIF(Operazioni!A:A,A13,Operazioni!C:C) -> 0 | AB13: =INDEX(Valute!B:B,MATCH(J13,Valute!A:A,0)) -> 0.86002565 | AC13: =SUMIF(Operazioni!A:A,A13,Operazioni!K:K) -> 0 | AD13: =((I13+AA13)/IF(OR(D13="O",D13="CE"),100,1)*Z13)*AB13+AC13 -> 6119.6759 | AE13: =AD13-W13 -> 3175.6159 | AF13: =IF(W13<>0,AE13/W13,"") -> 1.0786519 | AO13: =AC13*(1-N13) -> 0 | AP13: =((I13+AA13)/IF(OR(D13="O",D13="CE"),100,1)*AJ13*(1-AK13)-AL13)*AM13-AN13+AC13 -> 0 | AQ13: =AP13-W13 -> -2944.06 | AR13: =IF(W13<>0,AQ13/W13,"") -> -1 | AS13: =(AQ13-AC13)*N13 -> -765.4556 | AT13: =IF(W13<>0,(AQ13-AS13)/W13,"") -> -0.74
A14: 54 | B14: 1 | C14: Microsoft | D14: A | E14: Azioni | F14: US | G14: Tecnologia | H14: US | I14: 10 | J14: USD | K14: US5949181045 | L14: MSFT | M14: #VALUE! | N14: 0.26 | O14: 42006 | P14: Nasdaq | Q14: Fineco-C | R14: 173.18 | S14: 0 | T14: 0 | U14: 1 | W14: =(I14/IF(OR(D14="O",D14="CE"),100,1)*R14*(1+S14)+T14)*U14+V14 -> 1731.8 | X14: Nasdaq | Y14: Fineco-C | Z14: 454.6 | AA14: =SUMIF(Operazioni!A:A,A14,Operazioni!C:C) -> 0 | AB14: =INDEX(Valute!B:B,MATCH(J14,Valute!A:A,0)) -> 0.86002565 | AC14: =SUMIF(Operazioni!A:A,A14,Operazioni!K:K) -> 0 | AD14: =((I14+AA14)/IF(OR(D14="O",D14="CE"),100,1)*Z14)*AB14+AC14 -> 3909.6766 | AE14: =AD14-W14 -> 2177.8766 | AF14: =IF(W14<>0,AE14/W14,"") -> 1.2575797 | AG14: 45638 | AH14: Nasdaq | AI14: Fineco-C | AJ14: 454.6 | AL14: 27.28 | AM14: 0.9553 | AO14: =AC14*(1-N14) -> 0 | AP14: =((I14+AA14)/IF(OR(D14="O",D14="CE"),100,1)*AJ14*(1-AK14)-AL14)*AM14-AN14+AC14 -> 4316.7332 | AQ14: =AP14-W14 -> 2584.9332 | AR14: =IF(W14<>0,AQ14/W14,"") -> 1.492628 | AS14: =((AQ14-AC14)*N14)-240.53 -> 431.55264 | AT14: =IF(W14<>0,(AQ14-AS14)/W14,"") -> 1.2434349
A15: 23 | B15: 1 | C15: Microsoft | D15: A | E15: Azioni | F15: US | G15: Tecnologia | H15: US | I15: 49 | J15: USD | K15: US5949181045 | L15: MSFT | M15: #VALUE! | N15: 0.26 | O15: 42006 | P15: Nasdaq | Q15: Fineco-C | R15: 173.18 | S15: 0 | T15: 0 | U15: 1 | W15: =(I15/IF(OR(D15="O",D15="CE"),100,1)*R15*(1+S15)+T15)*U15+V15 -> 8485.82 | X15: Nasdaq | Y15: Fineco-C | Z15: {=_FV(M15,"Price",TRUE)} -> 418.57 | AA15: =SUMIF(Operazioni!A:A,A15,Operazioni!C:C) -> 0 | AB15: =INDEX(Valute!B:B,MATCH(J15,Valute!A:A,0)) -> 0.86002565 | AC15: =SUMIF(Operazioni!A:A,A15,Operazioni!K:K) -> 626.3878 | AD15: =((I15+AA15)/IF(OR(D15="O",D15="CE"),100,1)*Z15)*AB15+AC15 -> 18265.454 | AE15: =AD15-W15 -> 9779.6337 | AF15: =IF(W15<>0,AE15/W15,"") -> 1.1524677 | AO15: =AC15*(1-N15) -> 463.52697 | AP15: =((I15+AA15)/IF(OR(D15="O",D15="CE"),100,1)*AJ15*(1-AK15)-AL15)*AM15-AN15+AC15 -> 626.3878 | AQ15: =AP15-W15 -> -7859.4322 | AR15: =IF(W15<>0,AQ15/W15,"") -> -0.92618418 | AS15: =(AQ15-AC15)*N15 -> -2206.3132 | AT15: =IF(W15<>0,(AQ15-AS15)/W15,"") -> -0.66618418
A16: 82 | B16: 1 | C16: Microsoft | D16: A | E16: Azioni | F16: US | G16: Tecnologia | H16: US | I16: 17 | J16: USD | K16: US5949181045 | L16: MSFT | M16: #VALUE! | N16: 0.26 | O16: 42359 | P16: Nasdaq | Q16: Fineco | R16: 399.122 | S16: 0 | T16: 0 | U16: 1 | W16: =(I16/IF(OR(D16="O",D16="CE"),100,1)*R16*(1+S16)+T16)*U16+V16 -> 6785.074 | X16: Nasdaq | Y16: Fineco | Z16: {=_FV(M16,"Price",TRUE)} -> 418.57 | AA16: =SUMIF(Operazioni!A:A,A16,Operazioni!C:C) -> 0 | AB16: =INDEX(Valute!B:B,MATCH(J16,Valute!A:A,0)) -> 0.86002565 | AC16: =SUMIF(Operazioni!A:A,A16,Operazioni!K:K) -> 0 | AD16: =((I16+AA16)/IF(OR(D16="O",D16="CE"),100,1)*Z16)*AB16+AC16 -> 6119.6759 | AE16: =AD16-W16 -> -665.39808 | AF16: =IF(W16<>0,AE16/W16,"") -> -0.098067918
A17: 56 | B17: 1 | C17: Microsoft | D17: A | E17: Azioni | F17: US | G17: Tecnologia | H17: US | I17: 17 | J17: USD | K17: US5949181045 | L17: MSFT | M17: #VALUE! | N17: 0.26 | O17: 45667 | P17: Nasdaq | Q17: Fineco | R17: 399.122 | S17: 0 | T17: 0 | U17: 1 | W17: =(I17/IF(OR(D17="O",D17="CE"),100,1)*R17*(1+S17)+T17)*U17+V17 -> 6785.074 | X17: Nasdaq | Y17: Fineco | Z17: {=_FV(M17,"Price",TRUE)} -> 418.57 | AA17: =SUMIF(Operazioni!A:A,A17,Operazioni!C:C) -> 0 | AB17: =INDEX(Valute!B:B,MATCH(J17,Valute!A:A,0)) -> 0.86002565 | AC17: =SUMIF(Operazioni!A:A,A17,Operazioni!K:K) -> 0 | AD17: =((I17+AA17)/IF(OR(D17="O",D17="CE"),100,1)*Z17)*AB17+AC17 -> 6119.6759 | AE17: =AD17-W17 -> -665.39808 | AF17: =IF(W17<>0,AE17/W17,"") -> -0.098067918
A18: 1 | B18: 1 | C18: iShares Core MSCI World UCITS ETF USD (Acc) | D18: ETF | E18: Azioni | F18: Mondo Sviluppato | H18: iShares | I18: 10 | J18: EUR | K18: IE00B4L5Y983 | L18: SWDA.MI | M18: #VALUE! | N18: 0.26 | O18: 45096 | P18: Milano | Q18: Fineco-C | R18: 76.88 | S18: 0 | T18: 0 | U18: 1 | W18: =(I18/IF(OR(D18="O",D18="CE"),100,1)*R18*(1+S18)+T18)*U18+V18 -> 768.8 | X18: Milano | Y18: Fineco-C | Z18: {=_FV(M18,"Price",TRUE)} -> 123.26 | AA18: =SUMIF(Operazioni!A:A,A18,Operazioni!C:C) -> 0 | AB18: =INDEX(Valute!B:B,MATCH(J18,Valute!A:A,0)) -> 1 | AC18: =SUMIF(Operazioni!A:A,A18,Operazioni!K:K) -> 0 | AD18: =((I18+AA18)/IF(OR(D18="O",D18="CE"),100,1)*Z18)*AB18+AC18 -> 1232.6 | AE18: =AD18-W18 -> 463.8 | AF18: =IF(W18<>0,AE18/W18,"") -> 0.60327784 | AO18: =AC18*(1-N18) -> 0 | AP18: =((I18+AA18)/IF(OR(D18="O",D18="CE"),100,1)*AJ18*(1-AK18)-AL18)*AM18-AN18+AC18 -> 0 | AQ18: =AP18-W18 -> -768.8 | AR18: =IF(W18<>0,AQ18/W18,"") -> -1 | AS18: =(AQ18-AC18)*N18 -> -199.888 | AT18: =IF(W18<>0,(AQ18-AS18)/W18,"") -> -0.74
A19: 2 | B19: 1 | C19: iShares Core MSCI World UCITS ETF USD (Acc) | D19: ETF | E19: Azioni | F19: Mondo Sviluppato | H19: iShares | I19: 3 | J19: EUR | K19: IE00B4L5Y983 | L19: SWDA.MI | M19: #VALUE! | N19: 0.26 | O19: 45131 | P19: Milano | Q19: Fineco-C | R19: 77.38 | S19: 0 | T19: 0 | U19: 1 | W19: =(I19/IF(OR(D19="O",D19="CE"),100,1)*R19*(1+S19)+T19)*U19+V19 -> 232.14 | X19: Milano | Y19: Fineco-C | Z19: {=_FV(M19,"Price",TRUE)} -> 123.26 | AA19: =SUMIF(Operazioni!A:A,A19,Operazioni!C:C) -> 0 | AB19: =INDEX(Valute!B:B,MATCH(J19,Valute!A:A,0)) -> 1 | AC19: =SUMIF(Operazioni!A:A,A19,Operazioni!K:K) -> 0 | AD19: =((I19+AA19)/IF(OR(D19="O",D19="CE"),100,1)*Z19)*AB19+AC19 -> 369.78 | AE19: =AD19-W19 -> 137.64 | AF19: =IF(W19<>0,AE19/W19,"") -> 0.59291807 | AO19: =AC19*(1-N19) -> 0 | AP19: =((I19+AA19)/IF(OR(D19="O",D19="CE"),100,1)*AJ19*(1-AK19)-AL19)*AM19-AN19+AC19 -> 0 | AQ19: =AP19-W19 -> -232.14 | AR19: =IF(W19<>0,AQ19/W19,"") -> -1 | AS19: =(AQ19-AC19)*N19 -> -60.3564 | AT19: =IF(W19<>0,(AQ19-AS19)/W19,"") -> -0.74
A20: 3 | B20: 1 | C20: Vanguard FTSE Emerging Markets UCITS ETF (USD) Dis | D20: ETF | E20: Azioni | F20: Paesi Emergenti | H20: Vanguard | I20: 10 | J20: EUR | K20: IE00B3VVMM84 | L20: VFEM.MI | M20: #VALUE! | N20: 0.26 | O20: 45096 | P20: Milano | Q20: Fineco-C | R20: 51.31 | S20: 0 | T20: 0 | U20: 1 | V20: 2.95 | W20: =(I20/IF(OR(D20="O",D20="CE"),100,1)*R20*(1+S20)+T20)*U20+V20 -> 516.05 | X20: Milano | Y20: Fineco-C | Z20: {=_FV(M20,"Price",TRUE)} -> 70.96 | AA20: =SUMIF(Operazioni!A:A,A20,Operazioni!C:C) -> 0 | AB20: =INDEX(Valute!B:B,MATCH(J20,Valute!A:A,0)) -> 1 | AC20: =SUMIF(Operazioni!A:A,A20,Operazioni!K:K) -> 24.938 | AD20: =((I20+AA20)/IF(OR(D20="O",D20="CE"),100,1)*Z20)*AB20+AC20 -> 734.538 | AE20: =AD20-W20 -> 218.488 | AF20: =IF(W20<>0,AE20/W20,"") -> 0.42338533 | AG20: 45992 | AH20: Milano | AI20: Fineco-C | AJ20: 63.96 | AL20: 2.95 | AM20: 1 | AO20: =AC20*(1-N20) -> 18.45412 | AP20: =((I20+AA20)/IF(OR(D20="O",D20="CE"),100,1)*AJ20*(1-AK20)-AL20)*AM20-AN20+AC20 -> 661.588 | AQ20: =AP20-W20 -> 145.538 | AR20: =IF(W20<>0,AQ20/W20,"") -> 0.28202306 | AS20: =(AQ20-AC20)*N20 -> 31.356 | AT20: =IF(W20<>0,(AQ20-AS20)/W20,"") -> 0.22126151
A21: 4 | B21: 1 | C21: iShares Global Clean Energy UCITS ETF USD (Dist) | D21: ETF | E21: Azioni | F21: Mondo | G21: Energia | H21: iShares | I21: 50 | J21: EUR | K21: IE00B1XNHC34 | L21: INRG.MI | M21: #VALUE! | N21: 0.26 | O21: 45112 | P21: Milano | Q21: Fineco-C | R21: 9.635 | S21: 0 | T21: 0 | U21: 1 | V21: 2.95 | W21: =(I21/IF(OR(D21="O",D21="CE"),100,1)*R21*(1+S21)+T21)*U21+V21 -> 484.7 | X21: Milano | Y21: Fineco-C | Z21: 7.4341 | AA21: =SUMIF(Operazioni!A:A,A21,Operazioni!C:C) -> 0 | AB21: =INDEX(Valute!B:B,MATCH(J21,Valute!A:A,0)) -> 1 | AC21: =SUMIF(Operazioni!A:A,A21,Operazioni!K:K) -> 2.3532 | AD21: =((I21+AA21)/IF(OR(D21="O",D21="CE"),100,1)*Z21)*AB21+AC21 -> 374.0582 | AE21: =AD21-W21 -> -110.6418 | AF21: =IF(W21<>0,AE21/W21,"") -> -0.22826862 | AG21: 45531 | AH21: Milano | AI21: Fineco-C | AJ21: 7.43412 | AK21: 0.0072 | AL21: 2.95 | AM21: 1 | AO21: =AC21*(1-N21) -> 1.741368 | AP21: =((I21+AA21)/IF(OR(D21="O",D21="CE"),100,1)*AJ21*(1-AK21)-AL21)*AM21-AN21+AC21 -> 368.43292 | AQ21: =AP21-W21 -> -116.26708 | AR21: =IF(W21<>0,AQ21/W21,"") -> -0.23987432 | AS21: =(AQ21-AC21)*N21 -> -30.841274 | AT21: =IF(W21<>0,(AQ21-AS21)/W21,"") -> -0.17624471
A22: 5 | B22: 1 | C22: iShares Core S&P 500 UCITS ETF USD (Dist) | D22: ETF | E22: Azioni | F22: US | H22: iShares | I22: 10 | J22: EUR | K22: IE0031442068 | L22: IUSA.MI | M22: #VALUE! | N22: 0.26 | O22: 45112 | P22: Milano | Q22: Fineco-C | R22: 40.63 | S22: 0 | T22: 0 | U22: 1 | V22: 2.95 | W22: =(I22/IF(OR(D22="O",D22="CE"),100,1)*R22*(1+S22)+T22)*U22+V22 -> 409.25 | X22: Milano | Y22: Fineco-C | Z22: {=_FV(M22,"Price",TRUE)} -> 64.45 | AA22: =SUMIF(Operazioni!A:A,A22,Operazioni!C:C) -> 0 | AB22: =INDEX(Valute!B:B,MATCH(J22,Valute!A:A,0)) -> 1 | AC22: =SUMIF(Operazioni!A:A,A22,Operazioni!K:K) -> 14.07332 | AD22: =((I22+AA22)/IF(OR(D22="O",D22="CE"),100,1)*Z22)*AB22+AC22 -> 658.57332 | AE22: =AD22-W22 -> 249.32332 | AF22: =IF(W22<>0,AE22/W22,"") -> 0.60922009 | AG22: 45992 | AH22: Milano | AI22: Fineco-C | AJ22: 58.51 | AL22: 2.95 | AM22: 1 | AO22: =AC22*(1-N22) -> 10.414257 | AP22: =((I22+AA22)/IF(OR(D22="O",D22="CE"),100,1)*AJ22*(1-AK22)-AL22)*AM22-AN22+AC22 -> 596.22332 | AQ22: =AP22-W22 -> 186.97332 | AR22: =IF(W22<>0,AQ22/W22,"") -> 0.45686822 | AS22: =(AQ22-AC22)*N22 -> 44.954 | AT22: =IF(W22<>0,(AQ22-AS22)/W22,"") -> 0.34702338
A23: 6 | B23: 1 | C23: iShares Core S&P 500 UCITS ETF USD (Dist) | D23: ETF | E23: Azioni | F23: US | H23: iShares | I23: 15 | J23: EUR | K23: IE0031442068 | L23: IUSA.MI | M23: #VALUE! | N23: 0.26 | O23: 45128 | P23: Milano | Q23: Fineco-C | R23: 40.7 | S23: 0 | T23: 0 | U23: 1 | V23: 2.95 | W23: =(I23/IF(OR(D23="O",D23="CE"),100,1)*R23*(1+S23)+T23)*U23+V23 -> 613.45 | X23: Milano | Y23: Fineco-C | Z23: {=_FV(M23,"Price",TRUE)} -> 64.45 | AA23: =SUMIF(Operazioni!A:A,A23,Operazioni!C:C) -> 0 | AB23: =INDEX(Valute!B:B,MATCH(J23,Valute!A:A,0)) -> 1 | AC23: =SUMIF(Operazioni!A:A,A23,Operazioni!K:K) -> 9.02948 | AD23: =((I23+AA23)/IF(OR(D23="O",D23="CE"),100,1)*Z23)*AB23+AC23 -> 975.77948 | AE23: =AD23-W23 -> 362.32948 | AF23: =IF(W23<>0,AE23/W23,"") -> 0.59064224 | AG23: 45992 | AH23: Milano | AI23: Fineco-C | AJ23: 58.51 | AL23: 2.95 | AM23: 1 | AO23: =AC23*(1-N23) -> 6.6818152 | AP23: =((I23+AA23)/IF(OR(D23="O",D23="CE"),100,1)*AJ23*(1-AK23)-AL23)*AM23-AN23+AC23 -> 883.72948 | AQ23: =AP23-W23 -> 270.27948 | AR23: =IF(W23<>0,AQ23/W23,"") -> 0.44058926 | AS23: =(AQ23-AC23)*N23 -> 67.925 | AT23: =IF(W23<>0,(AQ23-AS23)/W23,"") -> 0.32986304
A24: 7 | B24: 1 | C24: Amundi MSCI Semiconductors ESG Screened UCITS ETF Acc | D24: ETF | E24: Azioni | F24: Mondo | G24: Tecnologia | H24: Amundi | I24: 20 | J24: EUR | K24: LU1900066033 | L24: CHIP.MI | M24: #VALUE! | N24: 0.26 | O24: 45124 | P24: Milano | Q24: Fineco-C | R24: 28.41 | S24: 0 | T24: 0 | U24: 1 | W24: =(I24/IF(OR(D24="O",D24="CE"),100,1)*R24*(1+S24)+T24)*U24+V24 -> 568.2 | X24: Milano | Y24: Fineco-C | Z24: 57 | AA24: =SUMIF(Operazioni!A:A,A24,Operazioni!C:C) -> 0 | AB24: =INDEX(Valute!B:B,MATCH(J24,Valute!A:A,0)) -> 1 | AC24: =SUMIF(Operazioni!A:A,A24,Operazioni!K:K) -> 0 | AD24: =((I24+AA24)/IF(OR(D24="O",D24="CE"),100,1)*Z24)*AB24+AC24 -> 1140 | AE24: =AD24-W24 -> 571.8 | AF24: =IF(W24<>0,AE24/W24,"") -> 1.0063358 | AG24: 45663 | AH24: Milano | AI24: Fineco-C | AJ24: 57 | AL24: 2.95 | AM24: 1 | AO24: =AC24*(1-N24) -> 0 | AP24: =((I24+AA24)/IF(OR(D24="O",D24="CE"),100,1)*AJ24*(1-AK24)-AL24)*AM24-AN24+AC24 -> 1137.05 | AQ24: =AP24-W24 -> 568.85 | AR24: =IF(W24<>0,AQ24/W24,"") -> 1.001144 | AS24: =(AQ24-AC24)*N24 -> 147.901 | AT24: =IF(W24<>0,(AQ24-AS24)/W24,"") -> 0.74084653
A25: 8 | B25: 1 | C25: Xtrackers Artif. Int. and Big Data UCITS ETF 1C | D25: ETF | E25: Azioni | F25: US | G25: Tecnologia | H25: Xtrackers | I25: 6 | J25: EUR | K25: IE00BGV5VN51 | L25: XAIX.MI | M25: #VALUE! | N25: 0.26 | O25: 45128 | P25: Milano | Q25: Fineco-C | R25: 87 | S25: 0 | T25: 0 | U25: 1 | V25: 2.95 | W25: =(I25/IF(OR(D25="O",D25="CE"),100,1)*R25*(1+S25)+T25)*U25+V25 -> 524.95 | X25: Milano | Y25: Fineco-C | Z25: {=_FV(M25,"Price",TRUE)} -> 200.84 | AA25: =SUMIF(Operazioni!A:A,A25,Operazioni!C:C) -> 0 | AB25: =INDEX(Valute!B:B,MATCH(J25,Valute!A:A,0)) -> 1 | AC25: =SUMIF(Operazioni!A:A,A25,Operazioni!K:K) -> 0 | AD25: =((I25+AA25)/IF(OR(D25="O",D25="CE"),100,1)*Z25)*AB25+AC25 -> 1205.04 | AE25: =AD25-W25 -> 680.09 | AF25: =IF(W25<>0,AE25/W25,"") -> 1.2955329 | AG25: 46156 | AH25: Milano | AI25: Fineco-C | AJ25: 193.7 | AL25: 2.95 | AM25: 1 | AO25: =AC25*(1-N25) -> 0 | AP25: =((I25+AA25)/IF(OR(D25="O",D25="CE"),100,1)*AJ25*(1-AK25)-AL25)*AM25-AN25+AC25 -> 1159.25 | AQ25: =AP25-W25 -> 634.3 | AR25: =IF(W25<>0,AQ25/W25,"") -> 1.2083056 | AS25: =(AQ25-AC25)*N25 -> 164.918 | AT25: =IF(W25<>0,(AQ25-AS25)/W25,"") -> 0.89414611
A26: 9 | B26: 1 | C26: iShares Core MSCI Europe UCITS ETF EUR (Acc) | D26: ETF | E26: Azioni | F26: EU | H26: iShares | I26: 14 | J26: EUR | K26: IE00B4K48X80 | L26: SMEA.MI | M26: #VALUE! | N26: 0.26 | O26: 45128 | P26: Milano | Q26: Fineco-C | R26: 69.25 | S26: 0 | T26: 0 | U26: 1 | V26: 2.95 | W26: =(I26/IF(OR(D26="O",D26="CE"),100,1)*R26*(1+S26)+T26)*U26+V26 -> 972.45 | X26: Milano | Y26: Fineco-C | Z26: {=_FV(M26,"Price",TRUE)} -> 101.64 | AA26: =SUMIF(Operazioni!A:A,A26,Operazioni!C:C) -> 0 | AB26: =INDEX(Valute!B:B,MATCH(J26,Valute!A:A,0)) -> 1 | AC26: =SUMIF(Operazioni!A:A,A26,Operazioni!K:K) -> 0 | AD26: =((I26+AA26)/IF(OR(D26="O",D26="CE"),100,1)*Z26)*AB26+AC26 -> 1422.96 | AE26: =AD26-W26 -> 450.51 | AF26: =IF(W26<>0,AE26/W26,"") -> 0.46327318 | AO26: =AC26*(1-N26) -> 0 | AP26: =((I26+AA26)/IF(OR(D26="O",D26="CE"),100,1)*AJ26*(1-AK26)-AL26)*AM26-AN26+AC26 -> 0 | AQ26: =AP26-W26 -> -972.45 | AR26: =IF(W26<>0,AQ26/W26,"") -> -1 | AS26: =(AQ26-AC26)*N26 -> -252.837 | AT26: =IF(W26<>0,(AQ26-AS26)/W26,"") -> -0.74
A27: 24 | B27: 1 | C27: Vanguard FTSE All-World UCITS ETF (USD) Acc | D27: ETF | E27: Azioni | F27: Mondo | H27: Vanguard | I27: 10 | J27: EUR | K27: IE00BK5BQT80 | L27: VWCE.MI | M27: #VALUE! | N27: 0.26 | O27: 45161 | P27: Milano | Q27: Fineco-C | R27: 100.5 | S27: 0 | T27: 0 | U27: 1 | V27: 2.95 | W27: =(I27/IF(OR(D27="O",D27="CE"),100,1)*R27*(1+S27)+T27)*U27+V27 -> 1007.95 | X27: Milano | Y27: Fineco-C | Z27: {=_FV(M27,"Price",TRUE)} -> 162.56 | AA27: =SUMIF(Operazioni!A:A,A27,Operazioni!C:C) -> 0 | AB27: =INDEX(Valute!B:B,MATCH(J27,Valute!A:A,0)) -> 1 | AC27: =SUMIF(Operazioni!A:A,A27,Operazioni!K:K) -> 0 | AD27: =((I27+AA27)/IF(OR(D27="O",D27="CE"),100,1)*Z27)*AB27+AC27 -> 1625.6 | AE27: =AD27-W27 -> 617.65 | AF27: =IF(W27<>0,AE27/W27,"") -> 0.61277841 | AO27: =AC27*(1-N27) -> 0 | AP27: =((I27+AA27)/IF(OR(D27="O",D27="CE"),100,1)*AJ27*(1-AK27)-AL27)*AM27-AN27+AC27 -> 0 | AQ27: =AP27-W27 -> -1007.95 | AR27: =IF(W27<>0,AQ27/W27,"") -> -1 | AS27: =(AQ27-AC27)*N27 -> -262.067 | AT27: =IF(W27<>0,(AQ27-AS27)/W27,"") -> -0.74
A28: 27 | B28: 1 | C28: Vanguard FTSE All-World UCITS ETF (USD) Acc | D28: ETF | E28: Azioni | F28: Mondo | H28: Vanguard | I28: 60 | J28: EUR | K28: IE00BK5BQT80 | L28: VWCE.MI | M28: #VALUE! | N28: 0.26 | O28: 45162 | P28: Milano | Q28: Fineco-C | R28: 101.3 | S28: 0.0019 | T28: 0 | U28: 1 | V28: 2.95 | W28: =(I28/IF(OR(D28="O",D28="CE"),100,1)*R28*(1+S28)+T28)*U28+V28 -> 6092.4982 | X28: Milano | Y28: Fineco-C | Z28: {=_FV(M28,"Price")} -> 162.56 | AA28: =SUMIF(Operazioni!A:A,A28,Operazioni!C:C) -> 0 | AB28: =INDEX(Valute!B:B,MATCH(J28,Valute!A:A,0)) -> 1 | AC28: =SUMIF(Operazioni!A:A,A28,Operazioni!K:K) -> 0 | AD28: =((I28+AA28)/IF(OR(D28="O",D28="CE"),100,1)*Z28)*AB28+AC28 -> 9753.6 | AE28: =AD28-W28 -> 3661.1018 | AF28: =IF(W28<>0,AE28/W28,"") -> 0.60091964 | AO28: =AC28*(1-N28) -> 0 | AP28: =((I28+AA28)/IF(OR(D28="O",D28="CE"),100,1)*AJ28*(1-AK28)-AL28)*AM28-AN28+AC28 -> 0 | AQ28: =AP28-W28 -> -6092.4982 | AR28: =IF(W28<>0,AQ28/W28,"") -> -1 | AS28: =(AQ28-AC28)*N28 -> -1584.0495 | AT28: =IF(W28<>0,(AQ28-AS28)/W28,"") -> -0.74
A29: 28 | B29: 1 | C29: Vanguard FTSE All-World UCITS ETF (USD) Acc | D29: ETF | E29: Azioni | F29: Mondo | H29: Vanguard | I29: 30 | J29: EUR | K29: IE00BK5BQT80 | L29: VWCE.MI | M29: #VALUE! | N29: 0.26 | O29: 45163 | P29: Milano | Q29: Fineco-C | R29: 100.5 | S29: 0.0019 | T29: 0 | U29: 1 | V29: 2.95 | W29: =(I29/IF(OR(D29="O",D29="CE"),100,1)*R29*(1+S29)+T29)*U29+V29 -> 3023.6785 | X29: Milano | Y29: Fineco-C | Z29: {=_FV(M29,"Price")} -> 162.56 | AA29: =SUMIF(Operazioni!A:A,A29,Operazioni!C:C) -> 0 | AB29: =INDEX(Valute!B:B,MATCH(J29,Valute!A:A,0)) -> 1 | AC29: =SUMIF(Operazioni!A:A,A29,Operazioni!K:K) -> 0 | AD29: =((I29+AA29)/IF(OR(D29="O",D29="CE"),100,1)*Z29)*AB29+AC29 -> 4876.8 | AE29: =AD29-W29 -> 1853.1215 | AF29: =IF(W29<>0,AE29/W29,"") -> 0.61286989 | AO29: =AC29*(1-N29) -> 0 | AP29: =((I29+AA29)/IF(OR(D29="O",D29="CE"),100,1)*AJ29*(1-AK29)-AL29)*AM29-AN29+AC29 -> 0 | AQ29: =AP29-W29 -> -3023.6785 | AR29: =IF(W29<>0,AQ29/W29,"") -> -1 | AS29: =(AQ29-AC29)*N29 -> -786.15641 | AT29: =IF(W29<>0,(AQ29-AS29)/W29,"") -> -0.74
A30: 32 | B30: 1 | C30: Vanguard FTSE All-World UCITS ETF (USD) Acc | D30: ETF | E30: Azioni | F30: Mondo | H30: Vanguard | I30: 20 | J30: EUR | K30: IE00BK5BQT80 | L30: VWCE.MI | M30: #VALUE! | N30: 0.26 | O30: 45302 | P30: Milano | Q30: Fineco | R30: 107.14 | S30: 0 | T30: 0 | U30: 1 | V30: 19 | W30: =(I30/IF(OR(D30="O",D30="CE"),100,1)*R30*(1+S30)+T30)*U30+V30 -> 2161.8 | X30: Milano | Y30: Fineco | Z30: {=_FV(M30,"Price",TRUE)} -> 162.56 | AA30: =SUMIF(Operazioni!A:A,A30,Operazioni!C:C) -> 0 | AB30: =INDEX(Valute!B:B,MATCH(J30,Valute!A:A,0)) -> 1 | AC30: =SUMIF(Operazioni!A:A,A30,Operazioni!K:K) -> 0 | AD30: =((I30+AA30)/IF(OR(D30="O",D30="CE"),100,1)*Z30)*AB30+AC30 -> 3251.2 | AE30: =AD30-W30 -> 1089.4 | AF30: =IF(W30<>0,AE30/W30,"") -> 0.50393191 | AO30: =AC30*(1-N30) -> 0 | AP30: =((I30+AA30)/IF(OR(D30="O",D30="CE"),100,1)*AJ30*(1-AK30)-AL30)*AM30-AN30+AC30 -> 0 | AQ30: =AP30-W30 -> -2161.8 | AR30: =IF(W30<>0,AQ30/W30,"") -> -1 | AS30: =(AQ30-AC30)*N30 -> -562.068 | AT30: =IF(W30<>0,(AQ30-AS30)/W30,"") -> -0.74
A31: 10 | B31: 1 | C31: BTP-VAL 13GN27SU CUM | D31: O | E31: Obblig | F31: Italia | G31: Governativo | H31: Italia | I31: 10000 | J31: EUR | K31: IT0005547408 | N31: 0.125 | O31: 45083 | P31: MOT | Q31: Fineco-C | R31: 100 | S31: 0 | T31: 0 | U31: 1 | W31: =(I31/IF(OR(D31="O",D31="CE"),100,1)*R31*(1+S31)+T31)*U31+V31 -> 10000 | X31: MOT | Y31: Fineco-C | Z31: 100 | AA31: =SUMIF(Operazioni!A:A,A31,Operazioni!C:C) -> 0 | AB31: =INDEX(Valute!B:B,MATCH(J31,Valute!A:A,0)) -> 1 | AC31: =SUMIF(Operazioni!A:A,A31,Operazioni!K:K) -> 743.75 | AD31: =((I31+AA31)/IF(OR(D31="O",D31="CE"),100,1)*Z31)*AB31+AC31 -> 10743.75 | AE31: =AD31-W31 -> 743.75002 | AF31: =IF(W31<>0,AE31/W31,"") -> 0.074375002 | AO31: =AC31*(1-N31) -> 650.78125 | AP31: =((I31+AA31)/IF(OR(D31="O",D31="CE"),100,1)*AJ31*(1-AK31)-AL31)*AM31-AN31+AC31 -> 743.75 | AQ31: =AP31-W31 -> -9256.25 | AR31: =IF(W31<>0,AQ31/W31,"") -> -0.925625 | AS31: =(AQ31-AC31)*N31 -> -1250 | AT31: =IF(W31<>0,(AQ31-AS31)/W31,"") -> -0.800625
A32: 11 | B32: 1 | C32: USA-15FB26 6 | D32: O | E32: Obblig | F32: US | G32: Governativo | H32: US | I32: 5000 | J32: USD | K32: US912810EW46 | N32: 0.125 | O32: 45128 | P32: ETLX | Q32: Fineco-C | R32: 103.39 | S32: 0.005 | T32: 0 | U32: 0.9017 | V32: 82.57 | W32: =(I32/IF(OR(D32="O",D32="CE"),100,1)*R32*(1+S32)+T32)*U32+V32 -> 4767.2148 | X32: ETLX | Y32: Fineco-C | Z32: 100 | AA32: =SUMIF(Operazioni!A:A,A32,Operazioni!C:C) -> 0 | AB32: =INDEX(Valute!B:B,MATCH(J32,Valute!A:A,0)) -> 0.86002565 | AC32: =SUMIF(Operazioni!A:A,A32,Operazioni!K:K) -> 710.55323 | AD32: =((I32+AA32)/IF(OR(D32="O",D32="CE"),100,1)*Z32)*AB32+AC32 -> 5010.6815 | AE32: =AD32-W32 -> 243.46664 | AF32: =IF(W32<>0,AE32/W32,"") -> 0.051071043 | AG32: 46070 | AH32: Milano | AI32: Fineco-C | AJ32: 100 | AM32: 0.8437 | AO32: =AC32*(1-N32) -> 621.73407 | AP32: =((I32+AA32)/IF(OR(D32="O",D32="CE"),100,1)*AJ32*(1-AK32)-AL32)*AM32-AN32+AC32 -> 4929.0532 | AQ32: =AP32-W32 -> 161.83839 | AR32: =IF(W32<>0,AQ32/W32,"") -> 0.033948205 | AS32: =(AQ32-AC32)*N32 -> -68.589355 | AT32: =IF(W32<>0,(AQ32-AS32)/W32,"") -> 0.048335925
A33: 12 | B33: 1 | C33: BTP-1OT53 4,5 | D33: O | E33: Obblig | F33: Italia | G33: Governativo | H33: Italia | I33: 5000 | J33: EUR | K33: IT0005534141 | N33: 0.125 | O33: 45128 | P33: MOT | Q33: Fineco-C | R33: 100.67 | S33: 0.0019 | T33: 0 | U33: 1 | V33: 61.82 | W33: =(I33/IF(OR(D33="O",D33="CE"),100,1)*R33*(1+S33)+T33)*U33+V33 -> 5104.8836 | X33: MOT | Y33: Fineco-C | Z33: 100 | AA33: =SUMIF(Operazioni!A:A,A33,Operazioni!C:C) -> 0 | AB33: =INDEX(Valute!B:B,MATCH(J33,Valute!A:A,0)) -> 1 | AC33: =SUMIF(Operazioni!A:A,A33,Operazioni!K:K) -> 590.625 | AD33: =((I33+AA33)/IF(OR(D33="O",D33="CE"),100,1)*Z33)*AB33+AC33 -> 5590.625 | AE33: =AD33-W33 -> 485.74136 | AF33: =IF(W33<>0,AE33/W33,"") -> 0.095152288 | AO33: =AC33*(1-N33) -> 516.79688 | AP33: =((I33+AA33)/IF(OR(D33="O",D33="CE"),100,1)*AJ33*(1-AK33)-AL33)*AM33-AN33+AC33 -> 590.625 | AQ33: =AP33-W33 -> -4514.2586 | AR33: =IF(W33<>0,AQ33/W33,"") -> -0.88430197 | AS33: =(AQ33-AC33)*N33 -> -638.11046 | AT33: =IF(W33<>0,(AQ33-AS33)/W33,"") -> -0.75930197
A34: 25 | B34: 1 | C34: BTP-29ST25 3,60 | D34: O | E34: Obblig | F34: Italia | G34: Governativo | H34: Italia | I34: 5000 | J34: EUR | K34: IT0005557084 | N34: 0.125 | O34: 45161 | P34: MOT | Q34: Fineco-C | R34: 99.99 | S34: 0.0019 | T34: 0 | U34: 1 | V34: 12.39 | W34: =(I34/IF(OR(D34="O",D34="CE"),100,1)*R34*(1+S34)+T34)*U34+V34 -> 5021.3891 | X34: MOT | Y34: Fineco-C | Z34: 100 | AA34: =SUMIF(Operazioni!A:A,A34,Operazioni!C:C) -> 0 | AB34: =INDEX(Valute!B:B,MATCH(J34,Valute!A:A,0)) -> 1 | AC34: =SUMIF(Operazioni!A:A,A34,Operazioni!K:K) -> 342.3875 | AD34: =((I34+AA34)/IF(OR(D34="O",D34="CE"),100,1)*Z34)*AB34+AC34 -> 5342.3875 | AE34: =AD34-W34 -> 320.99846 | AF34: =IF(W34<>0,AE34/W34,"") -> 0.063926228 | AG34: 45929 | AH34: Milano | AI34: Fineco-C | AJ34: 100 | AM34: 1 | AO34: =AC34*(1-N34) -> 299.58906 | AP34: =((I34+AA34)/IF(OR(D34="O",D34="CE"),100,1)*AJ34*(1-AK34)-AL34)*AM34-AN34+AC34 -> 5342.3875 | AQ34: =AP34-W34 -> 320.99845 | AR34: =IF(W34<>0,AQ34/W34,"") -> 0.063926226 | AS34: =(AQ34-AC34)*N34 -> -2.6736313 | AT34: =IF(W34<>0,(AQ34-AS34)/W34,"") -> 0.064458674
A35: 26 | B35: 1 | C35: USA-15MG25 2,125 | D35: O | E35: Obblig | F35: US | G35: Governativo | H35: US | I35: 5000 | J35: USD | K35: US912828XB14 | N35: 0.125 | O35: 45161 | P35: ETLX | Q35: Fineco-C | R35: 95.17 | S35: 0.005 | T35: 0 | U35: 0.9184 | V35: 52.51 | W35: =(I35/IF(OR(D35="O",D35="CE"),100,1)*R35*(1+S35)+T35)*U35+V35 -> 4444.5674 | X35: ETLX | Y35: Fineco-C | Z35: 100 | AA35: =SUMIF(Operazioni!A:A,A35,Operazioni!C:C) -> 0 | AB35: =INDEX(Valute!B:B,MATCH(J35,Valute!A:A,0)) -> 0.86002565 | AC35: =SUMIF(Operazioni!A:A,A35,Operazioni!K:K) -> 171.0275 | AD35: =((I35+AA35)/IF(OR(D35="O",D35="CE"),100,1)*Z35)*AB35+AC35 -> 4471.1557 | AE35: =AD35-W35 -> 26.588318 | AF35: =IF(W35<>0,AE35/W35,"") -> 0.005982206 | AG35: 45792 | AH35: Milano | AI35: Fineco-C | AJ35: 100 | AM35: =1/1.1185 -> 0.89405454 | AO35: =AC35*(1-N35) -> 149.64906 | AP35: =((I35+AA35)/IF(OR(D35="O",D35="CE"),100,1)*AJ35*(1-AK35)-AL35)*AM35-AN35+AC35 -> 4641.3002 | AQ35: =AP35-W35 -> 196.73275 | AR35: =IF(W35<>0,AQ35/W35,"") -> 0.044263645 | AS35: =(AQ35-AC35)*N35 -> 3.2131568 | AT35: =IF(W35<>0,(AQ35-AS35)/W35,"") -> 0.043540705
A36: 29 | B36: 1 | C36: BTP-VAL 10OT28SU CUM | D36: O | E36: Obblig | F36: Italia | G36: Governativo | H36: Italia | I36: 5000 | J36: EUR | K36: IT0005565400 | N36: 0.125 | O36: 45201 | P36: MOT | Q36: Fineco | R36: 100 | S36: 0 | T36: 0 | U36: 1 | W36: =(I36/IF(OR(D36="O",D36="CE"),100,1)*R36*(1+S36)+T36)*U36+V36 -> 5000 | X36: MOT | Y36: Fineco | Z36: 100 | AA36: =SUMIF(Operazioni!A:A,A36,Operazioni!C:C) -> 0 | AB36: =INDEX(Valute!B:B,MATCH(J36,Valute!A:A,0)) -> 1 | AC36: =SUMIF(Operazioni!A:A,A36,Operazioni!K:K) -> 403.59375 | AD36: =((I36+AA36)/IF(OR(D36="O",D36="CE"),100,1)*Z36)*AB36+AC36 -> 5403.5938 | AE36: =AD36-W36 -> 403.59376 | AF36: =IF(W36<>0,AE36/W36,"") -> 0.080718752 | AO36: =AC36*(1-N36) -> 353.14453 | AP36: =((I36+AA36)/IF(OR(D36="O",D36="CE"),100,1)*AJ36*(1-AK36)-AL36)*AM36-AN36+AC36 -> 403.59375 | AQ36: =AP36-W36 -> -4596.4062 | AR36: =IF(W36<>0,AQ36/W36,"") -> -0.91928125 | AS36: =(AQ36-AC36)*N36 -> -625 | AT36: =IF(W36<>0,(AQ36-AS36)/W36,"") -> -0.79428125
A37: 31 | B37: 1 | C37: SPAIN-30LG33 2,35 | D37: O | E37: Obblig | F37: EU | G37: Governativo | H37: Spagna | I37: 2000 | J37: EUR | K37: ES00000128Q6 | N37: 0.125 | O37: 45302 | P37: MOT | Q37: Fineco | R37: 94.04 | S37: 0 | T37: 0 | U37: 1 | V37: 19 | W37: =(I37/IF(OR(D37="O",D37="CE"),100,1)*R37*(1+S37)+T37)*U37+V37 -> 1899.8 | X37: MOT | Y37: Fineco | Z37: 100 | AA37: =SUMIF(Operazioni!A:A,A37,Operazioni!C:C) -> 0 | AB37: =INDEX(Valute!B:B,MATCH(J37,Valute!A:A,0)) -> 1 | AC37: =SUMIF(Operazioni!A:A,A37,Operazioni!K:K) -> 82.25 | AD37: =((I37+AA37)/IF(OR(D37="O",D37="CE"),100,1)*Z37)*AB37+AC37 -> 2082.25 | AE37: =AD37-W37 -> 182.45 | AF37: =IF(W37<>0,AE37/W37,"") -> 0.096036427 | AO37: =AC37*(1-N37) -> 71.96875 | AP37: =((I37+AA37)/IF(OR(D37="O",D37="CE"),100,1)*AJ37*(1-AK37)-AL37)*AM37-AN37+AC37 -> 82.25 | AQ37: =AP37-W37 -> -1817.55 | AR37: =IF(W37<>0,AQ37/W37,"") -> -0.95670597 | AS37: =(AQ37-AC37)*N37 -> -237.475 | AT37: =IF(W37<>0,(AQ37-AS37)/W37,"") -> -0.83170597
A38: 33 | B38: 1 | C38: BTP-VAL 5MZ30SU CUM | D38: O | E38: Obblig | F38: Italia | G38: Governativo | H38: Italia | I38: 2000 | J38: EUR | K38: IT0005583486 | N38: 0.125 | O38: 45350 | P38: MOT | Q38: Fineco | R38: 100 | S38: 0 | T38: 0 | U38: 1 | W38: =(I38/IF(OR(D38="O",D38="CE"),100,1)*R38*(1+S38)+T38)*U38+V38 -> 2000 | X38: MOT | Y38: Fineco | Z38: 100 | AA38: =SUMIF(Operazioni!A:A,A38,Operazioni!C:C) -> 0 | AB38: =INDEX(Valute!B:B,MATCH(J38,Valute!A:A,0)) -> 1 | AC38: =SUMIF(Operazioni!A:A,A38,Operazioni!K:K) -> 113.75 | AD38: =((I38+AA38)/IF(OR(D38="O",D38="CE"),100,1)*Z38)*AB38+AC38 -> 2113.75 | AE38: =AD38-W38 -> 113.75 | AF38: =IF(W38<>0,AE38/W38,"") -> 0.056875002 | AO38: =AC38*(1-N38) -> 99.53125 | AP38: =((I38+AA38)/IF(OR(D38="O",D38="CE"),100,1)*AJ38*(1-AK38)-AL38)*AM38-AN38+AC38 -> 113.75 | AQ38: =AP38-W38 -> -1886.25 | AR38: =IF(W38<>0,AQ38/W38,"") -> -0.943125 | AS38: =(AQ38-AC38)*N38 -> -250 | AT38: =IF(W38<>0,(AQ38-AS38)/W38,"") -> -0.818125
A39: 34 | B39: 1 | C39: Vanguard FTSE All-World UCITS ETF (USD) Acc | D39: ETF | E39: Azioni | F39: Mondo | H39: Vanguard | I39: 9 | J39: EUR | K39: IE00BK5BQT80 | L39: VWCE.MI | M39: #VALUE! | N39: 0.26 | O39: 45427 | P39: Milano | Q39: Fineco | R39: 118.934 | S39: 0 | T39: 0 | U39: 1 | V39: 2.95 | W39: =(I39/IF(OR(D39="O",D39="CE"),100,1)*R39*(1+S39)+T39)*U39+V39 -> 1073.356 | X39: Milano | Y39: Fineco | Z39: {=_FV(M39,"Price",TRUE)} -> 162.56 | AA39: =SUMIF(Operazioni!A:A,A39,Operazioni!C:C) -> 0 | AB39: =INDEX(Valute!B:B,MATCH(J39,Valute!A:A,0)) -> 1 | AC39: =SUMIF(Operazioni!A:A,A39,Operazioni!K:K) -> 0 | AD39: =((I39+AA39)/IF(OR(D39="O",D39="CE"),100,1)*Z39)*AB39+AC39 -> 1463.04 | AE39: =AD39-W39 -> 389.684 | AF39: =IF(W39<>0,AE39/W39,"") -> 0.36305196 | AO39: =AC39*(1-N39) -> 0 | AP39: =((I39+AA39)/IF(OR(D39="O",D39="CE"),100,1)*AJ39*(1-AK39)-AL39)*AM39-AN39+AC39 -> 0 | AQ39: =AP39-W39 -> -1073.356 | AR39: =IF(W39<>0,AQ39/W39,"") -> -1 | AS39: =(AQ39-AC39)*N39 -> -279.07256 | AT39: =IF(W39<>0,(AQ39-AS39)/W39,"") -> -0.74
A40: 35 | B40: 1 | C40: Invesco Physical Gold ETC | D40: ETF | E40: Oro | F40: US | G40: Siderurgia | H40: Invesco | I40: 10 | J40: EUR | K40: IE00B579F325 | L40: SGLD.MI | M40: #VALUE! | N40: 0.26 | O40: 45439 | P40: Milano | Q40: Fineco | R40: 208.4 | S40: 0 | T40: 0 | U40: 1 | V40: 19 | W40: =(I40/IF(OR(D40="O",D40="CE"),100,1)*R40*(1+S40)+T40)*U40+V40 -> 2103 | X40: Milano | Y40: Fineco | Z40: {=_FV(M40,"Price",TRUE)} -> 372.88 | AA40: =SUMIF(Operazioni!A:A,A40,Operazioni!C:C) -> 0 | AB40: =INDEX(Valute!B:B,MATCH(J40,Valute!A:A,0)) -> 1 | AC40: =SUMIF(Operazioni!A:A,A40,Operazioni!K:K) -> 0 | AD40: =((I40+AA40)/IF(OR(D40="O",D40="CE"),100,1)*Z40)*AB40+AC40 -> 3728.8 | AE40: =AD40-W40 -> 1625.8 | AF40: =IF(W40<>0,AE40/W40,"") -> 0.77308607 | AO40: =AC40*(1-N40) -> 0 | AP40: =((I40+AA40)/IF(OR(D40="O",D40="CE"),100,1)*AJ40*(1-AK40)-AL40)*AM40-AN40+AC40 -> 0 | AQ40: =AP40-W40 -> -2103 | AR40: =IF(W40<>0,AQ40/W40,"") -> -1 | AS40: =(AQ40-AC40)*N40 -> -546.78 | AT40: =IF(W40<>0,(AQ40-AS40)/W40,"") -> -0.74
A41: 36 | B41: 1 | C41: Vanguard FTSE All-World UCITS ETF (USD) Acc | D41: ETF | E41: Azioni | F41: Mondo | H41: Vanguard | I41: 8 | J41: EUR | K41: IE00BK5BQT80 | L41: VWCE.MI | M41: #VALUE! | N41: 0.26 | O41: 45446 | P41: Milano | Q41: Fineco | R41: 119.293 | S41: 0 | T41: 0 | U41: 1 | V41: 2.95 | W41: =(I41/IF(OR(D41="O",D41="CE"),100,1)*R41*(1+S41)+T41)*U41+V41 -> 957.294 | X41: Milano | Y41: Fineco | Z41: {=_FV(M41,"Price",TRUE)} -> 162.56 | AA41: =SUMIF(Operazioni!A:A,A41,Operazioni!C:C) -> 0 | AB41: =INDEX(Valute!B:B,MATCH(J41,Valute!A:A,0)) -> 1 | AC41: =SUMIF(Operazioni!A:A,A41,Operazioni!K:K) -> 0 | AD41: =((I41+AA41)/IF(OR(D41="O",D41="CE"),100,1)*Z41)*AB41+AC41 -> 1300.48 | AE41: =AD41-W41 -> 343.186 | AF41: =IF(W41<>0,AE41/W41,"") -> 0.35849593 | AO41: =AC41*(1-N41) -> 0 | AP41: =((I41+AA41)/IF(OR(D41="O",D41="CE"),100,1)*AK40*(1-AK41)-AL41)*AM41-AN41+AC41 -> 0 | AQ41: =AP41-W41 -> -957.294 | AR41: =IF(W41<>0,AQ41/W41,"") -> -1 | AS41: =(AQ41-AC41)*N41 -> -248.89644 | AT41: =IF(W41<>0,(AQ41-AS41)/W41,"") -> -0.74
A42: 37 | B42: 1 | C42: BTP-28GE26 3,2 | D42: O | E42: Obblig | F42: Italia | G42: Governativo | H42: Italia | I42: 2000 | J42: EUR | K42: IT0005584302 | N42: 0.125 | O42: 45470 | P42: MOT | Q42: Fineco | R42: 99.57 | S42: 0 | T42: 0 | U42: 1 | V42: 19 | W42: =(I42/IF(OR(D42="O",D42="CE"),100,1)*R42*(1+S42)+T42)*U42+V42 -> 2010.4 | X42: MOT | Y42: Fineco | Z42: 100 | AA42: =SUMIF(Operazioni!A:A,A42,Operazioni!C:C) -> 0 | AB42: =INDEX(Valute!B:B,MATCH(J42,Valute!A:A,0)) -> 1 | AC42: =SUMIF(Operazioni!A:A,A42,Operazioni!K:K) -> 107.38875 | AD42: =((I42+AA42)/IF(OR(D42="O",D42="CE"),100,1)*Z42)*AB42+AC42 -> 2107.3888 | AE42: =AD42-W42 -> 96.988754 | AF42: =IF(W42<>0,AE42/W42,"") -> 0.048243511 | AG42: 46050 | AH42: Milano | AI42: Fineco | AJ42: 99.9585 | AM42: 1 | AO42: =AC42*(1-N42) -> 93.965156 | AP42: =((I42+AA42)/IF(OR(D42="O",D42="CE"),100,1)*AJ42*(1-AK42)-AL42)*AM42-AN42+AC42 -> 2106.5588 | AQ42: =AP42-W42 -> 96.15875 | AR42: =IF(W42<>0,AQ42/W42,"") -> 0.047830656 | AS42: =(AQ42-AC42)*N42 -> -1.40375 | AT42: =IF(W42<>0,(AQ42-AS42)/W42,"") -> 0.0485289
A43: 38 | B43: 1 | C43: Vanguard FTSE All-World UCITS ETF (USD) Acc | D43: ETF | E43: Azioni | F43: Mondo | H43: Vanguard | I43: 8 | J43: EUR | K43: IE00BK5BQT80 | L43: VWCE.MI | M43: #VALUE! | N43: 0.26 | O43: 45474 | P43: Milano | Q43: Fineco | R43: 122.487 | S43: 0 | T43: 0 | U43: 1 | V43: 2.95 | W43: =(I43/IF(OR(D43="O",D43="CE"),100,1)*R43*(1+S43)+T43)*U43+V43 -> 982.846 | X43: Milano | Y43: Fineco | Z43: {=_FV(M43,"Price")} -> 162.56 | AA43: =SUMIF(Operazioni!A:A,A43,Operazioni!C:C) -> 0 | AB43: =INDEX(Valute!B:B,MATCH(J43,Valute!A:A,0)) -> 1 | AC43: =SUMIF(Operazioni!A:A,A43,Operazioni!K:K) -> 0 | AD43: =((I43+AA43)/IF(OR(D43="O",D43="CE"),100,1)*Z43)*AB43+AC43 -> 1300.48 | AE43: =AD43-W43 -> 317.634 | AF43: =IF(W43<>0,AE43/W43,"") -> 0.32317779 | AO43: =AC43*(1-N43) -> 0 | AP43: =((I43+AA43)/IF(OR(D43="O",D43="CE"),100,1)*AJ43*(1-AK43)-AL43)*AM43-AN43+AC43 -> 0 | AQ43: =AP43-W43 -> -982.846 | AR43: =IF(W43<>0,AQ43/W43,"") -> -1 | AS43: =(AQ43-AC43)*N43 -> -255.53996 | AT43: =IF(W43<>0,(AQ43-AS43)/W43,"") -> -0.74
A44: 39 | B44: 1 | C44: Xtrackers II EUR Overnight Rate Swap UCITS ETF 1C | D44: ETF | E44: Obblig | F44: EU | G44: Governativo | H44: Xtrackers | I44: 7 | J44: EUR | K44: LU0290358497 | L44: XEON.MI | M44: #VALUE! | N44: 0.125 | O44: 45477 | P44: Milano | Q44: Fineco | R44: 142.3807 | S44: 0 | T44: 0 | U44: 1 | W44: =(I44/IF(OR(D44="O",D44="CE"),100,1)*R44*(1+S44)+T44)*U44+V44 -> 996.6649 | X44: Milano | Y44: Fineco | Z44: {=_FV(M44,"Price")} -> 149.2184 | AA44: =SUMIF(Operazioni!A:A,A44,Operazioni!C:C) -> 0 | AB44: =INDEX(Valute!B:B,MATCH(J44,Valute!A:A,0)) -> 1 | AC44: =SUMIF(Operazioni!A:A,A44,Operazioni!K:K) -> 0 | AD44: =((I44+AA44)/IF(OR(D44="O",D44="CE"),100,1)*Z44)*AB44+AC44 -> 1044.5288 | AE44: =AD44-W44 -> 47.863902 | AF44: =IF(W44<>0,AE44/W44,"") -> 0.048024067 | AO44: =AC44*(1-N44) -> 0 | AP44: =((I44+AA44)/IF(OR(D44="O",D44="CE"),100,1)*AJ44*(1-AK44)-AL44)*AM44-AN44+AC44 -> 0 | AQ44: =AP44-W44 -> -996.6649 | AR44: =IF(W44<>0,AQ44/W44,"") -> -1 | AS44: =(AQ44-AC44)*N44 -> -124.58311 | AT44: =IF(W44<>0,(AQ44-AS44)/W44,"") -> -0.875
A45: 40 | B45: 1 | C45: Xtrackers II EUR Overnight Rate Swap UCITS ETF 1C | D45: ETF | E45: Obblig | F45: EU | G45: Governativo | H45: Xtrackers | I45: 7 | J45: EUR | K45: LU0290358497 | L45: XEON.MI | M45: #VALUE! | N45: 0.125 | O45: 45499 | P45: Milano | Q45: Fineco | R45: 142.7145 | S45: 0 | T45: 0 | U45: 1 | W45: =(I45/IF(OR(D45="O",D45="CE"),100,1)*R45*(1+S45)+T45)*U45+V45 -> 999.0015 | X45: Milano | Y45: Fineco | Z45: {=_FV(M45,"Price")} -> 149.2184 | AA45: =SUMIF(Operazioni!A:A,A45,Operazioni!C:C) -> 0 | AB45: =INDEX(Valute!B:B,MATCH(J45,Valute!A:A,0)) -> 1 | AC45: =SUMIF(Operazioni!A:A,A45,Operazioni!K:K) -> 0 | AD45: =((I45+AA45)/IF(OR(D45="O",D45="CE"),100,1)*Z45)*AB45+AC45 -> 1044.5288 | AE45: =AD45-W45 -> 45.527302 | AF45: =IF(W45<>0,AE45/W45,"") -> 0.045572806 | AO45: =AC45*(1-N45) -> 0 | AP45: =((I45+AA45)/IF(OR(D45="O",D45="CE"),100,1)*AJ45*(1-AK45)-AL45)*AM45-AN45+AC45 -> 0 | AQ45: =AP45-W45 -> -999.0015 | AR45: =IF(W45<>0,AQ45/W45,"") -> -1 | AS45: =(AQ45-AC45)*N45 -> -124.87519 | AT45: =IF(W45<>0,(AQ45-AS45)/W45,"") -> -0.875
A46: 41 | B46: 1 | C46: Vanguard FTSE All-World UCITS ETF (USD) Acc | D46: ETF | E46: Azioni | F46: Mondo | H46: Vanguard | I46: 9 | J46: EUR | K46: IE00BK5BQT80 | L46: VWCE.MI | M46: #VALUE! | N46: 0.26 | O46: 45505 | P46: Milano | Q46: Fineco | R46: 123.541 | S46: 0 | T46: 0 | U46: 1 | V46: 2.95 | W46: =(I46/IF(OR(D46="O",D46="CE"),100,1)*R46*(1+S46)+T46)*U46+V46 -> 1114.819 | X46: Milano | Y46: Fineco | Z46: {=_FV(M46,"Price")} -> 162.56 | AA46: =SUMIF(Operazioni!A:A,A46,Operazioni!C:C) -> 0 | AB46: =INDEX(Valute!B:B,MATCH(J46,Valute!A:A,0)) -> 1 | AC46: =SUMIF(Operazioni!A:A,A46,Operazioni!K:K) -> 0 | AD46: =((I46+AA46)/IF(OR(D46="O",D46="CE"),100,1)*Z46)*AB46+AC46 -> 1463.04 | AE46: =AD46-W46 -> 348.221 | AF46: =IF(W46<>0,AE46/W46,"") -> 0.31235654 | AO46: =AC46*(1-N46) -> 0 | AP46: =((I46+AA46)/IF(OR(D46="O",D46="CE"),100,1)*AJ46*(1-AK46)-AL46)*AM46-AN46+AC46 -> 0 | AQ46: =AP46-W46 -> -1114.819 | AR46: =IF(W46<>0,AQ46/W46,"") -> -1 | AS46: =(AQ46-AC46)*N46 -> -289.85294 | AT46: =IF(W46<>0,(AQ46-AS46)/W46,"") -> -0.74
A47: 42 | B47: 1 | C47: Xtrackers II EUR Overnight Rate Swap UCITS ETF 1C | D47: ETF | E47: Obblig | F47: EU | G47: Governativo | H47: Xtrackers | I47: 7 | J47: EUR | K47: LU0290358497 | L47: XEON.MI | M47: #VALUE! | N47: 0.125 | O47: 45499 | P47: Milano | Q47: Fineco | R47: 143.1672 | S47: 0 | T47: 0 | U47: 1 | W47: =(I47/IF(OR(D47="O",D47="CE"),100,1)*R47*(1+S47)+T47)*U47+V47 -> 1002.1704 | X47: Milano | Y47: Fineco | Z47: {=_FV(M47,"Price")} -> 149.2184 | AA47: =SUMIF(Operazioni!A:A,A47,Operazioni!C:C) -> 0 | AB47: =INDEX(Valute!B:B,MATCH(J47,Valute!A:A,0)) -> 1 | AC47: =SUMIF(Operazioni!A:A,A47,Operazioni!K:K) -> 0 | AD47: =((I47+AA47)/IF(OR(D47="O",D47="CE"),100,1)*Z47)*AB47+AC47 -> 1044.5288 | AE47: =AD47-W47 -> 42.358402 | AF47: =IF(W47<>0,AE47/W47,"") -> 0.042266666 | AO47: =AC47*(1-N47) -> 0 | AP47: =((I47+AA47)/IF(OR(D47="O",D47="CE"),100,1)*AJ47*(1-AK47)-AL47)*AM47-AN47+AC47 -> 0 | AQ47: =AP47-W47 -> -1002.1704 | AR47: =IF(W47<>0,AQ47/W47,"") -> -1 | AS47: =(AQ47-AC47)*N47 -> -125.2713 | AT47: =IF(W47<>0,(AQ47-AS47)/W47,"") -> -0.875
A48: 43 | B48: 1 | C48: Vanguard FTSE All-World UCITS ETF (USD) Acc | D48: ETF | E48: Azioni | F48: Mondo | H48: Vanguard | I48: 9 | J48: EUR | K48: IE00BK5BQT80 | L48: VWCE.MI | M48: #VALUE! | N48: 0.26 | O48: 45538 | P48: Milano | Q48: Fineco | R48: 123.62978 | S48: 0 | T48: 0 | U48: 1 | V48: 2.32 | W48: =(I48/IF(OR(D48="O",D48="CE"),100,1)*R48*(1+S48)+T48)*U48+V48 -> 1114.988 | X48: Milano | Y48: Fineco | Z48: {=_FV(M48,"Price")} -> 162.56 | AA48: =SUMIF(Operazioni!A:A,A48,Operazioni!C:C) -> 0 | AB48: =INDEX(Valute!B:B,MATCH(J48,Valute!A:A,0)) -> 1 | AC48: =SUMIF(Operazioni!A:A,A48,Operazioni!K:K) -> 0 | AD48: =((I48+AA48)/IF(OR(D48="O",D48="CE"),100,1)*Z48)*AB48+AC48 -> 1463.04 | AE48: =AD48-W48 -> 348.05198 | AF48: =IF(W48<>0,AE48/W48,"") -> 0.3121576 | AO48: =AC48*(1-N48) -> 0 | AP48: =((I48+AA48)/IF(OR(D48="O",D48="CE"),100,1)*AJ48*(1-AK48)-AL48)*AM48-AN48+AC48 -> 0 | AQ48: =AP48-W48 -> -1114.988 | AR48: =IF(W48<>0,AQ48/W48,"") -> -1 | AS48: =(AQ48-AC48)*N48 -> -289.89689 | AT48: =IF(W48<>0,(AQ48-AS48)/W48,"") -> -0.74
A49: 44 | B49: 1 | C49: iShares iBonds Dec 2028 Term EUR Corp UCITS ETF (Acc) | D49: ETF | E49: Obblig | F49: EU | G49: Industria | H49: iShares | I49: 450 | J49: EUR | K49: IE0008UEVOE0 | L49: IVOA.DE | M49: #VALUE! | N49: 0.26 | O49: 45538 | P49: Xetra | Q49: Fineco | R49: 5.36756 | S49: 0 | T49: 0 | U49: 1 | V49: 2.32 | W49: =(I49/IF(OR(D49="O",D49="CE"),100,1)*R49*(1+S49)+T49)*U49+V49 -> 2417.722 | X49: Xetra | Y49: Fineco | Z49: {=_FV(M49,"Price")} -> 5.665 | AA49: =SUMIF(Operazioni!A:A,A49,Operazioni!C:C) -> 0 | AB49: =INDEX(Valute!B:B,MATCH(J49,Valute!A:A,0)) -> 1 | AC49: =SUMIF(Operazioni!A:A,A49,Operazioni!K:K) -> 0 | AD49: =((I49+AA49)/IF(OR(D49="O",D49="CE"),100,1)*Z49)*AB49+AC49 -> 2549.25 | AE49: =AD49-W49 -> 131.528 | AF49: =IF(W49<>0,AE49/W49,"") -> 0.054401625 | AO49: =AC49*(1-N49) -> 0 | AP49: =((I49+AA49)/IF(OR(D49="O",D49="CE"),100,1)*AJ49*(1-AK49)-AL49)*AM49-AN49+AC49 -> 0 | AQ49: =AP49-W49 -> -2417.722 | AR49: =IF(W49<>0,AQ49/W49,"") -> -1 | AS49: =(AQ49-AC49)*N49 -> -628.60772 | AT49: =IF(W49<>0,(AQ49-AS49)/W49,"") -> -0.74
A50: 45 | B50: 1 | C50: Amundi IS Fix. Mat. 2028 Euro Gov Bd Br. UCITS ETF Dis | D50: ETF | E50: Obblig | F50: EU | G50: Governativo | H50: Amundi | I50: 250 | J50: EUR | K50: LU2780871401 | L50: MB28.MI | M50: #VALUE! | N50: 0.125 | O50: 45538 | P50: Milano | Q50: Fineco | R50: 10.26928 | S50: 0 | T50: 0 | U50: 1 | V50: 2.32 | W50: =(I50/IF(OR(D50="O",D50="CE"),100,1)*R50*(1+S50)+T50)*U50+V50 -> 2569.64 | X50: Milano | Y50: Fineco | Z50: {=_FV(M50,"Price")} -> 10.4085 | AA50: =SUMIF(Operazioni!A:A,A50,Operazioni!C:C) -> 0 | AB50: =INDEX(Valute!B:B,MATCH(J50,Valute!A:A,0)) -> 1 | AC50: =SUMIF(Operazioni!A:A,A50,Operazioni!K:K) -> 113.4 | AD50: =((I50+AA50)/IF(OR(D50="O",D50="CE"),100,1)*Z50)*AB50+AC50 -> 2715.525 | AE50: =AD50-W50 -> 145.885 | AF50: =IF(W50<>0,AE50/W50,"") -> 0.056772546 | AO50: =AC50*(1-N50) -> 99.225 | AP50: =((I50+AA50)/IF(OR(D50="O",D50="CE"),100,1)*AJ50*(1-AK50)-AL50)*AM50-AN50+AC50 -> 113.4 | AQ50: =AP50-W50 -> -2456.24 | AR50: =IF(W50<>0,AQ50/W50,"") -> -0.9558693 | AS50: =(AQ50-AC50)*N50 -> -321.205 | AT50: =IF(W50<>0,(AQ50-AS50)/W50,"") -> -0.8308693
A51: 46 | B51: 1 | C51: Xtrackers II EUR Overnight Rate Swap UCITS ETF 1C | D51: ETF | E51: Obblig | F51: EU | G51: Governativo | H51: Xtrackers | I51: 21 | J51: EUR | K51: LU0290358497 | L51: XEON.MI | M51: #VALUE! | N51: 0.125 | O51: 45562 | P51: Milano | Q51: Fineco | R51: 143.625 | S51: 0 | T51: 0 | U51: 1 | W51: =(I51/IF(OR(D51="O",D51="CE"),100,1)*R51*(1+S51)+T51)*U51+V51 -> 3016.125 | X51: Milano | Y51: Fineco | Z51: {=_FV(M51,"Price")} -> 149.2184 | AA51: =SUMIF(Operazioni!A:A,A51,Operazioni!C:C) -> 0 | AB51: =INDEX(Valute!B:B,MATCH(J51,Valute!A:A,0)) -> 1 | AC51: =SUMIF(Operazioni!A:A,A51,Operazioni!K:K) -> 0 | AD51: =((I51+AA51)/IF(OR(D51="O",D51="CE"),100,1)*Z51)*AB51+AC51 -> 3133.5864 | AE51: =AD51-W51 -> 117.46141 | AF51: =IF(W51<>0,AE51/W51,"") -> 0.038944475 | AO51: =AC51*(1-N51) -> 0 | AP51: =((I51+AA51)/IF(OR(D51="O",D51="CE"),100,1)*AJ51*(1-AK51)-AL51)*AM51-AN51+AC51 -> 0 | AQ51: =AP51-W51 -> -3016.125 | AR51: =IF(W51<>0,AQ51/W51,"") -> -1 | AS51: =(AQ51-AC51)*N51 -> -377.01562 | AT51: =IF(W51<>0,(AQ51-AS51)/W51,"") -> -0.875
A52: 47 | B52: 1 | C52: Vanguard FTSE All-World UCITS ETF (USD) Acc | D52: ETF | E52: Azioni | F52: Mondo | H52: Vanguard | I52: 9 | J52: EUR | K52: IE00BK5BQT80 | L52: VWCE.MI | M52: #VALUE! | N52: 0.26 | O52: 45566 | P52: Milano | Q52: Fineco | R52: 125.967 | S52: 0 | T52: 0 | U52: 1 | V52: 2.32 | W52: =(I52/IF(OR(D52="O",D52="CE"),100,1)*R52*(1+S52)+T52)*U52+V52 -> 1136.023 | X52: Milano | Y52: Fineco | Z52: {=_FV(M52,"Price")} -> 162.56 | AA52: =SUMIF(Operazioni!A:A,A52,Operazioni!C:C) -> 0 | AB52: =INDEX(Valute!B:B,MATCH(J52,Valute!A:A,0)) -> 1 | AC52: =SUMIF(Operazioni!A:A,A52,Operazioni!K:K) -> 0 | AD52: =((I52+AA52)/IF(OR(D52="O",D52="CE"),100,1)*Z52)*AB52+AC52 -> 1463.04 | AE52: =AD52-W52 -> 327.017 | AF52: =IF(W52<>0,AE52/W52,"") -> 0.28786125 | AO52: =AC52*(1-N52) -> 0 | AP52: =((I52+AA52)/IF(OR(D52="O",D52="CE"),100,1)*AJ52*(1-AK52)-AL52)*AM52-AN52+AC52 -> 0 | AQ52: =AP52-W52 -> -1136.023 | AR52: =IF(W52<>0,AQ52/W52,"") -> -1 | AS52: =(AQ52-AC52)*N52 -> -295.36598 | AT52: =IF(W52<>0,(AQ52-AS52)/W52,"") -> -0.74
A53: 48 | B53: 1 | C53: iShares iBonds Dec 2028 Term EUR Corp UCITS ETF (Acc) | D53: ETF | E53: Obblig | F53: EU | G53: Industria | H53: iShares | I53: 450 | J53: EUR | K53: IE0008UEVOE0 | L53: IVOA.DE | M53: #VALUE! | N53: 0.26 | O53: 45566 | P53: Milano | Q53: Fineco | R53: 5.437 | S53: 0 | T53: 0 | U53: 1 | V53: 2.32 | W53: =(I53/IF(OR(D53="O",D53="CE"),100,1)*R53*(1+S53)+T53)*U53+V53 -> 2448.97 | X53: Milano | Y53: Fineco | Z53: {=_FV(M53,"Price")} -> 5.665 | AA53: =SUMIF(Operazioni!A:A,A53,Operazioni!C:C) -> 0 | AB53: =INDEX(Valute!B:B,MATCH(J53,Valute!A:A,0)) -> 1 | AC53: =SUMIF(Operazioni!A:A,A53,Operazioni!K:K) -> 0 | AD53: =((I53+AA53)/IF(OR(D53="O",D53="CE"),100,1)*Z53)*AB53+AC53 -> 2549.25 | AE53: =AD53-W53 -> 100.28 | AF53: =IF(W53<>0,AE53/W53,"") -> 0.040947829 | AO53: =AC53*(1-N53) -> 0 | AP53: =((I53+AA53)/IF(OR(D53="O",D53="CE"),100,1)*AJ53*(1-AK53)-AL53)*AM53-AN53+AC53 -> 0 | AQ53: =AP53-W53 -> -2448.97 | AR53: =IF(W53<>0,AQ53/W53,"") -> -1 | AS53: =(AQ53-AC53)*N53 -> -636.7322 | AT53: =IF(W53<>0,(AQ53-AS53)/W53,"") -> -0.74
A54: 49 | B54: 1 | C54: Amundi IS Fix. Mat. 2028 Euro Gov Bd Br. UCITS ETF Dis | D54: ETF | E54: Obblig | F54: EU | G54: Governativo | H54: Amundi | I54: 250 | J54: EUR | K54: LU2780871401 | L54: MB28.MI | M54: #VALUE! | N54: 0.125 | O54: 45566 | P54: Xetra | Q54: Fineco | R54: 10.408 | S54: 0 | T54: 0 | U54: 1 | V54: 2.32 | W54: =(I54/IF(OR(D54="O",D54="CE"),100,1)*R54*(1+S54)+T54)*U54+V54 -> 2604.32 | X54: Xetra | Y54: Fineco | Z54: {=_FV(M54,"Price")} -> 10.4085 | AA54: =SUMIF(Operazioni!A:A,A54,Operazioni!C:C) -> 0 | AB54: =INDEX(Valute!B:B,MATCH(J54,Valute!A:A,0)) -> 1 | AC54: =SUMIF(Operazioni!A:A,A54,Operazioni!K:K) -> 0 | AD54: =((I54+AA54)/IF(OR(D54="O",D54="CE"),100,1)*Z54)*AB54+AC54 -> 2602.125 | AE54: =AD54-W54 -> -2.1949951 | AF54: =IF(W54<>0,AE54/W54,"") -> -0.00084282848 | AO54: =AC54*(1-N54) -> 0 | AP54: =((I54+AA54)/IF(OR(D54="O",D54="CE"),100,1)*AJ54*(1-AK54)-AL54)*AM54-AN54+AC54 -> 0 | AQ54: =AP54-W54 -> -2604.32 | AR54: =IF(W54<>0,AQ54/W54,"") -> -1 | AS54: =(AQ54-AC54)*N54 -> -325.54 | AT54: =IF(W54<>0,(AQ54-AS54)/W54,"") -> -0.875
A55: 50 | B55: 1 | C55: Xtrackers II EUR Overnight Rate Swap UCITS ETF 1C | D55: ETF | E55: Obblig | F55: EU | G55: Governativo | H55: Xtrackers | I55: 5 | J55: EUR | K55: LU0290358497 | L55: XEON.MI | M55: #VALUE! | N55: 0.125 | O55: 45593 | P55: Milano | Q55: Fineco | R55: 144.0219 | S55: 0 | T55: 0 | U55: 1 | W55: =(I55/IF(OR(D55="O",D55="CE"),100,1)*R55*(1+S55)+T55)*U55+V55 -> 720.1095 | X55: Milano | Y55: Fineco | Z55: {=_FV(M55,"Price")} -> 149.2184 | AA55: =SUMIF(Operazioni!A:A,A55,Operazioni!C:C) -> 0 | AB55: =INDEX(Valute!B:B,MATCH(J55,Valute!A:A,0)) -> 1 | AC55: =SUMIF(Operazioni!A:A,A55,Operazioni!K:K) -> 0 | AD55: =((I55+AA55)/IF(OR(D55="O",D55="CE"),100,1)*Z55)*AB55+AC55 -> 746.092 | AE55: =AD55-W55 -> 25.982501 | AF55: =IF(W55<>0,AE55/W55,"") -> 0.03608132 | AO55: =AC55*(1-N55) -> 0 | AP55: =((I55+AA55)/IF(OR(D55="O",D55="CE"),100,1)*AJ55*(1-AK55)-AL55)*AM55-AN55+AC55 -> 0 | AQ55: =AP55-W55 -> -720.1095 | AR55: =IF(W55<>0,AQ55/W55,"") -> -1 | AS55: =(AQ55-AC55)*N55 -> -90.013687 | AT55: =IF(W55<>0,(AQ55-AS55)/W55,"") -> -0.875
A56: 51 | B56: 1 | C56: Vanguard FTSE All-World UCITS ETF (USD) Acc | D56: ETF | E56: Azioni | F56: Mondo | H56: Vanguard | I56: 8 | J56: EUR | K56: IE00BK5BQT80 | L56: VWCE.MI | M56: #VALUE! | N56: 0.26 | O56: 45597 | P56: Milano | Q56: Fineco | R56: 126.52 | S56: 0 | T56: 0 | U56: 1 | V56: 2.95 | W56: =(I56/IF(OR(D56="O",D56="CE"),100,1)*R56*(1+S56)+T56)*U56+V56 -> 1015.11 | X56: Milano | Y56: Fineco | Z56: {=_FV(M56,"Price")} -> 162.56 | AA56: =SUMIF(Operazioni!A:A,A56,Operazioni!C:C) -> 0 | AB56: =INDEX(Valute!B:B,MATCH(J56,Valute!A:A,0)) -> 1 | AC56: =SUMIF(Operazioni!A:A,A56,Operazioni!K:K) -> 0 | AD56: =((I56+AA56)/IF(OR(D56="O",D56="CE"),100,1)*Z56)*AB56+AC56 -> 1300.48 | AE56: =AD56-W56 -> 285.37 | AF56: =IF(W56<>0,AE56/W56,"") -> 0.28112225 | AO56: =AC56*(1-N56) -> 0 | AP56: =((I56+AA56)/IF(OR(D56="O",D56="CE"),100,1)*AJ56*(1-AK56)-AL56)*AM56-AN56+AC56 -> 0 | AQ56: =AP56-W56 -> -1015.11 | AR56: =IF(W56<>0,AQ56/W56,"") -> -1 | AS56: =(AQ56-AC56)*N56 -> -263.9286 | AT56: =IF(W56<>0,(AQ56-AS56)/W56,"") -> -0.74
A57: 52 | B57: 1 | C57: Xtrackers II EUR Overnight Rate Swap UCITS ETF 1C | D57: ETF | E57: Obblig | F57: EU | G57: Governativo | H57: Xtrackers | I57: 3 | J57: EUR | K57: LU0290358497 | L57: XEON.MI | M57: #VALUE! | N57: 0.125 | O57: 45623 | P57: Milano | Q57: Fineco | R57: 144.4187 | S57: 0 | T57: 0 | U57: 1 | W57: =(I57/IF(OR(D57="O",D57="CE"),100,1)*R57*(1+S57)+T57)*U57+V57 -> 433.2561 | X57: Milano | Y57: Fineco | Z57: {=_FV(M57,"Price")} -> 149.2184 | AA57: =SUMIF(Operazioni!A:A,A57,Operazioni!C:C) -> 0 | AB57: =INDEX(Valute!B:B,MATCH(J57,Valute!A:A,0)) -> 1 | AC57: =SUMIF(Operazioni!A:A,A57,Operazioni!K:K) -> 0 | AD57: =((I57+AA57)/IF(OR(D57="O",D57="CE"),100,1)*Z57)*AB57+AC57 -> 447.6552 | AE57: =AD57-W57 -> 14.399101 | AF57: =IF(W57<>0,AE57/W57,"") -> 0.033234618 | AO57: =AC57*(1-N57) -> 0 | AP57: =((I57+AA57)/IF(OR(D57="O",D57="CE"),100,1)*AJ57*(1-AK57)-AL57)*AM57-AN57+AC57 -> 0 | AQ57: =AP57-W57 -> -433.2561 | AR57: =IF(W57<>0,AQ57/W57,"") -> -1 | AS57: =(AQ57-AC57)*N57 -> -54.157013 | AT57: =IF(W57<>0,(AQ57-AS57)/W57,"") -> -0.875
A58: 53 | B58: 1 | C58: Vanguard FTSE All-World UCITS ETF (USD) Acc | D58: ETF | E58: Azioni | F58: Mondo | H58: Vanguard | I58: 8 | J58: EUR | K58: IE00BK5BQT80 | L58: VWCE.MI | M58: #VALUE! | N58: 0.26 | O58: 45628 | P58: Milano | Q58: Fineco | R58: 135.065 | S58: 0 | T58: 0 | U58: 1 | V58: 2.95 | W58: =(I58/IF(OR(D58="O",D58="CE"),100,1)*R58*(1+S58)+T58)*U58+V58 -> 1083.47 | X58: Milano | Y58: Fineco | Z58: {=_FV(M58,"Price")} -> 162.56 | AA58: =SUMIF(Operazioni!A:A,A58,Operazioni!C:C) -> 0 | AB58: =INDEX(Valute!B:B,MATCH(J58,Valute!A:A,0)) -> 1 | AC58: =SUMIF(Operazioni!A:A,A58,Operazioni!K:K) -> 0 | AD58: =((I58+AA58)/IF(OR(D58="O",D58="CE"),100,1)*Z58)*AB58+AC58 -> 1300.48 | AE58: =AD58-W58 -> 217.01 | AF58: =IF(W58<>0,AE58/W58,"") -> 0.20029166 | AO58: =AC58*(1-N58) -> 0 | AP58: =((I58+AA58)/IF(OR(D58="O",D58="CE"),100,1)*AJ58*(1-AK58)-AL58)*AM58-AN58+AC58 -> 0 | AQ58: =AP58-W58 -> -1083.47 | AR58: =IF(W58<>0,AQ58/W58,"") -> -1 | AS58: =(AQ58-AC58)*N58 -> -281.7022 | AT58: =IF(W58<>0,(AQ58-AS58)/W58,"") -> -0.74
A59: 55 | B59: 1 | C59: Vanguard FTSE All-World UCITS ETF (USD) Acc | D59: ETF | E59: Azioni | F59: Mondo | H59: Vanguard | I59: 8 | J59: EUR | K59: IE00BK5BQT80 | L59: VWCE.MI | M59: #VALUE! | N59: 0.26 | O59: 45659 | P59: Milano | Q59: Fineco | R59: 134.6438 | S59: 0 | T59: 0 | U59: 1 | V59: 2.95 | W59: =(I59/IF(OR(D59="O",D59="CE"),100,1)*R59*(1+S59)+T59)*U59+V59 -> 1080.1004 | X59: Milano | Y59: Fineco | Z59: {=_FV(M59,"Price")} -> 162.56 | AA59: =SUMIF(Operazioni!A:A,A59,Operazioni!C:C) -> 0 | AB59: =INDEX(Valute!B:B,MATCH(J59,Valute!A:A,0)) -> 1 | AC59: =SUMIF(Operazioni!A:A,A59,Operazioni!K:K) -> 0 | AD59: =((I59+AA59)/IF(OR(D59="O",D59="CE"),100,1)*Z59)*AB59+AC59 -> 1300.48 | AE59: =AD59-W59 -> 220.3796 | AF59: =IF(W59<>0,AE59/W59,"") -> 0.20403622 | AO59: =AC59*(1-N59) -> 0 | AP59: =((I59+AA59)/IF(OR(D59="O",D59="CE"),100,1)*AJ59*(1-AK59)-AL59)*AM59-AN59+AC59 -> 0 | AQ59: =AP59-W59 -> -1080.1004 | AR59: =IF(W59<>0,AQ59/W59,"") -> -1 | AS59: =(AQ59-AC59)*N59 -> -280.8261 | AT59: =IF(W59<>0,(AQ59-AS59)/W59,"") -> -0.74
A60: 57 | B60: 1 | C60: BTP-PIU 25FB33 CUM | D60: O | E60: Obblig | F60: Italia | G60: Governativo | H60: Italia | I60: 2000 | J60: EUR | K60: IT0005634800 | N60: 0.125 | O60: 45705 | P60: Milano | Q60: Fineco | R60: 100 | S60: 0 | T60: 0 | U60: 1 | W60: =(I60/IF(OR(D60="O",D60="CE"),100,1)*R60*(1+S60)+T60)*U60+V60 -> 2000 | X60: Milano | Y60: Fineco | Z60: 100 | AA60: =SUMIF(Operazioni!A:A,A60,Operazioni!C:C) -> 0 | AB60: =INDEX(Valute!B:B,MATCH(J60,Valute!A:A,0)) -> 1 | AC60: =SUMIF(Operazioni!A:A,A60,Operazioni!K:K) -> 62.34375 | AD60: =((I60+AA60)/IF(OR(D60="O",D60="CE"),100,1)*Z60)*AB60+AC60 -> 2062.3438 | AE60: =AD60-W60 -> 62.343754 | AF60: =IF(W60<>0,AE60/W60,"") -> 0.031171877 | AO60: =AC60*(1-N60) -> 54.550781 | AP60: =((I60+AA60)/IF(OR(D60="O",D60="CE"),100,1)*AJ60*(1-AK60)-AL60)*AM60-AN60+AC60 -> 62.34375 | AQ60: =AP60-W60 -> -1937.6562 | AR60: =IF(W60<>0,AQ60/W60,"") -> -0.96882813 | AS60: =(AQ60-AC60)*N60 -> -250 | AT60: =IF(W60<>0,(AQ60-AS60)/W60,"") -> -0.84382813
A61: 58 | B61: 1 | C61: FRANCE-25FB28 0,75 | D61: O | E61: Obblig | F61: EU | G61: Governativo | H61: Francia | I61: 2000 | J61: EUR | K61: FR001400AIN5 | N61: 0.125 | O61: 45715 | P61: MOT | Q61: Directa | R61: 95.52 | S61: 0 | T61: 0 | U61: 1 | V61: 8 | W61: =(I61/IF(OR(D61="O",D61="CE"),100,1)*R61*(1+S61)+T61)*U61+V61 -> 1918.4 | X61: Milano | Y61: Directa | Z61: 100 | AA61: =SUMIF(Operazioni!A:A,A61,Operazioni!C:C) -> 0 | AB61: =INDEX(Valute!B:B,MATCH(J61,Valute!A:A,0)) -> 1 | AC61: =SUMIF(Operazioni!A:A,A61,Operazioni!K:K) -> 13.125 | AD61: =((I61+AA61)/IF(OR(D61="O",D61="CE"),100,1)*Z61)*AB61+AC61 -> 2013.125 | AE61: =AD61-W61 -> 94.725004 | AF61: =IF(W61<>0,AE61/W61,"") -> 0.049377087 | AO61: =AC61*(1-N61) -> 11.484375 | AP61: =((I61+AA61)/IF(OR(D61="O",D61="CE"),100,1)*AJ61*(1-AK61)-AL61)*AM61-AN61+AC61 -> 13.125 | AQ61: =AP61-W61 -> -1905.275 | AR61: =IF(W61<>0,AQ61/W61,"") -> -0.99315836 | AS61: =(AQ61-AC61)*N61 -> -239.8 | AT61: =IF(W61<>0,(AQ61-AS61)/W61,"") -> -0.86815836
A62: 59 | B62: 1 | C62: Vanguard FTSE All-World UCITS ETF (USD) Acc | D62: ETF | E62: Azioni | F62: Mondo | H62: Vanguard | I62: 15 | J62: EUR | K62: IE00BK5BQT80 | L62: VWCE.MI | M62: #VALUE! | N62: 0.26 | O62: 45719 | P62: Milano | Q62: Fineco | R62: 137.01 | S62: 0 | T62: 0 | U62: 1 | V62: 2.95 | W62: =(I62/IF(OR(D62="O",D62="CE"),100,1)*R62*(1+S62)+T62)*U62+V62 -> 2058.1 | X62: Milano | Y62: Fineco | Z62: {=_FV(M62,"Price")} -> 162.56 | AA62: =SUMIF(Operazioni!A:A,A62,Operazioni!C:C) -> 0 | AB62: =INDEX(Valute!B:B,MATCH(J62,Valute!A:A,0)) -> 1 | AC62: =SUMIF(Operazioni!A:A,A62,Operazioni!K:K) -> 0 | AD62: =((I62+AA62)/IF(OR(D62="O",D62="CE"),100,1)*Z62)*AB62+AC62 -> 2438.4 | AE62: =AD62-W62 -> 380.3 | AF62: =IF(W62<>0,AE62/W62,"") -> 0.18478208 | AO62: =AC62*(1-N62) -> 0 | AP62: =((I62+AA62)/IF(OR(D62="O",D62="CE"),100,1)*AJ62*(1-AK62)-AL62)*AM62-AN62+AC62 -> 0 | AQ62: =AP62-W62 -> -2058.1 | AR62: =IF(W62<>0,AQ62/W62,"") -> -1 | AS62: =(AQ62-AC62)*N62 -> -535.106 | AT62: =IF(W62<>0,(AQ62-AS62)/W62,"") -> -0.74
A63: 60 | B63: 1 | C63: Vanguard FTSE All-World UCITS ETF (USD) Acc | D63: ETF | E63: Azioni | F63: Mondo | H63: Vanguard | I63: 8 | J63: EUR | K63: IE00BK5BQT80 | L63: VWCE.MI | M63: #VALUE! | N63: 0.26 | O63: 45748 | P63: Milano | Q63: Fineco | R63: 127.081 | S63: 0 | T63: 0 | U63: 1 | V63: 2.95 | W63: =(I63/IF(OR(D63="O",D63="CE"),100,1)*R63*(1+S63)+T63)*U63+V63 -> 1019.598 | X63: Milano | Y63: Fineco | Z63: {=_FV(M63,"Price")} -> 162.56 | AA63: =SUMIF(Operazioni!A:A,A63,Operazioni!C:C) -> 0 | AB63: =INDEX(Valute!B:B,MATCH(J63,Valute!A:A,0)) -> 1 | AC63: =SUMIF(Operazioni!A:A,A63,Operazioni!K:K) -> 0 | AD63: =((I63+AA63)/IF(OR(D63="O",D63="CE"),100,1)*Z63)*AB63+AC63 -> 1300.48 | AE63: =AD63-W63 -> 280.882 | AF63: =IF(W63<>0,AE63/W63,"") -> 0.27548308 | AO63: =AC63*(1-N63) -> 0 | AP63: =((I63+AA63)/IF(OR(D63="O",D63="CE"),100,1)*AJ63*(1-AK63)-AL63)*AM63-AN63+AC63 -> 0 | AQ63: =AP63-W63 -> -1019.598 | AR63: =IF(W63<>0,AQ63/W63,"") -> -1 | AS63: =(AQ63-AC63)*N63 -> -265.09548 | AT63: =IF(W63<>0,(AQ63-AS63)/W63,"") -> -0.74
A64: 61 | B64: 1 | C64: Vanguard FTSE All-World UCITS ETF (USD) Acc | D64: ETF | E64: Azioni | F64: Mondo | H64: Vanguard | I64: 9 | J64: EUR | K64: IE00BK5BQT80 | L64: VWCE.MI | M64: #VALUE! | N64: 0.26 | O64: 45779 | P64: Milano | Q64: Fineco | R64: 123.69 | S64: 0 | T64: 0 | U64: 1 | V64: 2.95 | W64: =(I64/IF(OR(D64="O",D64="CE"),100,1)*R64*(1+S64)+T64)*U64+V64 -> 1116.16 | X64: Milano | Y64: Fineco | Z64: {=_FV(M64,"Price")} -> 162.56 | AA64: =SUMIF(Operazioni!A:A,A64,Operazioni!C:C) -> 0 | AB64: =INDEX(Valute!B:B,MATCH(J64,Valute!A:A,0)) -> 1 | AC64: =SUMIF(Operazioni!A:A,A64,Operazioni!K:K) -> 0 | AD64: =((I64+AA64)/IF(OR(D64="O",D64="CE"),100,1)*Z64)*AB64+AC64 -> 1463.04 | AE64: =AD64-W64 -> 346.88 | AF64: =IF(W64<>0,AE64/W64,"") -> 0.31077982 | AO64: =AC64*(1-N64) -> 0 | AP64: =((I64+AA64)/IF(OR(D64="O",D64="CE"),100,1)*AJ64*(1-AK64)-AL64)*AM64-AN64+AC64 -> 0 | AQ64: =AP64-W64 -> -1116.16 | AR64: =IF(W64<>0,AQ64/W64,"") -> -1 | AS64: =(AQ64-AC64)*N64 -> -290.2016 | AT64: =IF(W64<>0,(AQ64-AS64)/W64,"") -> -0.74
A65: 62 | B65: 1 | C65: iShares iBonds Dec 2029 Term EUR Corp UCITS ETF (Acc) | D65: ETF | E65: Obblig | F65: EU | G65: Industria | H65: iShares | I65: 880 | J65: EUR | K65: IE000SNLFDR7 | L65: 29GA.MI | M65: #VALUE! | N65: 0.26 | O65: 45793 | P65: Milano | Q65: Directa | R65: 5.202 | S65: 0 | T65: 0 | U65: 1 | V65: 8.7 | W65: =(I65/IF(OR(D65="O",D65="CE"),100,1)*R65*(1+S65)+T65)*U65+V65 -> 4586.46 | X65: Milano | Y65: Directa | Z65: {=_FV(M65,"Price")} -> 5.2686 | AA65: =SUMIF(Operazioni!A:A,A65,Operazioni!C:C) -> 0 | AB65: =INDEX(Valute!B:B,MATCH(J65,Valute!A:A,0)) -> 1 | AC65: =SUMIF(Operazioni!A:A,A65,Operazioni!K:K) -> 0 | AD65: =((I65+AA65)/IF(OR(D65="O",D65="CE"),100,1)*Z65)*AB65+AC65 -> 4636.368 | AE65: =AD65-W65 -> 49.908009 | AF65: =IF(W65<>0,AE65/W65,"") -> 0.010881597 | AO65: =AC65*(1-N65) -> 0 | AP65: =((I65+AA65)/IF(OR(D65="O",D65="CE"),100,1)*AJ65*(1-AK65)-AL65)*AM65-AN65+AC65 -> 0 | AQ65: =AP65-W65 -> -4586.46 | AR65: =IF(W65<>0,AQ65/W65,"") -> -1 | AS65: =(AQ65-AC65)*N65 -> -1192.4796 | AT65: =IF(W65<>0,(AQ65-AS65)/W65,"") -> -0.74
A66: 63 | B66: 1 | C66: BTP ITALIA-4GN32 CUM | D66: O | E66: Obblig | F66: Italia | G66: Governativo | H66: Italia | I66: 2000 | J66: EUR | K66: IT0005648248 | N66: 0.125 | O66: 45812 | P66: Milano | Q66: Fineco | R66: 100 | S66: 0 | T66: 0 | U66: 1 | V66: 0 | W66: =(I66/IF(OR(D66="O",D66="CE"),100,1)*R66*(1+S66)+T66)*U66+V66 -> 2000 | X66: Milano | Y66: Fineco | Z66: 100 | AA66: =SUMIF(Operazioni!A:A,A66,Operazioni!C:C) -> 0 | AB66: =INDEX(Valute!B:B,MATCH(J66,Valute!A:A,0)) -> 1 | AC66: =SUMIF(Operazioni!A:A,A66,Operazioni!K:K) -> 20.265 | AD66: =((I66+AA66)/IF(OR(D66="O",D66="CE"),100,1)*Z66)*AB66+AC66 -> 2020.265 | AE66: =AD66-W66 -> 20.265004 | AF66: =IF(W66<>0,AE66/W66,"") -> 0.010132502 | AO66: =AC66*(1-N66) -> 17.731875 | AP66: =((I66+AA66)/IF(OR(D66="O",D66="CE"),100,1)*AJ66*(1-AK66)-AL66)*AM66-AN66+AC66 -> 20.265 | AQ66: =AP66-W66 -> -1979.735 | AR66: =IF(W66<>0,AQ66/W66,"") -> -0.9898675 | AS66: =(AQ66-AC66)*N66 -> -250 | AT66: =IF(W66<>0,(AQ66-AS66)/W66,"") -> -0.8648675
A67: 64 | B67: 1 | C67: Invesco Physical Gold ETC | D67: ETF | E67: Oro | F67: US | G67: Siderurgia | H67: Invesco | I67: 5 | J67: EUR | K67: IE00B579F325 | L67: SGLD.MI | M67: #VALUE! | N67: 0.26 | O67: 45804 | P67: Milano | Q67: Directa | R67: 279.49 | S67: 0 | T67: 0 | U67: 1 | V67: 2.66 | W67: =(I67/IF(OR(D67="O",D67="CE"),100,1)*R67*(1+S67)+T67)*U67+V67 -> 1400.11 | X67: Milano | Y67: Directa | Z67: {=_FV(M67,"Price")} -> 372.88 | AA67: =SUMIF(Operazioni!A:A,A67,Operazioni!C:C) -> 0 | AB67: =INDEX(Valute!B:B,MATCH(J67,Valute!A:A,0)) -> 1 | AC67: =SUMIF(Operazioni!A:A,A67,Operazioni!K:K) -> 0 | AD67: =((I67+AA67)/IF(OR(D67="O",D67="CE"),100,1)*Z67)*AB67+AC67 -> 1864.4 | AE67: =AD67-W67 -> 464.29 | AF67: =IF(W67<>0,AE67/W67,"") -> 0.33160966 | AO67: =AC67*(1-N67) -> 0 | AP67: =((I67+AA67)/IF(OR(D67="O",D67="CE"),100,1)*AJ67*(1-AK67)-AL67)*AM67-AN67+AC67 -> 0 | AQ67: =AP67-W67 -> -1400.11 | AR67: =IF(W67<>0,AQ67/W67,"") -> -1 | AS67: =(AQ67-AC67)*N67 -> -364.0286 | AT67: =IF(W67<>0,(AQ67-AS67)/W67,"") -> -0.74
A68: 65 | B68: 1 | C68: Vanguard FTSE All-World UCITS ETF (USD) Acc | D68: ETF | E68: Azioni | F68: Mondo | H68: Vanguard | I68: 8 | J68: EUR | K68: IE00BK5BQT80 | L68: VWCE.MI | M68: #VALUE! | N68: 0.26 | O68: 45810 | P68: Milano | Q68: Fineco | R68: 127.42 | S68: 0 | T68: 0 | U68: 1 | V68: 2.95 | W68: =(I68/IF(OR(D68="O",D68="CE"),100,1)*R68*(1+S68)+T68)*U68+V68 -> 1022.31 | X68: Milano | Y68: Fineco | Z68: {=_FV(M68,"Price")} -> 162.56 | AA68: =SUMIF(Operazioni!A:A,A68,Operazioni!C:C) -> 0 | AB68: =INDEX(Valute!B:B,MATCH(J68,Valute!A:A,0)) -> 1 | AC68: =SUMIF(Operazioni!A:A,A68,Operazioni!K:K) -> 0 | AD68: =((I68+AA68)/IF(OR(D68="O",D68="CE"),100,1)*Z68)*AB68+AC68 -> 1300.48 | AE68: =AD68-W68 -> 278.17 | AF68: =IF(W68<>0,AE68/W68,"") -> 0.27209946 | AO68: =AC68*(1-N68) -> 0 | AP68: =((I68+AA68)/IF(OR(D68="O",D68="CE"),100,1)*AJ68*(1-AK68)-AL68)*AM68-AN68+AC68 -> 0 | AQ68: =AP68-W68 -> -1022.31 | AR68: =IF(W68<>0,AQ68/W68,"") -> -1 | AS68: =(AQ68-AC68)*N68 -> -265.8006 | AT68: =IF(W68<>0,(AQ68-AS68)/W68,"") -> -0.74
A69: 66 | B69: 1 | C69: iShares iBonds Dec 2030 Term EUR Corp UCITS ETF EUR (Acc) | D69: ETF | E69: Obblig | F69: EU | G69: Industria | H69: iShares | I69: 476 | J69: EUR | K69: IE000Y2BJVK9 | L69: 30IA.MI | M69: #VALUE! | N69: 0.26 | O69: 45838 | P69: Milano | Q69: Directa | R69: 5.235 | S69: 0 | T69: 0 | U69: 1 | V69: 4.73 | W69: =(I69/IF(OR(D69="O",D69="CE"),100,1)*R69*(1+S69)+T69)*U69+V69 -> 2496.59 | X69: Milano | Y69: Directa | Z69: {=_FV(M69,"Price")} -> 5.309 | AA69: =SUMIF(Operazioni!A:A,A69,Operazioni!C:C) -> 0 | AB69: =INDEX(Valute!B:B,MATCH(J69,Valute!A:A,0)) -> 1 | AC69: =SUMIF(Operazioni!A:A,A69,Operazioni!K:K) -> 0 | AD69: =((I69+AA69)/IF(OR(D69="O",D69="CE"),100,1)*Z69)*AB69+AC69 -> 2527.084 | AE69: =AD69-W69 -> 30.494005 | AF69: =IF(W69<>0,AE69/W69,"") -> 0.012214262 | AO69: =AC69*(1-N69) -> 0 | AP69: =((I69+AA69)/IF(OR(D69="O",D69="CE"),100,1)*AJ69*(1-AK69)-AL69)*AM69-AN69+AC69 -> 0 | AQ69: =AP69-W69 -> -2496.59 | AR69: =IF(W69<>0,AQ69/W69,"") -> -1 | AS69: =(AQ69-AC69)*N69 -> -649.1134 | AT69: =IF(W69<>0,(AQ69-AS69)/W69,"") -> -0.74
A70: 67 | B70: 1 | C70: Vanguard FTSE All-World UCITS ETF (USD) Acc | D70: ETF | E70: Azioni | F70: Mondo | H70: Vanguard | I70: 8 | J70: EUR | K70: IE00BK5BQT80 | L70: VWCE.MI | M70: #VALUE! | N70: 0.26 | O70: 45839 | P70: Milano | Q70: Fineco | R70: 129.56 | S70: 0 | T70: 0 | U70: 1 | V70: 2.95 | W70: =(I70/IF(OR(D70="O",D70="CE"),100,1)*R70*(1+S70)+T70)*U70+V70 -> 1039.43 | X70: Milano | Y70: Fineco | Z70: {=_FV(M70,"Price")} -> 162.56 | AA70: =SUMIF(Operazioni!A:A,A70,Operazioni!C:C) -> 0 | AB70: =INDEX(Valute!B:B,MATCH(J70,Valute!A:A,0)) -> 1 | AC70: =SUMIF(Operazioni!A:A,A70,Operazioni!K:K) -> 0 | AD70: =((I70+AA70)/IF(OR(D70="O",D70="CE"),100,1)*Z70)*AB70+AC70 -> 1300.48 | AE70: =AD70-W70 -> 261.05 | AF70: =IF(W70<>0,AE70/W70,"") -> 0.25114727 | AO70: =AC70*(1-N70) -> 0 | AP70: =((I70+AA70)/IF(OR(D70="O",D70="CE"),100,1)*AJ70*(1-AK70)-AL70)*AM70-AN70+AC70 -> 0 | AQ70: =AP70-W70 -> -1039.43 | AR70: =IF(W70<>0,AQ70/W70,"") -> -1 | AS70: =(AQ70-AC70)*N70 -> -270.2518 | AT70: =IF(W70<>0,(AQ70-AS70)/W70,"") -> -0.74
A71: 68 | B71: 1 | C71: iShares iBonds Dec 2030 Term EUR Corp UCITS ETF EUR (Acc) | D71: ETF | E71: Obblig | F71: EU | G71: Industria | H71: iShares | I71: 400 | J71: EUR | K71: IE000Y2BJVK9 | L71: 30IA.MI | M71: #VALUE! | N71: 0.26 | O71: 45866 | P71: Milano | Q71: Directa | R71: 5.258 | S71: 0 | T71: 0 | U71: 1 | V71: 4 | W71: =(I71/IF(OR(D71="O",D71="CE"),100,1)*R71*(1+S71)+T71)*U71+V71 -> 2107.2 | X71: Milano | Y71: Directa | Z71: {=_FV(M71,"Price")} -> 5.309 | AA71: =SUMIF(Operazioni!A:A,A71,Operazioni!C:C) -> 0 | AB71: =INDEX(Valute!B:B,MATCH(J71,Valute!A:A,0)) -> 1 | AC71: =SUMIF(Operazioni!A:A,A71,Operazioni!K:K) -> 0 | AD71: =((I71+AA71)/IF(OR(D71="O",D71="CE"),100,1)*Z71)*AB71+AC71 -> 2123.6 | AE71: =AD71-W71 -> 16.400004 | AF71: =IF(W71<>0,AE71/W71,"") -> 0.0077828417 | AO71: =AC71*(1-N71) -> 0 | AP71: =((I71+AA71)/IF(OR(D71="O",D71="CE"),100,1)*AJ71*(1-AK71)-AL71)*AM71-AN71+AC71 -> 0 | AQ71: =AP71-W71 -> -2107.2 | AR71: =IF(W71<>0,AQ71/W71,"") -> -1 | AS71: =(AQ71-AC71)*N71 -> -547.872 | AT71: =IF(W71<>0,(AQ71-AS71)/W71,"") -> -0.74
A72: 69 | B72: 1 | C72: Vanguard FTSE All-World UCITS ETF (USD) Acc | D72: ETF | E72: Azioni | F72: Mondo | H72: Vanguard | I72: 8 | J72: EUR | K72: IE00BK5BQT80 | L72: VWCE.MI | M72: #VALUE! | N72: 0.26 | O72: 45873 | P72: Milano | Q72: Fineco | R72: 133.45 | S72: 0 | T72: 0 | U72: 1 | V72: 2.95 | W72: =(I72/IF(OR(D72="O",D72="CE"),100,1)*R72*(1+S72)+T72)*U72+V72 -> 1070.55 | X72: Milano | Y72: Fineco | Z72: {=_FV(M72,"Price")} -> 162.56 | AA72: =SUMIF(Operazioni!A:A,A72,Operazioni!C:C) -> 0 | AB72: =INDEX(Valute!B:B,MATCH(J72,Valute!A:A,0)) -> 1 | AC72: =SUMIF(Operazioni!A:A,A72,Operazioni!K:K) -> 0 | AD72: =((I72+AA72)/IF(OR(D72="O",D72="CE"),100,1)*Z72)*AB72+AC72 -> 1300.48 | AE72: =AD72-W72 -> 229.93 | AF72: =IF(W72<>0,AE72/W72,"") -> 0.21477745 | AO72: =AC72*(1-N72) -> 0 | AP72: =((I72+AA72)/IF(OR(D72="O",D72="CE"),100,1)*AJ72*(1-AK72)-AL72)*AM72-AN72+AC72 -> 0 | AQ72: =AP72-W72 -> -1070.55 | AR72: =IF(W72<>0,AQ72/W72,"") -> -1 | AS72: =(AQ72-AC72)*N72 -> -278.343 | AT72: =IF(W72<>0,(AQ72-AS72)/W72,"") -> -0.74
A73: 70 | B73: 1 | C73: iShares iBonds Dec 2031 Term EUR Corp UCITS ETF EUR (Acc) | D73: ETF | E73: Obblig | F73: EU | G73: Industria | H73: iShares | I73: 670 | J73: EUR | K73: IE000D9WMGF0 | L73: IG31.MI | M73: #VALUE! | N73: 0.26 | O73: 45896 | P73: Milano | Q73: Directa | R73: 5.211 | S73: 0 | T73: 0 | U73: 1 | V73: 6.63 | W73: =(I73/IF(OR(D73="O",D73="CE"),100,1)*R73*(1+S73)+T73)*U73+V73 -> 3498 | X73: Milano | Y73: Directa | Z73: {=_FV(M73,"Price")} -> 5.277 | AA73: =SUMIF(Operazioni!A:A,A73,Operazioni!C:C) -> 0 | AB73: =INDEX(Valute!B:B,MATCH(J73,Valute!A:A,0)) -> 1 | AC73: =SUMIF(Operazioni!A:A,A73,Operazioni!K:K) -> 0 | AD73: =((I73+AA73)/IF(OR(D73="O",D73="CE"),100,1)*Z73)*AB73+AC73 -> 3535.59 | AE73: =AD73-W73 -> 37.590007 | AF73: =IF(W73<>0,AE73/W73,"") -> 0.010746143 | AO73: =AC73*(1-N73) -> 0 | AP73: =((I73+AA73)/IF(OR(D73="O",D73="CE"),100,1)*AJ73*(1-AK73)-AL73)*AM73-AN73+AC73 -> 0 | AQ73: =AP73-W73 -> -3498 | AR73: =IF(W73<>0,AQ73/W73,"") -> -1 | AS73: =(AQ73-AC73)*N73 -> -909.48 | AT73: =IF(W73<>0,(AQ73-AS73)/W73,"") -> -0.74
A74: 71 | B74: 1 | C74: Vanguard FTSE All-World UCITS ETF (USD) Acc | D74: ETF | E74: Azioni | F74: Mondo | H74: Vanguard | I74: 8 | J74: EUR | K74: IE00BK5BQT80 | L74: VWCE.MI | M74: #VALUE! | N74: 0.26 | O74: 45902 | P74: Milano | Q74: Directa | R74: 135.11 | S74: 0 | T74: 0 | U74: 1 | V74: 2.95 | W74: =(I74/IF(OR(D74="O",D74="CE"),100,1)*R74*(1+S74)+T74)*U74+V74 -> 1083.83 | X74: Milano | Y74: Fineco | Z74: {=_FV(M74,"Price")} -> 162.56 | AA74: =SUMIF(Operazioni!A:A,A74,Operazioni!C:C) -> 0 | AB74: =INDEX(Valute!B:B,MATCH(J74,Valute!A:A,0)) -> 1 | AC74: =SUMIF(Operazioni!A:A,A74,Operazioni!K:K) -> 0 | AD74: =((I74+AA74)/IF(OR(D74="O",D74="CE"),100,1)*Z74)*AB74+AC74 -> 1300.48 | AE74: =AD74-W74 -> 216.65 | AF74: =IF(W74<>0,AE74/W74,"") -> 0.19989297 | AO74: =AC74*(1-N74) -> 0 | AP74: =((I74+AA74)/IF(OR(D74="O",D74="CE"),100,1)*AJ74*(1-AK74)-AL74)*AM74-AN74+AC74 -> 0 | AQ74: =AP74-W74 -> -1083.83 | AR74: =IF(W74<>0,AQ74/W74,"") -> -1 | AS74: =(AQ74-AC74)*N74 -> -281.7958 | AT74: =IF(W74<>0,(AQ74-AS74)/W74,"") -> -0.74
A75: 72 | B75: 1 | C75: Vanguard FTSE All-World UCITS ETF (USD) Acc | D75: ETF | E75: Azioni | F75: Mondo | H75: Vanguard | I75: 8 | J75: EUR | K75: IE00BK5BQT80 | L75: VWCE.MI | M75: #VALUE! | N75: 0.26 | O75: 45931 | P75: Milano | Q75: Directa | R75: 140.02 | S75: 0 | T75: 0 | U75: 1 | V75: 2.95 | W75: =(I75/IF(OR(D75="O",D75="CE"),100,1)*R75*(1+S75)+T75)*U75+V75 -> 1123.11 | X75: Milano | Y75: Fineco | Z75: {=_FV(M75,"Price")} -> 162.56 | AA75: =SUMIF(Operazioni!A:A,A75,Operazioni!C:C) -> 0 | AB75: =INDEX(Valute!B:B,MATCH(J75,Valute!A:A,0)) -> 1 | AC75: =SUMIF(Operazioni!A:A,A75,Operazioni!K:K) -> 0 | AD75: =((I75+AA75)/IF(OR(D75="O",D75="CE"),100,1)*Z75)*AB75+AC75 -> 1300.48 | AE75: =AD75-W75 -> 177.37 | AF75: =IF(W75<>0,AE75/W75,"") -> 0.15792754 | AO75: =AC75*(1-N75) -> 0 | AP75: =((I75+AA75)/IF(OR(D75="O",D75="CE"),100,1)*AJ75*(1-AK75)-AL75)*AM75-AN75+AC75 -> 0 | AQ75: =AP75-W75 -> -1123.11 | AR75: =IF(W75<>0,AQ75/W75,"") -> -1 | AS75: =(AQ75-AC75)*N75 -> -292.0086 | AT75: =IF(W75<>0,(AQ75-AS75)/W75,"") -> -0.74
A76: 73 | B76: 1 | C76: BTP VAL-28OT32 CUM | D76: O | E76: Obblig | F76: Italia | G76: Governativo | H76: Italia | I76: 6000 | J76: EUR | K76: IT0005672024 | N76: 0.125 | O76: 45950 | P76: Milano | Q76: Fineco | R76: 100 | S76: 0 | T76: 0 | U76: 1 | V76: 0 | W76: =(I76/IF(OR(D76="O",D76="CE"),100,1)*R76*(1+S76)+T76)*U76+V76 -> 6000 | X76: Milano | Y76: Fineco | Z76: 100 | AA76: =SUMIF(Operazioni!A:A,A76,Operazioni!C:C) -> 0 | AB76: =INDEX(Valute!B:B,MATCH(J76,Valute!A:A,0)) -> 1 | AC76: =SUMIF(Operazioni!A:A,A76,Operazioni!K:K) -> 68.25 | AD76: =((I76+AA76)/IF(OR(D76="O",D76="CE"),100,1)*Z76)*AB76+AC76 -> 6068.25 | AE76: =AD76-W76 -> 68.250011 | AF76: =IF(W76<>0,AE76/W76,"") -> 0.011375002 | AO76: =AC76*(1-N76) -> 59.71875 | AP76: =((I76+AA76)/IF(OR(D76="O",D76="CE"),100,1)*AJ76*(1-AK76)-AL76)*AM76-AN76+AC76 -> 68.25 | AQ76: =AP76-W76 -> -5931.75 | AR76: =IF(W76<>0,AQ76/W76,"") -> -0.988625 | AS76: =(AQ76-AC76)*N76 -> -750 | AT76: =IF(W76<>0,(AQ76-AS76)/W76,"") -> -0.863625
A77: 74 | B77: 1 | C77: Vanguard FTSE All-World UCITS ETF (USD) Acc | D77: ETF | E77: Azioni | F77: Mondo | H77: Vanguard | I77: 8 | J77: EUR | K77: IE00BK5BQT80 | L77: VWCE.MI | M77: #VALUE! | N77: 0.26 | O77: 45964 | P77: Milano | Q77: Fineco | R77: 145.97 | S77: 0 | T77: 0 | U77: 1 | V77: 0 | W77: =(I77/IF(OR(D77="O",D77="CE"),100,1)*R77*(1+S77)+T77)*U77+V77 -> 1167.76 | X77: Milano | Y77: Fineco | Z77: {=_FV(M77,"Price")} -> 162.56 | AA77: =SUMIF(Operazioni!A:A,A77,Operazioni!C:C) -> 0 | AB77: =INDEX(Valute!B:B,MATCH(J77,Valute!A:A,0)) -> 1 | AC77: =SUMIF(Operazioni!A:A,A77,Operazioni!K:K) -> 0 | AD77: =((I77+AA77)/IF(OR(D77="O",D77="CE"),100,1)*Z77)*AB77+AC77 -> 1300.48 | AE77: =AD77-W77 -> 132.72 | AF77: =IF(W77<>0,AE77/W77,"") -> 0.11365349 | AO77: =AC77*(1-N77) -> 0 | AP77: =((I77+AA77)/IF(OR(D77="O",D77="CE"),100,1)*AJ77*(1-AK77)-AL77)*AM77-AN77+AC77 -> 0 | AQ77: =AP77-W77 -> -1167.76 | AR77: =IF(W77<>0,AQ77/W77,"") -> -1 | AS77: =(AQ77-AC77)*N77 -> -303.6176 | AT77: =IF(W77<>0,(AQ77-AS77)/W77,"") -> -0.74
A78: 75 | B78: 1 | C78: Xtrackers II EUR Overnight Rate Swap UCITS ETF 1C | D78: ETF | E78: Obblig | F78: EU | G78: Governativo | H78: Xtrackers | I78: 68 | J78: EUR | K78: LU0290358497 | L78: XEON.MI | M78: #VALUE! | N78: 0.125 | O78: 45992 | P78: Milano | Q78: Fineco | R78: 147.7984 | S78: 0 | T78: 0 | U78: 1 | V78: 0 | W78: =(I78/IF(OR(D78="O",D78="CE"),100,1)*R78*(1+S78)+T78)*U78+V78 -> 10050.291 | X78: Milano | Y78: Fineco | Z78: {=_FV(M78,"Price")} -> 149.2184 | AA78: =SUMIF(Operazioni!A:A,A78,Operazioni!C:C) -> 0 | AB78: =INDEX(Valute!B:B,MATCH(J78,Valute!A:A,0)) -> 1 | AC78: =SUMIF(Operazioni!A:A,A78,Operazioni!K:K) -> 0 | AD78: =((I78+AA78)/IF(OR(D78="O",D78="CE"),100,1)*Z78)*AB78+AC78 -> 10146.851 | AE78: =AD78-W78 -> 96.560019 | AF78: =IF(W78<>0,AE78/W78,"") -> 0.0096076837 | AO78: =AC78*(1-N78) -> 0 | AP78: =((I78+AA78)/IF(OR(D78="O",D78="CE"),100,1)*AJ78*(1-AK78)-AL78)*AM78-AN78+AC78 -> 0 | AQ78: =AP78-W78 -> -10050.291 | AR78: =IF(W78<>0,AQ78/W78,"") -> -1 | AS78: =(AQ78-AC78)*N78 -> -1256.2864 | AT78: =IF(W78<>0,(AQ78-AS78)/W78,"") -> -0.875
A79: 76 | B79: 1 | C79: Xtrackers II Eurozone Gov. Bond 1-3 UCITS ETF 1C | D79: ETF | E79: Obblig | F79: EU | G79: Governativo | H79: Xtrackers | I79: 58 | J79: EUR | K79: LU0290356871 | L79: X13E.MI | M79: #VALUE! | N79: 0.125 | O79: 45992 | P79: Milano | Q79: Fineco | R79: 173.5929 | S79: 0 | T79: 0 | U79: 1 | V79: 0 | W79: =(I79/IF(OR(D79="O",D79="CE"),100,1)*R79*(1+S79)+T79)*U79+V79 -> 10068.388 | X79: Milano | Y79: Fineco | Z79: {=_FV(M79,"Price")} -> 173.95 | AA79: =SUMIF(Operazioni!A:A,A79,Operazioni!C:C) -> 0 | AB79: =INDEX(Valute!B:B,MATCH(J79,Valute!A:A,0)) -> 1 | AC79: =SUMIF(Operazioni!A:A,A79,Operazioni!K:K) -> 0 | AD79: =((I79+AA79)/IF(OR(D79="O",D79="CE"),100,1)*Z79)*AB79+AC79 -> 10089.1 | AE79: =AD79-W79 -> 20.711819 | AF79: =IF(W79<>0,AE79/W79,"") -> 0.0020571137 | AO79: =AC79*(1-N79) -> 0 | AP79: =((I79+AA79)/IF(OR(D79="O",D79="CE"),100,1)*AJ79*(1-AK79)-AL79)*AM79-AN79+AC79 -> 0 | AQ79: =AP79-W79 -> -10068.388 | AR79: =IF(W79<>0,AQ79/W79,"") -> -1 | AS79: =(AQ79-AC79)*N79 -> -1258.5485 | AT79: =IF(W79<>0,(AQ79-AS79)/W79,"") -> -0.875
A80: 77 | B80: 1 | C80: Amundi Euro Government Bond 3-5Y UCITS ETF Acc | D80: ETF | E80: Obblig | F80: EU | G80: Governativo | H80: Amundi | I80: 66 | J80: EUR | K80: LU1650488494 | L80: EM35.MI | M80: #VALUE! | N80: 0.125 | O80: 45992 | P80: Milano | Q80: Fineco | R80: 152.56 | S80: 0 | T80: 0 | U80: 1 | V80: 0 | W80: =(I80/IF(OR(D80="O",D80="CE"),100,1)*R80*(1+S80)+T80)*U80+V80 -> 10068.96 | X80: Milano | Y80: Fineco | Z80: {=_FV(M80,"Price")} -> 152.32 | AA80: =SUMIF(Operazioni!A:A,A80,Operazioni!C:C) -> 0 | AB80: =INDEX(Valute!B:B,MATCH(J80,Valute!A:A,0)) -> 1 | AC80: =SUMIF(Operazioni!A:A,A80,Operazioni!K:K) -> 0 | AD80: =((I80+AA80)/IF(OR(D80="O",D80="CE"),100,1)*Z80)*AB80+AC80 -> 10053.12 | AE80: =AD80-W80 -> -15.839981 | AF80: =IF(W80<>0,AE80/W80,"") -> -0.0015731497 | AO80: =AC80*(1-N80) -> 0 | AP80: =((I80+AA80)/IF(OR(D80="O",D80="CE"),100,1)*AJ80*(1-AK80)-AL80)*AM80-AN80+AC80 -> 0 | AQ80: =AP80-W80 -> -10068.96 | AR80: =IF(W80<>0,AQ80/W80,"") -> -1 | AS80: =(AQ80-AC80)*N80 -> -1258.62 | AT80: =IF(W80<>0,(AQ80-AS80)/W80,"") -> -0.875
A81: 78 | B81: 1 | C81: Xtrackers MSCI World ex USA UCITS ETF 1C | D81: ETF | E81: Azioni | F81: Mondo ex-US | H81: Xtrackers | I81: 292 | J81: EUR | K81: IE0006WW1TQ4 | L81: EXUS.MI | M81: #VALUE! | N81: 0.26 | O81: 45992 | P81: Milano | Q81: Fineco | R81: 34.295 | S81: 0 | T81: 0 | U81: 1 | V81: 0 | W81: =(I81/IF(OR(D81="O",D81="CE"),100,1)*R81*(1+S81)+T81)*U81+V81 -> 10014.14 | X81: Milano | Y81: Fineco | Z81: {=_FV(M81,"Price")} -> 38.67 | AA81: =SUMIF(Operazioni!A:A,A81,Operazioni!C:C) -> 0 | AB81: =INDEX(Valute!B:B,MATCH(J81,Valute!A:A,0)) -> 1 | AC81: =SUMIF(Operazioni!A:A,A81,Operazioni!K:K) -> 0 | AD81: =((I81+AA81)/IF(OR(D81="O",D81="CE"),100,1)*Z81)*AB81+AC81 -> 11291.64 | AE81: =AD81-W81 -> 1277.5 | AF81: =IF(W81<>0,AE81/W81,"") -> 0.12756962 | AO81: =AC81*(1-N81) -> 0 | AP81: =((I81+AA81)/IF(OR(D81="O",D81="CE"),100,1)*AJ81*(1-AK81)-AL81)*AM81-AN81+AC81 -> 0 | AQ81: =AP81-W81 -> -10014.14 | AR81: =IF(W81<>0,AQ81/W81,"") -> -1 | AS81: =(AQ81-AC81)*N81 -> -2603.6764 | AT81: =IF(W81<>0,(AQ81-AS81)/W81,"") -> -0.74
A82: 79 | B82: 1 | C82: iShares Core MSCI EMU UCITS ETF EUR (Acc) | D82: ETF | E82: Azioni | F82: EU | H82: iShares | I82: 46 | J82: EUR | K82: IE00B53QG562 | L82: CSEMU.MI | M82: #VALUE! | N82: 0.26 | O82: 45992 | P82: Milano | Q82: Fineco | R82: 213.25 | S82: 0 | T82: 0 | U82: 1 | V82: 19 | W82: =(I82/IF(OR(D82="O",D82="CE"),100,1)*R82*(1+S82)+T82)*U82+V82 -> 9828.5 | X82: Milano | Y82: Fineco | Z82: {=_FV(M82,"Price")} -> 238.18 | AA82: =SUMIF(Operazioni!A:A,A82,Operazioni!C:C) -> 0 | AB82: =INDEX(Valute!B:B,MATCH(J82,Valute!A:A,0)) -> 1 | AC82: =SUMIF(Operazioni!A:A,A82,Operazioni!K:K) -> 0 | AD82: =((I82+AA82)/IF(OR(D82="O",D82="CE"),100,1)*Z82)*AB82+AC82 -> 10956.28 | AE82: =AD82-W82 -> 1127.78 | AF82: =IF(W82<>0,AE82/W82,"") -> 0.11474589 | AO82: =AC82*(1-N82) -> 0 | AP82: =((I82+AA82)/IF(OR(D82="O",D82="CE"),100,1)*AJ82*(1-AK82)-AL82)*AM82-AN82+AC82 -> 0 | AQ82: =AP82-W82 -> -9828.5 | AR82: =IF(W82<>0,AQ82/W82,"") -> -1 | AS82: =(AQ82-AC82)*N82 -> -2555.41 | AT82: =IF(W82<>0,(AQ82-AS82)/W82,"") -> -0.74
A83: 80 | B83: 1 | C83: Vanguard FTSE All-World UCITS ETF (USD) Acc | D83: ETF | E83: Azioni | F83: Mondo | H83: Vanguard | I83: 8 | J83: EUR | K83: IE00BK5BQT80 | L83: VWCE.MI | M83: #VALUE! | N83: 0.26 | O83: 45992 | P83: Milano | Q83: Fineco | R83: 144.11559 | S83: 0 | T83: 0 | U83: 1 | V83: 2.95 | W83: =(I83/IF(OR(D83="O",D83="CE"),100,1)*R83*(1+S83)+T83)*U83+V83 -> 1155.8747 | X83: Milano | Y83: Fineco | Z83: {=_FV(M83,"Price")} -> 162.56 | AA83: =SUMIF(Operazioni!A:A,A83,Operazioni!C:C) -> 0 | AB83: =INDEX(Valute!B:B,MATCH(J83,Valute!A:A,0)) -> 1 | AC83: =SUMIF(Operazioni!A:A,A83,Operazioni!K:K) -> 0 | AD83: =((I83+AA83)/IF(OR(D83="O",D83="CE"),100,1)*Z83)*AB83+AC83 -> 1300.48 | AE83: =AD83-W83 -> 144.60526 | AF83: =IF(W83<>0,AE83/W83,"") -> 0.12510461 | AO83: =AC83*(1-N83) -> 0 | AP83: =((I83+AA83)/IF(OR(D83="O",D83="CE"),100,1)*AJ83*(1-AK83)-AL83)*AM83-AN83+AC83 -> 0 | AQ83: =AP83-W83 -> -1155.8747 | AR83: =IF(W83<>0,AQ83/W83,"") -> -1 | AS83: =(AQ83-AC83)*N83 -> -300.52743 | AT83: =IF(W83<>0,(AQ83-AS83)/W83,"") -> -0.74
A84: 81 | B84: 1 | C84: Vanguard FTSE All-World UCITS ETF (USD) Acc | D84: ETF | E84: Azioni | F84: Mondo | H84: Vanguard | I84: 8 | J84: EUR | K84: IE00BK5BQT80 | L84: VWCE.MI | M84: #VALUE! | N84: 0.26 | O84: 45662 | P84: Milano | Q84: Fineco | R84: 146.94 | S84: 0 | T84: 0 | U84: 1 | V84: 2.95 | W84: =(I84/IF(OR(D84="O",D84="CE"),100,1)*R84*(1+S84)+T84)*U84+V84 -> 1178.47 | X84: Milano | Y84: Fineco | Z84: {=_FV(M84,"Price")} -> 162.56 | AA84: =SUMIF(Operazioni!A:A,A84,Operazioni!C:C) -> 0 | AB84: =INDEX(Valute!B:B,MATCH(J84,Valute!A:A,0)) -> 1 | AC84: =SUMIF(Operazioni!A:A,A84,Operazioni!K:K) -> 0 | AD84: =((I84+AA84)/IF(OR(D84="O",D84="CE"),100,1)*Z84)*AB84+AC84 -> 1300.48 | AE84: =AD84-W84 -> 122.01 | AF84: =IF(W84<>0,AE84/W84,"") -> 0.10353255 | AO84: =AC84*(1-N84) -> 0 | AP84: =((I84+AA84)/IF(OR(D84="O",D84="CE"),100,1)*AJ84*(1-AK84)-AL84)*AM84-AN84+AC84 -> 0 | AQ84: =AP84-W84 -> -1178.47 | AR84: =IF(W84<>0,AQ84/W84,"") -> -1 | AS84: =(AQ84-AC84)*N84 -> -306.4022 | AT84: =IF(W84<>0,(AQ84-AS84)/W84,"") -> -0.74
A85: 82 | B85: 1 | C85: Vanguard FTSE All-World UCITS ETF (USD) Acc | D85: ETF | E85: Azioni | F85: Mondo | H85: Vanguard | I85: 7 | J85: EUR | K85: IE00BK5BQT80 | L85: VWCE.MI | M85: #VALUE! | N85: 0.26 | O85: 46055 | P85: Milano | Q85: Fineco | R85: 148.04 | S85: 0 | T85: 0 | U85: 1 | V85: 2.95 | W85: =(I85/IF(OR(D85="O",D85="CE"),100,1)*R85*(1+S85)+T85)*U85+V85 -> 1039.23 | X85: Milano | Y85: Fineco | Z85: {=_FV(M85,"Price")} -> 162.56 | AA85: =SUMIF(Operazioni!A:A,A85,Operazioni!C:C) -> 0 | AB85: =INDEX(Valute!B:B,MATCH(J85,Valute!A:A,0)) -> 1 | AC85: =SUMIF(Operazioni!A:A,A85,Operazioni!K:K) -> 0 | AD85: =((I85+AA85)/IF(OR(D85="O",D85="CE"),100,1)*Z85)*AB85+AC85 -> 1137.92 | AE85: =AD85-W85 -> 98.690002 | AF85: =IF(W85<>0,AE85/W85,"") -> 0.094964543 | AO85: =AC85*(1-N85) -> 0 | AP85: =((I85+AA85)/IF(OR(D85="O",D85="CE"),100,1)*AJ85*(1-AK85)-AL85)*AM85-AN85+AC85 -> 0 | AQ85: =AP85-W85 -> -1039.23 | AR85: =IF(W85<>0,AQ85/W85,"") -> -1 | AS85: =(AQ85-AC85)*N85 -> -270.1998 | AT85: =IF(W85<>0,(AQ85-AS85)/W85,"") -> -0.74
A86: 83 | B86: 1 | C86: BTP-10MZ32 VAL CUM | D86: O | E86: Obblig | F86: Italia | G86: Governativo | H86: Italia | I86: 6000 | J86: EUR | K86: IT0005696320 | N86: 0.125 | O86: 46083 | P86: Milano | Q86: Fineco | R86: 100 | S86: 0 | T86: 0 | U86: 1 | V86: 0 | W86: =(I86/IF(OR(D86="O",D86="CE"),100,1)*R86*(1+S86)+T86)*U86+V86 -> 6000 | X86: Milano | Y86: Fineco | Z86: 100 | AA86: =SUMIF(Operazioni!A:A,A86,Operazioni!C:C) -> 0 | AB86: =INDEX(Valute!B:B,MATCH(J86,Valute!A:A,0)) -> 1 | AC86: =SUMIF(Operazioni!A:A,A86,Operazioni!K:K) -> 0 | AD86: =((I86+AA86)/IF(OR(D86="O",D86="CE"),100,1)*Z86)*AB86+AC86 -> 6000 | AE86: =AD86-W86 -> 1.1351479e-05 | AF86: =IF(W86<>0,AE86/W86,"") -> 1.8919131e-09 | AO86: =AC86*(1-N86) -> 0 | AP86: =((I86+AA86)/IF(OR(D86="O",D86="CE"),100,1)*AJ86*(1-AK86)-AL86)*AM86-AN86+AC86 -> 0 | AQ86: =AP86-W86 -> -6000 | AR86: =IF(W86<>0,AQ86/W86,"") -> -1 | AS86: =(AQ86-AC86)*N86 -> -750 | AT86: =IF(W86<>0,(AQ86-AS86)/W86,"") -> -0.875
A87: 84 | B87: 1 | C87: Vanguard FTSE All-World UCITS ETF (USD) Acc | D87: ETF | E87: Azioni | F87: Mondo | H87: Vanguard | I87: 7 | J87: EUR | K87: IE00BK5BQT80 | L87: VWCE.MI | M87: #VALUE! | N87: 0.26 | O87: 46083 | P87: Milano | Q87: Fineco | R87: 149.7 | S87: 0 | T87: 0 | U87: 1 | V87: 2.95 | W87: =(I87/IF(OR(D87="O",D87="CE"),100,1)*R87*(1+S87)+T87)*U87+V87 -> 1050.85 | X87: Milano | Y87: Fineco | Z87: {=_FV(M87,"Price")} -> 162.56 | AA87: =SUMIF(Operazioni!A:A,A87,Operazioni!C:C) -> 0 | AB87: =INDEX(Valute!B:B,MATCH(J87,Valute!A:A,0)) -> 1 | AC87: =SUMIF(Operazioni!A:A,A87,Operazioni!K:K) -> 0 | AD87: =((I87+AA87)/IF(OR(D87="O",D87="CE"),100,1)*Z87)*AB87+AC87 -> 1137.92 | AE87: =AD87-W87 -> 87.070002 | AF87: =IF(W87<>0,AE87/W87,"") -> 0.082856737 | AO87: =AC87*(1-N87) -> 0 | AP87: =((I87+AA87)/IF(OR(D87="O",D87="CE"),100,1)*AJ87*(1-AK87)-AL87)*AM87-AN87+AC87 -> 0 | AQ87: =AP87-W87 -> -1050.85 | AR87: =IF(W87<>0,AQ87/W87,"") -> -1 | AS87: =(AQ87-AC87)*N87 -> -273.221 | AT87: =IF(W87<>0,(AQ87-AS87)/W87,"") -> -0.74
A88: 85 | B88: 1 | C88: Vanguard FTSE All-World UCITS ETF (USD) Acc | D88: ETF | E88: Azioni | F88: Mondo | H88: Vanguard | I88: 7 | J88: EUR | K88: IE00BK5BQT80 | L88: VWCE.MI | M88: #VALUE! | N88: 0.26 | O88: 46113 | P88: Milano | Q88: Fineco | R88: 144.39 | S88: 0 | T88: 0 | U88: 1 | V88: 2.95 | W88: =(I88/IF(OR(D88="O",D88="CE"),100,1)*R88*(1+S88)+T88)*U88+V88 -> 1013.68 | X88: Milano | Y88: Fineco | Z88: {=_FV(M88,"Price")} -> 162.56 | AA88: =SUMIF(Operazioni!A:A,A88,Operazioni!C:C) -> 0 | AB88: =INDEX(Valute!B:B,MATCH(J88,Valute!A:A,0)) -> 1 | AC88: =SUMIF(Operazioni!A:A,A88,Operazioni!K:K) -> 0 | AD88: =((I88+AA88)/IF(OR(D88="O",D88="CE"),100,1)*Z88)*AB88+AC88 -> 1137.92 | AE88: =AD88-W88 -> 124.24 | AF88: =IF(W88<>0,AE88/W88,"") -> 0.12256334 | AO88: =AC88*(1-N88) -> 0 | AP88: =((I88+AA88)/IF(OR(D88="O",D88="CE"),100,1)*AJ88*(1-AK88)-AL88)*AM88-AN88+AC88 -> 0 | AQ88: =AP88-W88 -> -1013.68 | AR88: =IF(W88<>0,AQ88/W88,"") -> -1 | AS88: =(AQ88-AC88)*N88 -> -263.5568 | AT88: =IF(W88<>0,(AQ88-AS88)/W88,"") -> -0.74
A89: 86 | B89: 1 | C89: Vanguard FTSE All-World UCITS ETF (USD) Acc | D89: ETF | E89: Azioni | F89: Mondo | H89: Vanguard | I89: 7 | J89: EUR | K89: IE00BK5BQT80 | L89: VWCE.MI | M89: #VALUE! | N89: 0.26 | O89: 46147 | P89: Milano | Q89: Fineco | R89: 155.87 | S89: 0 | T89: 0 | U89: 1 | V89: 2.95 | W89: =(I89/IF(OR(D89="O",D89="CE"),100,1)*R89*(1+S89)+T89)*U89+V89 -> 1094.04 | X89: Milano | Y89: Fineco | Z89: {=_FV(M89,"Price")} -> 162.56 | AA89: =SUMIF(Operazioni!A:A,A89,Operazioni!C:C) -> 0 | AB89: =INDEX(Valute!B:B,MATCH(J89,Valute!A:A,0)) -> 1 | AC89: =SUMIF(Operazioni!A:A,A89,Operazioni!K:K) -> 0 | AD89: =((I89+AA89)/IF(OR(D89="O",D89="CE"),100,1)*Z89)*AB89+AC89 -> 1137.92 | AE89: =AD89-W89 -> 43.880002 | AF89: =IF(W89<>0,AE89/W89,"") -> 0.040108225 | AO89: =AC89*(1-N89) -> 0 | AP89: =((I89+AA89)/IF(OR(D89="O",D89="CE"),100,1)*AJ89*(1-AK89)-AL89)*AM89-AN89+AC89 -> 0 | AQ89: =AP89-W89 -> -1094.04 | AR89: =IF(W89<>0,AQ89/W89,"") -> -1 | AS89: =(AQ89-AC89)*N89 -> -284.4504 | AT89: =IF(W89<>0,(AQ89-AS89)/W89,"") -> -0.74
W90: =(I90/IF(OR(D90="O",D90="CE"),100,1)*R90*(1+S90)+T90)*U90+V90 -> 0 | AA90: =SUMIF(Operazioni!A:A,A90,Operazioni!C:C) -> 0 | AB90: =INDEX(Valute!B:B,MATCH(J90,Valute!A:A,0)) -> #N/A | AC90: =SUMIF(Operazioni!A:A,A90,Operazioni!K:K) -> 0 | AD90: =((I90+AA90)/IF(OR(D90="O",D90="CE"),100,1)*Z90)*AB90+AC90 -> #N/A | AE90: =AD90-W90 -> #N/A | AF90: =IF(W90<>0,AE90/W90,"") | AO90: =AC90*(1-N90) -> 0 | AP90: =((I90+AA90)/IF(OR(D90="O",D90="CE"),100,1)*AJ90*(1-AK90)-AL90)*AM90-AN90+AC90 -> 0 | AQ90: =AP90-W90 -> 0 | AR90: =IF(W90<>0,AQ90/W90,"") | AS90: =(AQ90-AC90)*N90 -> 0 | AT90: =IF(W90<>0,(AQ90-AS90)/W90,"")
W91: =(I91/IF(OR(D91="O",D91="CE"),100,1)*R91*(1+S91)+T91)*U91+V91 -> 0 | AA91: =SUMIF(Operazioni!A:A,A91,Operazioni!C:C) -> 0 | AB91: =INDEX(Valute!B:B,MATCH(J91,Valute!A:A,0)) -> #N/A | AC91: =SUMIF(Operazioni!A:A,A91,Operazioni!K:K) -> 0 | AD91: =((I91+AA91)/IF(OR(D91="O",D91="CE"),100,1)*Z91)*AB91+AC91 -> #N/A | AE91: =AD91-W91 -> #N/A | AF91: =IF(W91<>0,AE91/W91,"") | AO91: =AC91*(1-N91) -> 0 | AP91: =((I91+AA91)/IF(OR(D91="O",D91="CE"),100,1)*AJ91*(1-AK91)-AL91)*AM91-AN91+AC91 -> 0 | AQ91: =AP91-W91 -> 0 | AR91: =IF(W91<>0,AQ91/W91,"") | AS91: =(AQ91-AC91)*N91 -> 0 | AT91: =IF(W91<>0,(AQ91-AS91)/W91,"")
W92: =(I92/IF(OR(D92="O",D92="CE"),100,1)*R92*(1+S92)+T92)*U92+V92 -> 0 | AA92: =SUMIF(Operazioni!A:A,A92,Operazioni!C:C) -> 0 | AB92: =INDEX(Valute!B:B,MATCH(J92,Valute!A:A,0)) -> #N/A | AC92: =SUMIF(Operazioni!A:A,A92,Operazioni!K:K) -> 0 | AD92: =((I92+AA92)/IF(OR(D92="O",D92="CE"),100,1)*Z92)*AB92+AC92 -> #N/A | AE92: =AD92-W92 -> #N/A | AF92: =IF(W92<>0,AE92/W92,"") | AO92: =AC92*(1-N92) -> 0 | AP92: =((I92+AA92)/IF(OR(D92="O",D92="CE"),100,1)*AJ92*(1-AK92)-AL92)*AM92-AN92+AC92 -> 0 | AQ92: =AP92-W92 -> 0 | AR92: =IF(W92<>0,AQ92/W92,"") | AS92: =(AQ92-AC92)*N92 -> 0 | AT92: =IF(W92<>0,(AQ92-AS92)/W92,"")
W93: =(I93/IF(OR(D93="O",D93="CE"),100,1)*R93*(1+S93)+T93)*U93+V93 -> 0 | AA93: =SUMIF(Operazioni!A:A,A93,Operazioni!C:C) -> 0 | AB93: =INDEX(Valute!B:B,MATCH(J93,Valute!A:A,0)) -> #N/A | AC93: =SUMIF(Operazioni!A:A,A93,Operazioni!K:K) -> 0 | AD93: =((I93+AA93)/IF(OR(D93="O",D93="CE"),100,1)*Z93)*AB93+AC93 -> #N/A | AE93: =AD93-W93 -> #N/A | AF93: =IF(W93<>0,AE93/W93,"") | AO93: =AC93*(1-N93) -> 0 | AP93: =((I93+AA93)/IF(OR(D93="O",D93="CE"),100,1)*AJ93*(1-AK93)-AL93)*AM93-AN93+AC93 -> 0 | AQ93: =AP93-W93 -> 0 | AR93: =IF(W93<>0,AQ93/W93,"") | AS93: =(AQ93-AC93)*N93 -> 0 | AT93: =IF(W93<>0,(AQ93-AS93)/W93,"")
W94: =(I94/IF(OR(D94="O",D94="CE"),100,1)*R94*(1+S94)+T94)*U94+V94 -> 0 | AA94: =SUMIF(Operazioni!A:A,A94,Operazioni!C:C) -> 0 | AB94: =INDEX(Valute!B:B,MATCH(J94,Valute!A:A,0)) -> #N/A | AC94: =SUMIF(Operazioni!A:A,A94,Operazioni!K:K) -> 0 | AD94: =((I94+AA94)/IF(OR(D94="O",D94="CE"),100,1)*Z94)*AB94+AC94 -> #N/A | AE94: =AD94-W94 -> #N/A | AF94: =IF(W94<>0,AE94/W94,"") | AO94: =AC94*(1-N94) -> 0 | AP94: =((I94+AA94)/IF(OR(D94="O",D94="CE"),100,1)*AJ94*(1-AK94)-AL94)*AM94-AN94+AC94 -> 0 | AQ94: =AP94-W94 -> 0 | AR94: =IF(W94<>0,AQ94/W94,"") | AS94: =(AQ94-AC94)*N94 -> 0 | AT94: =IF(W94<>0,(AQ94-AS94)/W94,"")
W95: =(I95/IF(OR(D95="O",D95="CE"),100,1)*R95*(1+S95)+T95)*U95+V95 -> 0 | AA95: =SUMIF(Operazioni!A:A,A95,Operazioni!C:C) -> 0 | AB95: =INDEX(Valute!B:B,MATCH(J95,Valute!A:A,0)) -> #N/A | AC95: =SUMIF(Operazioni!A:A,A95,Operazioni!K:K) -> 0 | AD95: =((I95+AA95)/IF(OR(D95="O",D95="CE"),100,1)*Z95)*AB95+AC95 -> #N/A | AE95: =AD95-W95 -> #N/A | AF95: =IF(W95<>0,AE95/W95,"") | AO95: =AC95*(1-N95) -> 0 | AP95: =((I95+AA95)/IF(OR(D95="O",D95="CE"),100,1)*AJ95*(1-AK95)-AL95)*AM95-AN95+AC95 -> 0 | AQ95: =AP95-W95 -> 0 | AR95: =IF(W95<>0,AQ95/W95,"") | AS95: =(AQ95-AC95)*N95 -> 0 | AT95: =IF(W95<>0,(AQ95-AS95)/W95,"")
W96: =(I96/IF(OR(D96="O",D96="CE"),100,1)*R96*(1+S96)+T96)*U96+V96 -> 0 | AA96: =SUMIF(Operazioni!A:A,A96,Operazioni!C:C) -> 0 | AB96: =INDEX(Valute!B:B,MATCH(J96,Valute!A:A,0)) -> #N/A | AC96: =SUMIF(Operazioni!A:A,A96,Operazioni!K:K) -> 0 | AD96: =((I96+AA96)/IF(OR(D96="O",D96="CE"),100,1)*Z96)*AB96+AC96 -> #N/A | AE96: =AD96-W96 -> #N/A | AF96: =IF(W96<>0,AE96/W96,"") | AO96: =AC96*(1-N96) -> 0 | AP96: =((I96+AA96)/IF(OR(D96="O",D96="CE"),100,1)*AJ96*(1-AK96)-AL96)*AM96-AN96+AC96 -> 0 | AQ96: =AP96-W96 -> 0 | AR96: =IF(W96<>0,AQ96/W96,"") | AS96: =(AQ96-AC96)*N96 -> 0 | AT96: =IF(W96<>0,(AQ96-AS96)/W96,"")
W97: =(I97/IF(OR(D97="O",D97="CE"),100,1)*R97*(1+S97)+T97)*U97+V97 -> 0 | AA97: =SUMIF(Operazioni!A:A,A97,Operazioni!C:C) -> 0 | AB97: =INDEX(Valute!B:B,MATCH(J97,Valute!A:A,0)) -> #N/A | AC97: =SUMIF(Operazioni!A:A,A97,Operazioni!K:K) -> 0 | AD97: =((I97+AA97)/IF(OR(D97="O",D97="CE"),100,1)*Z97)*AB97+AC97 -> #N/A | AE97: =AD97-W97 -> #N/A | AF97: =IF(W97<>0,AE97/W97,"") | AO97: =AC97*(1-N97) -> 0 | AP97: =((I97+AA97)/IF(OR(D97="O",D97="CE"),100,1)*AJ97*(1-AK97)-AL97)*AM97-AN97+AC97 -> 0 | AQ97: =AP97-W97 -> 0 | AR97: =IF(W97<>0,AQ97/W97,"") | AS97: =(AQ97-AC97)*N97 -> 0 | AT97: =IF(W97<>0,(AQ97-AS97)/W97,"")
W98: =(I98/IF(OR(D98="O",D98="CE"),100,1)*R98*(1+S98)+T98)*U98+V98 -> 0 | AA98: =SUMIF(Operazioni!A:A,A98,Operazioni!C:C) -> 0 | AB98: =INDEX(Valute!B:B,MATCH(J98,Valute!A:A,0)) -> #N/A | AC98: =SUMIF(Operazioni!A:A,A98,Operazioni!K:K) -> 0 | AD98: =((I98+AA98)/IF(OR(D98="O",D98="CE"),100,1)*Z98)*AB98+AC98 -> #N/A | AE98: =AD98-W98 -> #N/A | AF98: =IF(W98<>0,AE98/W98,"") | AO98: =AC98*(1-N98) -> 0 | AP98: =((I98+AA98)/IF(OR(D98="O",D98="CE"),100,1)*AJ98*(1-AK98)-AL98)*AM98-AN98+AC98 -> 0 | AQ98: =AP98-W98 -> 0 | AR98: =IF(W98<>0,AQ98/W98,"") | AS98: =(AQ98-AC98)*N98 -> 0 | AT98: =IF(W98<>0,(AQ98-AS98)/W98,"")
W99: =(I99/IF(OR(D99="O",D99="CE"),100,1)*R99*(1+S99)+T99)*U99+V99 -> 0 | AA99: =SUMIF(Operazioni!A:A,A99,Operazioni!C:C) -> 0 | AB99: =INDEX(Valute!B:B,MATCH(J99,Valute!A:A,0)) -> #N/A | AC99: =SUMIF(Operazioni!A:A,A99,Operazioni!K:K) -> 0 | AD99: =((I99+AA99)/IF(OR(D99="O",D99="CE"),100,1)*Z99)*AB99+AC99 -> #N/A | AE99: =AD99-W99 -> #N/A | AF99: =IF(W99<>0,AE99/W99,"") | AO99: =AC99*(1-N99) -> 0 | AP99: =((I99+AA99)/IF(OR(D99="O",D99="CE"),100,1)*AJ99*(1-AK99)-AL99)*AM99-AN99+AC99 -> 0 | AQ99: =AP99-W99 -> 0 | AR99: =IF(W99<>0,AQ99/W99,"") | AS99: =(AQ99-AC99)*N99 -> 0 | AT99: =IF(W99<>0,(AQ99-AS99)/W99,"")
W100: =(I100/IF(OR(D100="O",D100="CE"),100,1)*R100*(1+S100)+T100)*U100+V100 -> 0 | AA100: =SUMIF(Operazioni!A:A,A100,Operazioni!C:C) -> 0 | AB100: =INDEX(Valute!B:B,MATCH(J100,Valute!A:A,0)) -> #N/A | AC100: =SUMIF(Operazioni!A:A,A100,Operazioni!K:K) -> 0 | AD100: =((I100+AA100)/IF(OR(D100="O",D100="CE"),100,1)*Z100)*AB100+AC100 -> #N/A | AE100: =AD100-W100 -> #N/A | AF100: =IF(W100<>0,AE100/W100,"") | AO100: =AC100*(1-N100) -> 0 | AP100: =((I100+AA100)/IF(OR(D100="O",D100="CE"),100,1)*AJ100*(1-AK100)-AL100)*AM100-AN100+AC100 -> 0 | AQ100: =AP100-W100 -> 0 | AR100: =IF(W100<>0,AQ100/W100,"") | AS100: =(AQ100-AC100)*N100 -> 0 | AT100: =IF(W100<>0,(AQ100-AS100)/W100,"")
...

Sheet Operazioni
A1: ID | B1: Data | C1: Variazione quantità | D1: Dividendi valuta | E1: Cambio | F1: Dividendi euro | G1: Valuta | H1: Dividendi lordi | I1: Tassazione | J1: Tasse | K1: Dividendi totali netti euro | L1: Note
A2: 21 | B2: 44430 | E2: 1 | F2: 0.38 | G2: =INDEX('Stato patrimoniale'!J:J,MATCH(A2,'Stato patrimoniale'!A:A,0)) -> USD | H2: =F2+D2*E2 -> 0.38 | I2: =INDEX('Stato patrimoniale'!N:N,MATCH(A2,'Stato patrimoniale'!A:A,0)) -> 0.26 | J2: =H2*I2 -> 0.0988 | K2: =H2-(H2*I2) -> 0.2812 | M2: Totale lordo: | N2: =SUM(H2:H1002) -> 5225.5508
A3: 23 | B3: 44452 | E3: 1 | F3: 29.09 | G3: =INDEX('Stato patrimoniale'!J:J,MATCH(A3,'Stato patrimoniale'!A:A,0)) -> USD | H3: =F3+D3*E3 -> 29.09 | I3: =INDEX('Stato patrimoniale'!N:N,MATCH(A3,'Stato patrimoniale'!A:A,0)) -> 0.26 | J3: =H3*I3 -> 7.5634 | K3: =H3-(H3*I3) -> 21.5266 | M3: Totale netto: | N3: =SUM(K2:K1002) -> 4409.5011
A4: 21 | B4: 44516 | E4: 1 | F4: 0.33 | G4: =INDEX('Stato patrimoniale'!J:J,MATCH(A4,'Stato patrimoniale'!A:A,0)) -> USD | H4: =F4+D4*E4 -> 0.33 | I4: =INDEX('Stato patrimoniale'!N:N,MATCH(A4,'Stato patrimoniale'!A:A,0)) -> 0.26 | J4: =H4*I4 -> 0.0858 | K4: =H4-(H4*I4) -> 0.2442
A5: 23 | B5: 44545 | E5: 1 | F5: 29 | G5: =INDEX('Stato patrimoniale'!J:J,MATCH(A5,'Stato patrimoniale'!A:A,0)) -> USD | H5: =F5+D5*E5 -> 29 | I5: =INDEX('Stato patrimoniale'!N:N,MATCH(A5,'Stato patrimoniale'!A:A,0)) -> 0.26 | J5: =H5*I5 -> 7.54 | K5: =H5-(H5*I5) -> 21.46
A6: 21 | B6: 44607 | E6: 1 | F6: 0.33 | G6: =INDEX('Stato patrimoniale'!J:J,MATCH(A6,'Stato patrimoniale'!A:A,0)) -> USD | H6: =F6+D6*E6 -> 0.33 | I6: =INDEX('Stato patrimoniale'!N:N,MATCH(A6,'Stato patrimoniale'!A:A,0)) -> 0.26 | J6: =H6*I6 -> 0.0858 | K6: =H6-(H6*I6) -> 0.2442
A7: 23 | B7: 44637 | E7: 1 | F7: 37.2 | G7: =INDEX('Stato patrimoniale'!J:J,MATCH(A7,'Stato patrimoniale'!A:A,0)) -> USD | H7: =F7+D7*E7 -> 37.2 | I7: =INDEX('Stato patrimoniale'!N:N,MATCH(A7,'Stato patrimoniale'!A:A,0)) -> 0.26 | J7: =H7*I7 -> 9.672 | K7: =H7-(H7*I7) -> 27.528
A8: 21 | B8: 44697 | E8: 1 | F8: 0.37 | G8: =INDEX('Stato patrimoniale'!J:J,MATCH(A8,'Stato patrimoniale'!A:A,0)) -> USD | H8: =F8+D8*E8 -> 0.37 | I8: =INDEX('Stato patrimoniale'!N:N,MATCH(A8,'Stato patrimoniale'!A:A,0)) -> 0.26 | J8: =H8*I8 -> 0.0962 | K8: =H8-(H8*I8) -> 0.2738
A9: 23 | B9: 44726 | E9: 1 | F9: 39.33 | G9: =INDEX('Stato patrimoniale'!J:J,MATCH(A9,'Stato patrimoniale'!A:A,0)) -> USD | H9: =F9+D9*E9 -> 39.33 | I9: =INDEX('Stato patrimoniale'!N:N,MATCH(A9,'Stato patrimoniale'!A:A,0)) -> 0.26 | J9: =H9*I9 -> 10.2258 | K9: =H9-(H9*I9) -> 29.1042
A10: 21 | B10: 44789 | E10: 1 | F10: 0.38 | G10: =INDEX('Stato patrimoniale'!J:J,MATCH(A10,'Stato patrimoniale'!A:A,0)) -> USD | H10: =F10+D10*E10 -> 0.38 | I10: =INDEX('Stato patrimoniale'!N:N,MATCH(A10,'Stato patrimoniale'!A:A,0)) -> 0.26 | J10: =H10*I10 -> 0.0988 | K10: =H10-(H10*I10) -> 0.2812
A11: 23 | B11: 44817 | E11: 1 | F11: 40.4 | G11: =INDEX('Stato patrimoniale'!J:J,MATCH(A11,'Stato patrimoniale'!A:A,0)) -> USD | H11: =F11+D11*E11 -> 40.4 | I11: =INDEX('Stato patrimoniale'!N:N,MATCH(A11,'Stato patrimoniale'!A:A,0)) -> 0.26 | J11: =H11*I11 -> 10.504 | K11: =H11-(H11*I11) -> 29.896
A12: 21 | B12: 44825 | E12: 1 | F12: 0.37 | G12: =INDEX('Stato patrimoniale'!J:J,MATCH(A12,'Stato patrimoniale'!A:A,0)) -> USD | H12: =F12+D12*E12 -> 0.37 | I12: =INDEX('Stato patrimoniale'!N:N,MATCH(A12,'Stato patrimoniale'!A:A,0)) -> 0.26 | J12: =H12*I12 -> 0.0962 | K12: =H12-(H12*I12) -> 0.2738
A13: 21 | B13: 44879 | E13: 1 | F13: 0.38 | G13: =INDEX('Stato patrimoniale'!J:J,MATCH(A13,'Stato patrimoniale'!A:A,0)) -> USD | H13: =F13+D13*E13 -> 0.38 | I13: =INDEX('Stato patrimoniale'!N:N,MATCH(A13,'Stato patrimoniale'!A:A,0)) -> 0.26 | J13: =H13*I13 -> 0.0988 | K13: =H13-(H13*I13) -> 0.2812
A14: 23 | B14: 44910 | E14: 1 | F14: 42.44 | G14: =INDEX('Stato patrimoniale'!J:J,MATCH(A14,'Stato patrimoniale'!A:A,0)) -> USD | H14: =F14+D14*E14 -> 42.44 | I14: =INDEX('Stato patrimoniale'!N:N,MATCH(A14,'Stato patrimoniale'!A:A,0)) -> 0.26 | J14: =H14*I14 -> 11.0344 | K14: =H14-(H14*I14) -> 31.4056
A15: 21 | B15: 44977 | E15: 1 | F15: 0.37 | G15: =INDEX('Stato patrimoniale'!J:J,MATCH(A15,'Stato patrimoniale'!A:A,0)) -> USD | H15: =F15+D15*E15 -> 0.37 | I15: =INDEX('Stato patrimoniale'!N:N,MATCH(A15,'Stato patrimoniale'!A:A,0)) -> 0.26 | J15: =H15*I15 -> 0.0962 | K15: =H15-(H15*I15) -> 0.2738
... A17: 21 | B17: 45070 | E17: 1 | F17: 0.38 | G17: =INDEX('Stato patrimoniale'!J:J,MATCH(A17,'Stato patrimoniale'!A:A,0)) -> USD | H17: =F17+D17*E17 -> 0.38 | I17: =INDEX('Stato patrimoniale'!N:N,MATCH(A17,'Stato patrimoniale'!A:A,0)) -> 0.26 | J17: =H17*I17 -> 0.0988 | K17: =H17-(H17*I17) -> 0.2812
A18: 20 | B18: 45070 | D18: 0.88 | E18: 1 | G18: =INDEX('Stato patrimoniale'!J:J,MATCH(A18,'Stato patrimoniale'!A:A,0)) -> EUR | H18: =F18+D18*E18 -> 0.88 | I18: =INDEX('Stato patrimoniale'!N:N,MATCH(A18,'Stato patrimoniale'!A:A,0)) -> 0.26 | J18: =H18*I18 -> 0.2288 | K18: =H18-(H18*I18) -> 0.6512
A19: 23 | B19: 45089 | E19: 1 | F19: 42.42 | G19: =INDEX('Stato patrimoniale'!J:J,MATCH(A19,'Stato patrimoniale'!A:A,0)) -> USD | H19: =F19+D19*E19 -> 42.42 | I19: =INDEX('Stato patrimoniale'!N:N,MATCH(A19,'Stato patrimoniale'!A:A,0)) -> 0.26 | J19: =H19*I19 -> 11.0292 | K19: =H19-(H19*I19) -> 31.3908
A20: 19 | B20: 45133 | D20: 1.6 | E20: 1 | G20: =INDEX('Stato patrimoniale'!J:J,MATCH(A20,'Stato patrimoniale'!A:A,0)) -> EUR | H20: =F20+D20*E20 -> 1.6 | I20: =INDEX('Stato patrimoniale'!N:N,MATCH(A20,'Stato patrimoniale'!A:A,0)) -> 0.26 | J20: =H20*I20 -> 0.416 | K20: =H20-(H20*I20) -> 1.184
A21: 11 | B21: 45154 | D21: 149.99 | E21: 0.917 | G21: =INDEX('Stato patrimoniale'!J:J,MATCH(A21,'Stato patrimoniale'!A:A,0)) -> USD | H21: =F21+D21*E21 -> 137.54083 | I21: =INDEX('Stato patrimoniale'!N:N,MATCH(A21,'Stato patrimoniale'!A:A,0)) -> 0.125 | J21: =H21*I21 -> 17.192604 | K21: =H21-(H21*I21) -> 120.34823
A22: 23 | B22: 45188 | E22: 1 | F22: 37.4 | G22: =INDEX('Stato patrimoniale'!J:J,MATCH(A22,'Stato patrimoniale'!A:A,0)) -> USD | H22: =F22+D22*E22 -> 37.4 | I22: =INDEX('Stato patrimoniale'!N:N,MATCH(A22,'Stato patrimoniale'!A:A,0)) -> 0.26 | J22: =H22*I22 -> 9.724 | K22: =H22-(H22*I22) -> 27.676
A23: 20 | B23: 45189 | D23: 4.56 | E23: 1 | G23: =INDEX('Stato patrimoniale'!J:J,MATCH(A23,'Stato patrimoniale'!A:A,0)) -> EUR | H23: =F23+D23*E23 -> 4.56 | I23: =INDEX('Stato patrimoniale'!N:N,MATCH(A23,'Stato patrimoniale'!A:A,0)) -> 0.26 | J23: =H23*I23 -> 1.1856 | K23: =H23-(H23*I23) -> 3.3744
A24: 16 | B24: 45189 | D24: 0.24 | E24: 1 | G24: =INDEX('Stato patrimoniale'!J:J,MATCH(A24,'Stato patrimoniale'!A:A,0)) -> EUR | H24: =F24+D24*E24 -> 0.24 | I24: =INDEX('Stato patrimoniale'!N:N,MATCH(A24,'Stato patrimoniale'!A:A,0)) -> 0.26 | J24: =H24*I24 -> 0.0624 | K24: =H24-(H24*I24) -> 0.1776
A25: 6 | B25: 45196 | D25: 2.082 | E25: 1 | G25: =INDEX('Stato patrimoniale'!J:J,MATCH(A25,'Stato patrimoniale'!A:A,0)) -> EUR | H25: =F25+D25*E25 -> 2.082 | I25: =INDEX('Stato patrimoniale'!N:N,MATCH(A25,'Stato patrimoniale'!A:A,0)) -> 0.26 | J25: =H25*I25 -> 0.54132 | K25: =H25-(H25*I25) -> 1.54068
A26: 5 | B26: 45196 | D26: 1.388 | E26: 1 | G26: =INDEX('Stato patrimoniale'!J:J,MATCH(A26,'Stato patrimoniale'!A:A,0)) -> EUR | H26: =F26+D26*E26 -> 1.388 | I26: =INDEX('Stato patrimoniale'!N:N,MATCH(A26,'Stato patrimoniale'!A:A,0)) -> 0.26 | J26: =H26*I26 -> 0.36088 | K26: =H26-(H26*I26) -> 1.02712
A27: 3 | B27: 45196 | D27: 6.33 | E27: 1 | G27: =INDEX('Stato patrimoniale'!J:J,MATCH(A27,'Stato patrimoniale'!A:A,0)) -> EUR | H27: =F27+D27*E27 -> 6.33 | I27: =INDEX('Stato patrimoniale'!N:N,MATCH(A27,'Stato patrimoniale'!A:A,0)) -> 0.26 | J27: =H27*I27 -> 1.6458 | K27: =H27-(H27*I27) -> 4.6842
A28: 25 | B28: 45198 | D28: 31.3 | E28: 1 | G28: =INDEX('Stato patrimoniale'!J:J,MATCH(A28,'Stato patrimoniale'!A:A,0)) -> EUR | H28: =F28+D28*E28 -> 31.3 | I28: =INDEX('Stato patrimoniale'!N:N,MATCH(A28,'Stato patrimoniale'!A:A,0)) -> 0.125 | J28: =H28*I28 -> 3.9125 | K28: =H28-(H28*I28) -> 27.3875
A29: 12 | B29: 45201 | D29: 112.5 | E29: 1 | G29: =INDEX('Stato patrimoniale'!J:J,MATCH(A29,'Stato patrimoniale'!A:A,0)) -> EUR | H29: =F29+D29*E29 -> 112.5 | I29: =INDEX('Stato patrimoniale'!N:N,MATCH(A29,'Stato patrimoniale'!A:A,0)) -> 0.125 | J29: =H29*I29 -> 14.0625 | K29: =H29-(H29*I29) -> 98.4375
A30: 26 | B30: 45245 | E30: 1 | F30: 48.86 | G30: =INDEX('Stato patrimoniale'!J:J,MATCH(A30,'Stato patrimoniale'!A:A,0)) -> USD | H30: =F30+D30*E30 -> 48.86 | I30: =INDEX('Stato patrimoniale'!N:N,MATCH(A30,'Stato patrimoniale'!A:A,0)) -> 0.125 | J30: =H30*I30 -> 6.1075 | K30: =H30-(H30*I30) -> 42.7525
A31: 21 | B31: 45250 | E31: 1 | F31: 0.38 | G31: =INDEX('Stato patrimoniale'!J:J,MATCH(A31,'Stato patrimoniale'!A:A,0)) -> USD | H31: =F31+D31*E31 -> 0.38 | I31: =INDEX('Stato patrimoniale'!N:N,MATCH(A31,'Stato patrimoniale'!A:A,0)) -> 0.26 | J31: =H31*I31 -> 0.0988 | K31: =H31-(H31*I31) -> 0.2812
A32: 20 | B32: 45252 | D32: 4.37 | E32: 1 | G32: =INDEX('Stato patrimoniale'!J:J,MATCH(A32,'Stato patrimoniale'!A:A,0)) -> EUR | H32: =F32+D32*E32 -> 4.37 | I32: =INDEX('Stato patrimoniale'!N:N,MATCH(A32,'Stato patrimoniale'!A:A,0)) -> 0.26 | J32: =H32*I32 -> 1.1362 | K32: =H32-(H32*I32) -> 3.2338
A33: 17 | B33: 45252 | D33: 14.4 | E33: 1 | G33: =INDEX('Stato patrimoniale'!J:J,MATCH(A33,'Stato patrimoniale'!A:A,0)) -> EUR | H33: =F33+D33*E33 -> 14.4 | I33: =INDEX('Stato patrimoniale'!N:N,MATCH(A33,'Stato patrimoniale'!A:A,0)) -> 0.26 | J33: =H33*I33 -> 3.744 | K33: =H33-(H33*I33) -> 10.656
A34: 15 | B34: 45252 | D34: 5.93 | E34: 1 | G34: =INDEX('Stato patrimoniale'!J:J,MATCH(A34,'Stato patrimoniale'!A:A,0)) -> EUR | H34: =F34+D34*E34 -> 5.93 | I34: =INDEX('Stato patrimoniale'!N:N,MATCH(A34,'Stato patrimoniale'!A:A,0)) -> 0.26 | J34: =H34*I34 -> 1.5418 | K34: =H34-(H34*I34) -> 4.3882
A35: 4 | B35: 45259 | D35: 2.03 | E35: 1 | G35: =INDEX('Stato patrimoniale'!J:J,MATCH(A35,'Stato patrimoniale'!A:A,0)) -> EUR | H35: =F35+D35*E35 -> 2.03 | I35: =INDEX('Stato patrimoniale'!N:N,MATCH(A35,'Stato patrimoniale'!A:A,0)) -> 0.26 | J35: =H35*I35 -> 0.5278 | K35: =H35-(H35*I35) -> 1.5022
A36: 10 | B36: 45273 | D36: 162.5 | E36: 1 | G36: =INDEX('Stato patrimoniale'!J:J,MATCH(A36,'Stato patrimoniale'!A:A,0)) -> EUR | H36: =F36+D36*E36 -> 162.5 | I36: =INDEX('Stato patrimoniale'!N:N,MATCH(A36,'Stato patrimoniale'!A:A,0)) -> 0.125 | J36: =H36*I36 -> 20.3125 | K36: =H36-(H36*I36) -> 142.1875
A37: 16 | B37: 45273 | D37: 0.24 | E37: 1 | G37: =INDEX('Stato patrimoniale'!J:J,MATCH(A37,'Stato patrimoniale'!A:A,0)) -> EUR | H37: =F37+D37*E37 -> 0.24 | I37: =INDEX('Stato patrimoniale'!N:N,MATCH(A37,'Stato patrimoniale'!A:A,0)) -> 0.26 | J37: =H37*I37 -> 0.0624 | K37: =H37-(H37*I37) -> 0.1776
A38: 23 | B38: 45279 | E38: 1 | F38: 40.29 | G38: =INDEX('Stato patrimoniale'!J:J,MATCH(A38,'Stato patrimoniale'!A:A,0)) -> USD | H38: =F38+D38*E38 -> 40.29 | I38: =INDEX('Stato patrimoniale'!N:N,MATCH(A38,'Stato patrimoniale'!A:A,0)) -> 0.26 | J38: =H38*I38 -> 10.4754 | K38: =H38-(H38*I38) -> 29.8146
A39: 3 | B39: 45287 | D39: 1.6 | E39: 1 | G39: =INDEX('Stato patrimoniale'!J:J,MATCH(A39,'Stato patrimoniale'!A:A,0)) -> EUR | H39: =F39+D39*E39 -> 1.6 | I39: =INDEX('Stato patrimoniale'!N:N,MATCH(A39,'Stato patrimoniale'!A:A,0)) -> 0.26 | J39: =H39*I39 -> 0.416 | K39: =H39-(H39*I39) -> 1.184
A40: 5 | B40: 45289 | D40: 3.34 | E40: 1 | G40: =INDEX('Stato patrimoniale'!J:J,MATCH(A40,'Stato patrimoniale'!A:A,0)) -> EUR | H40: =F40+D40*E40 -> 3.34 | I40: =INDEX('Stato patrimoniale'!N:N,MATCH(A40,'Stato patrimoniale'!A:A,0)) -> 0.26 | J40: =H40*I40 -> 0.8684 | K40: =H40-(H40*I40) -> 2.4716
A41: 29 | B41: 45301 | D41: 51.25 | E41: 1 | G41: =INDEX('Stato patrimoniale'!J:J,MATCH(A41,'Stato patrimoniale'!A:A,0)) -> EUR | H41: =F41+D41*E41 -> 51.25 | I41: =INDEX('Stato patrimoniale'!N:N,MATCH(A41,'Stato patrimoniale'!A:A,0)) -> 0.125 | J41: =H41*I41 -> 6.40625 | K41: =H41-(H41*I41) -> 44.84375
A42: 19 | B42: 45315 | D42: 8.6 | E42: 1 | G42: =INDEX('Stato patrimoniale'!J:J,MATCH(A42,'Stato patrimoniale'!A:A,0)) -> EUR | H42: =F42+D42*E42 -> 8.6 | I42: =INDEX('Stato patrimoniale'!N:N,MATCH(A42,'Stato patrimoniale'!A:A,0)) -> 0.26 | J42: =H42*I42 -> 2.236 | K42: =H42-(H42*I42) -> 6.364
A43: 11 | B43: 45338 | E43: 1 | F43: 139.63 | G43: =INDEX('Stato patrimoniale'!J:J,MATCH(A43,'Stato patrimoniale'!A:A,0)) -> USD | H43: =F43+D43*E43 -> 139.63 | I43: =INDEX('Stato patrimoniale'!N:N,MATCH(A43,'Stato patrimoniale'!A:A,0)) -> 0.125 | J43: =H43*I43 -> 17.45375 | K43: =H43-(H43*I43) -> 122.17625
A44: 21 | B44: 45345 | E44: 1 | F44: 0.38 | G44: =INDEX('Stato patrimoniale'!J:J,MATCH(A44,'Stato patrimoniale'!A:A,0)) -> USD | H44: =F44+D44*E44 -> 0.38 | I44: =INDEX('Stato patrimoniale'!N:N,MATCH(A44,'Stato patrimoniale'!A:A,0)) -> 0.26 | J44: =H44*I44 -> 0.0988 | K44: =H44-(H44*I44) -> 0.2812
A45: 23 | B45: 45372 | E45: 1 | F45: 44.42 | G45: =INDEX('Stato patrimoniale'!J:J,MATCH(A45,'Stato patrimoniale'!A:A,0)) -> USD | H45: =F45+D45*E45 -> 44.42 | I45: =INDEX('Stato patrimoniale'!N:N,MATCH(A45,'Stato patrimoniale'!A:A,0)) -> 0.26 | J45: =H45*I45 -> 11.5492 | K45: =H45-(H45*I45) -> 32.8708
A46: 20 | B46: 45372 | D46: 4.56 | E46: 1 | G46: =INDEX('Stato patrimoniale'!J:J,MATCH(A46,'Stato patrimoniale'!A:A,0)) -> EUR | H46: =F46+D46*E46 -> 4.56 | I46: =INDEX('Stato patrimoniale'!N:N,MATCH(A46,'Stato patrimoniale'!A:A,0)) -> 0.26 | J46: =H46*I46 -> 1.1856 | K46: =H46-(H46*I46) -> 3.3744
A47: 16 | B47: 45372 | D47: 0.24 | E47: 1 | G47: =INDEX('Stato patrimoniale'!J:J,MATCH(A47,'Stato patrimoniale'!A:A,0)) -> EUR | H47: =F47+D47*E47 -> 0.24 | I47: =INDEX('Stato patrimoniale'!N:N,MATCH(A47,'Stato patrimoniale'!A:A,0)) -> 0.26 | J47: =H47*I47 -> 0.0624 | K47: =H47-(H47*I47) -> 0.1776
A48: 5 | B48: 45379 | D48: 3.48 | E48: 1 | G48: =INDEX('Stato patrimoniale'!J:J,MATCH(A48,'Stato patrimoniale'!A:A,0)) -> EUR | H48: =F48+D48*E48 -> 3.48 | I48: =INDEX('Stato patrimoniale'!N:N,MATCH(A48,'Stato patrimoniale'!A:A,0)) -> 0.26 | J48: =H48*I48 -> 0.9048 | K48: =H48-(H48*I48) -> 2.5752
A49: 3 | B49: 45379 | D49: 1.39 | E49: 1 | G49: =INDEX('Stato patrimoniale'!J:J,MATCH(A49,'Stato patrimoniale'!A:A,0)) -> EUR | H49: =F49+D49*E49 -> 1.39 | I49: =INDEX('Stato patrimoniale'!N:N,MATCH(A49,'Stato patrimoniale'!A:A,0)) -> 0.26 | J49: =H49*I49 -> 0.3614 | K49: =H49-(H49*I49) -> 1.0286
A50: 12 | B50: 45384 | D50: 112.5 | E50: 1 | G50: =INDEX('Stato patrimoniale'!J:J,MATCH(A50,'Stato patrimoniale'!A:A,0)) -> EUR | H50: =F50+D50*E50 -> 112.5 | I50: =INDEX('Stato patrimoniale'!N:N,MATCH(A50,'Stato patrimoniale'!A:A,0)) -> 0.125 | J50: =H50*I50 -> 14.0625 | K50: =H50-(H50*I50) -> 98.4375
A51: 25 | B51: 45384 | D51: 90 | E51: 1 | G51: =INDEX('Stato patrimoniale'!J:J,MATCH(A51,'Stato patrimoniale'!A:A,0)) -> EUR | H51: =F51+D51*E51 -> 90 | I51: =INDEX('Stato patrimoniale'!N:N,MATCH(A51,'Stato patrimoniale'!A:A,0)) -> 0.125 | J51: =H51*I51 -> 11.25 | K51: =H51-(H51*I51) -> 78.75
A52: 29 | B52: 45392 | D52: 51.25 | E52: 1 | G52: =INDEX('Stato patrimoniale'!J:J,MATCH(A52,'Stato patrimoniale'!A:A,0)) -> EUR | H52: =F52+D52*E52 -> 51.25 | I52: =INDEX('Stato patrimoniale'!N:N,MATCH(A52,'Stato patrimoniale'!A:A,0)) -> 0.125 | J52: =H52*I52 -> 6.40625 | K52: =H52-(H52*I52) -> 44.84375
A53: 14 | B53: 45406 | D53: 19.83 | E53: 1 | G53: =INDEX('Stato patrimoniale'!J:J,MATCH(A53,'Stato patrimoniale'!A:A,0)) -> EUR | H53: =F53+D53*E53 -> 19.83 | I53: =INDEX('Stato patrimoniale'!N:N,MATCH(A53,'Stato patrimoniale'!A:A,0)) -> 0.26 | J53: =H53*I53 -> 5.1558 | K53: =H53-(H53*I53) -> 14.6742
A54: 26 | B54: 45428 | E54: 1 | F54: 48.9 | G54: =INDEX('Stato patrimoniale'!J:J,MATCH(A54,'Stato patrimoniale'!A:A,0)) -> USD | H54: =F54+D54*E54 -> 48.9 | I54: =INDEX('Stato patrimoniale'!N:N,MATCH(A54,'Stato patrimoniale'!A:A,0)) -> 0.125 | J54: =H54*I54 -> 6.1125 | K54: =H54-(H54*I54) -> 42.7875
A55: 21 | B55: 45432 | E55: 1 | F55: 0.4 | G55: =INDEX('Stato patrimoniale'!J:J,MATCH(A55,'Stato patrimoniale'!A:A,0)) -> USD | H55: =F55+D55*E55 -> 0.4 | I55: =INDEX('Stato patrimoniale'!N:N,MATCH(A55,'Stato patrimoniale'!A:A,0)) -> 0.26 | J55: =H55*I55 -> 0.104 | K55: =H55-(H55*I55) -> 0.296
A56: 17 | B56: 45434 | D56: 15.2 | E56: 1 | G56: =INDEX('Stato patrimoniale'!J:J,MATCH(A56,'Stato patrimoniale'!A:A,0)) -> EUR | H56: =F56+D56*E56 -> 15.2 | I56: =INDEX('Stato patrimoniale'!N:N,MATCH(A56,'Stato patrimoniale'!A:A,0)) -> 0.26 | J56: =H56*I56 -> 3.952 | K56: =H56-(H56*I56) -> 11.248
A57: 20 | B57: 45434 | D57: 4.37 | E57: 1 | G57: =INDEX('Stato patrimoniale'!J:J,MATCH(A57,'Stato patrimoniale'!A:A,0)) -> EUR | H57: =F57+D57*E57 -> 4.37 | I57: =INDEX('Stato patrimoniale'!N:N,MATCH(A57,'Stato patrimoniale'!A:A,0)) -> 0.26 | J57: =H57*I57 -> 1.1362 | K57: =H57-(H57*I57) -> 3.2338
A58: 13 | B58: 45441 | D58: 7.84 | E58: 1 | G58: =INDEX('Stato patrimoniale'!J:J,MATCH(A58,'Stato patrimoniale'!A:A,0)) -> EUR | H58: =F58+D58*E58 -> 7.84 | I58: =INDEX('Stato patrimoniale'!N:N,MATCH(A58,'Stato patrimoniale'!A:A,0)) -> 0.26 | J58: =H58*I58 -> 2.0384 | K58: =H58-(H58*I58) -> 5.8016
A59: 4 | B59: 45442 | D59: 1.15 | E59: 1 | G59: =INDEX('Stato patrimoniale'!J:J,MATCH(A59,'Stato patrimoniale'!A:A,0)) -> EUR | H59: =F59+D59*E59 -> 1.15 | I59: =INDEX('Stato patrimoniale'!N:N,MATCH(A59,'Stato patrimoniale'!A:A,0)) -> 0.26 | J59: =H59*I59 -> 0.299 | K59: =H59-(H59*I59) -> 0.851
A60: 33 | B60: 45448 | D60: 16.25 | E60: 1 | G60: =INDEX('Stato patrimoniale'!J:J,MATCH(A60,'Stato patrimoniale'!A:A,0)) -> EUR | H60: =F60+D60*E60 -> 16.25 | I60: =INDEX('Stato patrimoniale'!N:N,MATCH(A60,'Stato patrimoniale'!A:A,0)) -> 0.125 | J60: =H60*I60 -> 2.03125 | K60: =H60-(H60*I60) -> 14.21875
A61: 10 | B61: 45455 | D61: 162.5 | E61: 1 | G61: =INDEX('Stato patrimoniale'!J:J,MATCH(A61,'Stato patrimoniale'!A:A,0)) -> EUR | H61: =F61+D61*E61 -> 162.5 | I61: =INDEX('Stato patrimoniale'!N:N,MATCH(A61,'Stato patrimoniale'!A:A,0)) -> 0.125 | J61: =H61*I61 -> 20.3125 | K61: =H61-(H61*I61) -> 142.1875
A62: 23 | B62: 45462 | D62: 45.22 | E62: 1 | G62: =INDEX('Stato patrimoniale'!J:J,MATCH(A62,'Stato patrimoniale'!A:A,0)) -> USD | H62: =F62+D62*E62 -> 45.22 | I62: =INDEX('Stato patrimoniale'!N:N,MATCH(A62,'Stato patrimoniale'!A:A,0)) -> 0.26 | J62: =H62*I62 -> 11.7572 | K62: =H62-(H62*I62) -> 33.4628
A63: 6 | B63: 45469 | D63: 3.4 | E63: 1 | G63: =INDEX('Stato patrimoniale'!J:J,MATCH(A63,'Stato patrimoniale'!A:A,0)) -> EUR | H63: =F63+D63*E63 -> 3.4 | I63: =INDEX('Stato patrimoniale'!N:N,MATCH(A63,'Stato patrimoniale'!A:A,0)) -> 0.26 | J63: =H63*I63 -> 0.884 | K63: =H63-(H63*I63) -> 2.516
A64: 3 | B64: 45469 | D64: 4.57 | E64: 1 | G64: =INDEX('Stato patrimoniale'!J:J,MATCH(A64,'Stato patrimoniale'!A:A,0)) -> EUR | H64: =F64+D64*E64 -> 4.57 | I64: =INDEX('Stato patrimoniale'!N:N,MATCH(A64,'Stato patrimoniale'!A:A,0)) -> 0.26 | J64: =H64*I64 -> 1.1882 | K64: =H64-(H64*I64) -> 3.3818
A65: 16 | B65: 45469 | D65: 0.36 | E65: 1 | G65: =INDEX('Stato patrimoniale'!J:J,MATCH(A65,'Stato patrimoniale'!A:A,0)) -> EUR | H65: =F65+D65*E65 -> 0.36 | I65: =INDEX('Stato patrimoniale'!N:N,MATCH(A65,'Stato patrimoniale'!A:A,0)) -> 0.26 | J65: =H65*I65 -> 0.0936 | K65: =H65-(H65*I65) -> 0.2664
A66: 15 | B66: 45469 | D66: 14.08 | E66: 1 | G66: =INDEX('Stato patrimoniale'!J:J,MATCH(A66,'Stato patrimoniale'!A:A,0)) -> EUR | H66: =F66+D66*E66 -> 14.08 | I66: =INDEX('Stato patrimoniale'!N:N,MATCH(A66,'Stato patrimoniale'!A:A,0)) -> 0.26 | J66: =H66*I66 -> 3.6608 | K66: =H66-(H66*I66) -> 10.4192
A67: 29 | B67: 45483 | D67: 51.25 | E67: 1 | G67: =INDEX('Stato patrimoniale'!J:J,MATCH(A67,'Stato patrimoniale'!A:A,0)) -> EUR | H67: =F67+D67*E67 -> 51.25 | I67: =INDEX('Stato patrimoniale'!N:N,MATCH(A67,'Stato patrimoniale'!A:A,0)) -> 0.125 | J67: =H67*I67 -> 6.40625 | K67: =H67-(H67*I67) -> 44.84375
... A70: 31 | B70: 45503 | D70: 47 | E70: 1 | G70: =INDEX('Stato patrimoniale'!J:J,MATCH(A70,'Stato patrimoniale'!A:A,0)) -> EUR | H70: =F70+D70*E70 -> 47 | I70: =INDEX('Stato patrimoniale'!N:N,MATCH(A70,'Stato patrimoniale'!A:A,0)) -> 0.125 | J70: =H70*I70 -> 5.875 | K70: =H70-(H70*I70) -> 41.125
A71: 11 | B71: 45519 | E71: 1 | F71: 136.13 | G71: =INDEX('Stato patrimoniale'!J:J,MATCH(A71,'Stato patrimoniale'!A:A,0)) -> USD | H71: =F71+D71*E71 -> 136.13 | I71: =INDEX('Stato patrimoniale'!N:N,MATCH(A71,'Stato patrimoniale'!A:A,0)) -> 0.125 | J71: =H71*I71 -> 17.01625 | K71: =H71-(H71*I71) -> 119.11375
A72: 21 | B72: 45523 | E72: 1 | F72: 0.39 | G72: =INDEX('Stato patrimoniale'!J:J,MATCH(A72,'Stato patrimoniale'!A:A,0)) -> USD | H72: =F72+D72*E72 -> 0.39 | I72: =INDEX('Stato patrimoniale'!N:N,MATCH(A72,'Stato patrimoniale'!A:A,0)) -> 0.26 | J72: =H72*I72 -> 0.1014 | K72: =H72-(H72*I72) -> 0.2886
A73: 33 | B73: 45540 | D73: 16.25 | E73: 1 | G73: =INDEX('Stato patrimoniale'!J:J,MATCH(A73,'Stato patrimoniale'!A:A,0)) -> EUR | H73: =F73+D73*E73 -> 16.25 | I73: =INDEX('Stato patrimoniale'!N:N,MATCH(A73,'Stato patrimoniale'!A:A,0)) -> 0.125 | J73: =H73*I73 -> 2.03125 | K73: =H73-(H73*I73) -> 14.21875
A74: 23 | B74: 45553 | E74: 1 | F74: 43.5 | G74: =INDEX('Stato patrimoniale'!J:J,MATCH(A74,'Stato patrimoniale'!A:A,0)) -> USD | H74: =F74+D74*E74 -> 43.5 | I74: =INDEX('Stato patrimoniale'!N:N,MATCH(A74,'Stato patrimoniale'!A:A,0)) -> 0.26 | J74: =H74*I74 -> 11.31 | K74: =H74-(H74*I74) -> 32.19
A75: 6 | B75: 45560 | D75: 3.36 | E75: 1 | G75: =INDEX('Stato patrimoniale'!J:J,MATCH(A75,'Stato patrimoniale'!A:A,0)) -> EUR | H75: =F75+D75*E75 -> 3.36 | I75: =INDEX('Stato patrimoniale'!N:N,MATCH(A75,'Stato patrimoniale'!A:A,0)) -> 0.26 | J75: =H75*I75 -> 0.8736 | K75: =H75-(H75*I75) -> 2.4864
A76: 3 | B76: 45560 | D76: 5.81 | E76: 1 | G76: =INDEX('Stato patrimoniale'!J:J,MATCH(A76,'Stato patrimoniale'!A:A,0)) -> EUR | H76: =F76+D76*E76 -> 5.81 | I76: =INDEX('Stato patrimoniale'!N:N,MATCH(A76,'Stato patrimoniale'!A:A,0)) -> 0.26 | J76: =H76*I76 -> 1.5106 | K76: =H76-(H76*I76) -> 4.2994
A77: 20 | B77: 45560 | D77: 4.75 | E77: 1 | G77: =INDEX('Stato patrimoniale'!J:J,MATCH(A77,'Stato patrimoniale'!A:A,0)) -> EUR | H77: =F77+D77*E77 -> 4.75 | I77: =INDEX('Stato patrimoniale'!N:N,MATCH(A77,'Stato patrimoniale'!A:A,0)) -> 0.26 | J77: =H77*I77 -> 1.235 | K77: =H77-(H77*I77) -> 3.515
A78: 25 | B78: 45565 | D78: 90 | E78: 1 | G78: =INDEX('Stato patrimoniale'!J:J,MATCH(A78,'Stato patrimoniale'!A:A,0)) -> EUR | H78: =F78+D78*E78 -> 90 | I78: =INDEX('Stato patrimoniale'!N:N,MATCH(A78,'Stato patrimoniale'!A:A,0)) -> 0.125 | J78: =H78*I78 -> 11.25 | K78: =H78-(H78*I78) -> 78.75
A79: 12 | B79: 45566 | D79: 112.5 | E79: 1 | G79: =INDEX('Stato patrimoniale'!J:J,MATCH(A79,'Stato patrimoniale'!A:A,0)) -> EUR | H79: =F79+D79*E79 -> 112.5 | I79: =INDEX('Stato patrimoniale'!N:N,MATCH(A79,'Stato patrimoniale'!A:A,0)) -> 0.125 | J79: =H79*I79 -> 14.0625 | K79: =H79-(H79*I79) -> 98.4375
A80: 29 | B80: 45575 | D80: 51.25 | E80: 1 | G80: =INDEX('Stato patrimoniale'!J:J,MATCH(A80,'Stato patrimoniale'!A:A,0)) -> EUR | H80: =F80+D80*E80 -> 51.25 | I80: =INDEX('Stato patrimoniale'!N:N,MATCH(A80,'Stato patrimoniale'!A:A,0)) -> 0.125 | J80: =H80*I80 -> 6.40625 | K80: =H80-(H80*I80) -> 44.84375
A81: 26 | B81: 45611 | F81: 50.2 | G81: =INDEX('Stato patrimoniale'!J:J,MATCH(A81,'Stato patrimoniale'!A:A,0)) -> USD | H81: =F81+D81*E81 -> 50.2 | I81: =INDEX('Stato patrimoniale'!N:N,MATCH(A81,'Stato patrimoniale'!A:A,0)) -> 0.125 | J81: =H81*I81 -> 6.275 | K81: =H81-(H81*I81) -> 43.925
A82: 17 | B82: 45616 | D82: 17 | E82: 1 | G82: =INDEX('Stato patrimoniale'!J:J,MATCH(A82,'Stato patrimoniale'!A:A,0)) -> EUR | H82: =F82+D82*E82 -> 17 | I82: =INDEX('Stato patrimoniale'!N:N,MATCH(A82,'Stato patrimoniale'!A:A,0)) -> 0.26 | J82: =H82*I82 -> 4.42 | K82: =H82-(H82*I82) -> 12.58
A83: 14 | B83: 45616 | D83: 10.19 | E83: 1 | G83: =INDEX('Stato patrimoniale'!J:J,MATCH(A83,'Stato patrimoniale'!A:A,0)) -> EUR | H83: =F83+D83*E83 -> 10.19 | I83: =INDEX('Stato patrimoniale'!N:N,MATCH(A83,'Stato patrimoniale'!A:A,0)) -> 0.26 | J83: =H83*I83 -> 2.6494 | K83: =H83-(H83*I83) -> 7.5406
A84: 20 | B84: 45616 | D84: 4.75 | E84: 1 | G84: =INDEX('Stato patrimoniale'!J:J,MATCH(A84,'Stato patrimoniale'!A:A,0)) -> EUR | H84: =F84+D84*E84 -> 4.75 | I84: =INDEX('Stato patrimoniale'!N:N,MATCH(A84,'Stato patrimoniale'!A:A,0)) -> 0.26 | J84: =H84*I84 -> 1.235 | K84: =H84-(H84*I84) -> 3.515
A85: 15 | B85: 45616 | D85: 8.25 | E85: 1 | G85: =INDEX('Stato patrimoniale'!J:J,MATCH(A85,'Stato patrimoniale'!A:A,0)) -> EUR | H85: =F85+D85*E85 -> 8.25 | I85: =INDEX('Stato patrimoniale'!N:N,MATCH(A85,'Stato patrimoniale'!A:A,0)) -> 0.26 | J85: =H85*I85 -> 2.145 | K85: =H85-(H85*I85) -> 6.105
A86: 21 | B86: 45617 | F86: 0.41 | G86: =INDEX('Stato patrimoniale'!J:J,MATCH(A86,'Stato patrimoniale'!A:A,0)) -> USD | H86: =F86+D86*E86 -> 0.41 | I86: =INDEX('Stato patrimoniale'!N:N,MATCH(A86,'Stato patrimoniale'!A:A,0)) -> 0.26 | J86: =H86*I86 -> 0.1066 | K86: =H86-(H86*I86) -> 0.3034
A87: 33 | B87: 45631 | D87: 16.25 | E87: 1 | G87: =INDEX('Stato patrimoniale'!J:J,MATCH(A87,'Stato patrimoniale'!A:A,0)) -> EUR | H87: =F87+D87*E87 -> 16.25 | I87: =INDEX('Stato patrimoniale'!N:N,MATCH(A87,'Stato patrimoniale'!A:A,0)) -> 0.125 | J87: =H87*I87 -> 2.03125 | K87: =H87-(H87*I87) -> 14.21875
A88: 10 | B88: 45639 | D88: 162.5 | E88: 1 | G88: =INDEX('Stato patrimoniale'!J:J,MATCH(A88,'Stato patrimoniale'!A:A,0)) -> EUR | H88: =F88+D88*E88 -> 162.5 | I88: =INDEX('Stato patrimoniale'!N:N,MATCH(A88,'Stato patrimoniale'!A:A,0)) -> 0.125 | J88: =H88*I88 -> 20.3125 | K88: =H88-(H88*I88) -> 142.1875
A89: 45 | B89: 45639 | D89: 35 | E89: 1 | G89: =INDEX('Stato patrimoniale'!J:J,MATCH(A89,'Stato patrimoniale'!A:A,0)) -> EUR | H89: =F89+D89*E89 -> 35 | I89: 0.26 | J89: =H89*I89 -> 9.1 | K89: =H89-(H89*I89) -> 25.9 | L89: Tassazione Sbagliata
A90: 23 | B90: 45642 | E90: 1 | F90: 51.08 | G90: =INDEX('Stato patrimoniale'!J:J,MATCH(A90,'Stato patrimoniale'!A:A,0)) -> USD | H90: =F90+D90*E90 -> 51.08 | I90: =INDEX('Stato patrimoniale'!N:N,MATCH(A90,'Stato patrimoniale'!A:A,0)) -> 0.26 | J90: =H90*I90 -> 13.2808 | K90: =H90-(H90*I90) -> 37.7992
A91: 3 | B91: 45653 | D91: 1.59 | E91: 1 | G91: =INDEX('Stato patrimoniale'!J:J,MATCH(A91,'Stato patrimoniale'!A:A,0)) -> EUR | H91: =F91+D91*E91 -> 1.59 | I91: =INDEX('Stato patrimoniale'!N:N,MATCH(A91,'Stato patrimoniale'!A:A,0)) -> 0.26 | J91: =H91*I91 -> 0.4134 | K91: =H91-(H91*I91) -> 1.1766
A92: 5 | B92: 45653 | D92: 3.75 | E92: 1 | G92: =INDEX('Stato patrimoniale'!J:J,MATCH(A92,'Stato patrimoniale'!A:A,0)) -> EUR | H92: =F92+D92*E92 -> 3.75 | I92: =INDEX('Stato patrimoniale'!N:N,MATCH(A92,'Stato patrimoniale'!A:A,0)) -> 0.26 | J92: =H92*I92 -> 0.975 | K92: =H92-(H92*I92) -> 2.775
A93: 29 | B93: 45667 | D93: 51.25 | E93: 1 | G93: =INDEX('Stato patrimoniale'!J:J,MATCH(A93,'Stato patrimoniale'!A:A,0)) -> EUR | H93: =F93+D93*E93 -> 51.25 | I93: =INDEX('Stato patrimoniale'!N:N,MATCH(A93,'Stato patrimoniale'!A:A,0)) -> 0.125 | J93: =H93*I93 -> 6.40625 | K93: =H93-(H93*I93) -> 44.84375
A94: 19 | B94: 45679 | D94: 8.6 | E94: 1 | G94: =INDEX('Stato patrimoniale'!J:J,MATCH(A94,'Stato patrimoniale'!A:A,0)) -> EUR | H94: =F94+D94*E94 -> 8.6 | I94: =INDEX('Stato patrimoniale'!N:N,MATCH(A94,'Stato patrimoniale'!A:A,0)) -> 0.26 | J94: =H94*I94 -> 2.236 | K94: =H94-(H94*I94) -> 6.364
A95: 37 | B95: 45685 | D95: 32 | E95: 1 | G95: =INDEX('Stato patrimoniale'!J:J,MATCH(A95,'Stato patrimoniale'!A:A,0)) -> EUR | H95: =F95+D95*E95 -> 32 | I95: =INDEX('Stato patrimoniale'!N:N,MATCH(A95,'Stato patrimoniale'!A:A,0)) -> 0.125 | J95: =H95*I95 -> 4 | K95: =H95-(H95*I95) -> 28
A96: 21 | B96: 45705 | E96: 1 | F96: 0.41 | G96: =INDEX('Stato patrimoniale'!J:J,MATCH(A96,'Stato patrimoniale'!A:A,0)) -> USD | H96: =F96+D96*E96 -> 0.41 | I96: =INDEX('Stato patrimoniale'!N:N,MATCH(A96,'Stato patrimoniale'!A:A,0)) -> 0.26 | J96: =H96*I96 -> 0.1066 | K96: =H96-(H96*I96) -> 0.3034
A97: 11 | B97: 45706 | E97: 1 | F97: 143.58 | G97: =INDEX('Stato patrimoniale'!J:J,MATCH(A97,'Stato patrimoniale'!A:A,0)) -> USD | H97: =F97+D97*E97 -> 143.58 | I97: =INDEX('Stato patrimoniale'!N:N,MATCH(A97,'Stato patrimoniale'!A:A,0)) -> 0.125 | J97: =H97*I97 -> 17.9475 | K97: =H97-(H97*I97) -> 125.6325
A98: 33 | B98: 45721 | D98: 16.25 | E98: 1 | G98: =INDEX('Stato patrimoniale'!J:J,MATCH(A98,'Stato patrimoniale'!A:A,0)) -> EUR | H98: =F98+D98*E98 -> 16.25 | I98: =INDEX('Stato patrimoniale'!N:N,MATCH(A98,'Stato patrimoniale'!A:A,0)) -> 0.125 | J98: =H98*I98 -> 2.03125 | K98: =H98-(H98*I98) -> 14.21875
A99: 23 | B99: 45736 | E99: 1 | F99: 53.73 | G99: =INDEX('Stato patrimoniale'!J:J,MATCH(A99,'Stato patrimoniale'!A:A,0)) -> USD | H99: =F99+D99*E99 -> 53.73 | I99: =INDEX('Stato patrimoniale'!N:N,MATCH(A99,'Stato patrimoniale'!A:A,0)) -> 0.26 | J99: =H99*I99 -> 13.9698 | K99: =H99-(H99*I99) -> 39.7602
A100: 20 | B100: 45742 | D100: 4.75 | E100: 1 | G100: =INDEX('Stato patrimoniale'!J:J,MATCH(A100,'Stato patrimoniale'!A:A,0)) -> EUR | H100: =F100+D100*E100 -> 4.75 | I100: =INDEX('Stato patrimoniale'!N:N,MATCH(A100,'Stato patrimoniale'!A:A,0)) -> 0.26 | J100: =H100*I100 -> 1.235 | K100: =H100-(H100*I100) -> 3.515
A101: 5 | B101: 45742 | D101: 3.61 | E101: 1 | G101: =INDEX('Stato patrimoniale'!J:J,MATCH(A101,'Stato patrimoniale'!A:A,0)) -> EUR | H101: =F101+D101*E101 -> 3.61 | I101: =INDEX('Stato patrimoniale'!N:N,MATCH(A101,'Stato patrimoniale'!A:A,0)) -> 0.26 | J101: =H101*I101 -> 0.9386 | K101: =H101-(H101*I101) -> 2.6714
A102: 25 | B102: 45747 | D102: 90 | E102: 1 | G102: =INDEX('Stato patrimoniale'!J:J,MATCH(A102,'Stato patrimoniale'!A:A,0)) -> EUR | H102: =F102+D102*E102 -> 90 | I102: =INDEX('Stato patrimoniale'!N:N,MATCH(A102,'Stato patrimoniale'!A:A,0)) -> 0.125 | J102: =H102*I102 -> 11.25 | K102: =H102-(H102*I102) -> 78.75
A103: 12 | B103: 45748 | D103: 112.5 | E103: 1 | G103: =INDEX('Stato patrimoniale'!J:J,MATCH(A103,'Stato patrimoniale'!A:A,0)) -> EUR | H103: =F103+D103*E103 -> 112.5 | I103: =INDEX('Stato patrimoniale'!N:N,MATCH(A103,'Stato patrimoniale'!A:A,0)) -> 0.125 | J103: =H103*I103 -> 14.0625 | K103: =H103-(H103*I103) -> 98.4375
...

Sheet Securities
A1: Ticker Symbol | B1: ISIN | C1: Security Name | D1: Currency
A2: =IF(INDEX('Stato patrimoniale'!L:L,MATCH(C2,'Stato patrimoniale'!C:C,0))<>0,INDEX('Stato patrimoniale'!L:L,MATCH(C2,'Stato patrimoniale'!C:C,0)),"") -> CNHI.VI | B2: =INDEX('Stato patrimoniale'!K:K,MATCH(C2,'Stato patrimoniale'!C:C,0)) -> NL0010545661 | C2: {=_xlfn.UNIQUE('Stato patrimoniale'!C2:C106)} -> CNH Industrial | D2: =INDEX('Stato patrimoniale'!J:J,MATCH(C2,'Stato patrimoniale'!C:C,0)) -> EUR
A3: =IF(INDEX('Stato patrimoniale'!L:L,MATCH(C3,'Stato patrimoniale'!C:C,0))<>0,INDEX('Stato patrimoniale'!L:L,MATCH(C3,'Stato patrimoniale'!C:C,0)),"") -> UCG.MI | B3: =INDEX('Stato patrimoniale'!K:K,MATCH(C3,'Stato patrimoniale'!C:C,0)) -> IT0005239360 | C3: Unicredit | D3: =INDEX('Stato patrimoniale'!J:J,MATCH(C3,'Stato patrimoniale'!C:C,0)) -> EUR
A4: =IF(INDEX('Stato patrimoniale'!L:L,MATCH(C4,'Stato patrimoniale'!C:C,0))<>0,INDEX('Stato patrimoniale'!L:L,MATCH(C4,'Stato patrimoniale'!C:C,0)),"") -> PST.MI | B4: =INDEX('Stato patrimoniale'!K:K,MATCH(C4,'Stato patrimoniale'!C:C,0)) -> IT0003796171 | C4: Poste Italiane | D4: =INDEX('Stato patrimoniale'!J:J,MATCH(C4,'Stato patrimoniale'!C:C,0)) -> EUR
A5: =IF(INDEX('Stato patrimoniale'!L:L,MATCH(C5,'Stato patrimoniale'!C:C,0))<>0,INDEX('Stato patrimoniale'!L:L,MATCH(C5,'Stato patrimoniale'!C:C,0)),"") -> STMMI.MI | B5: =INDEX('Stato patrimoniale'!K:K,MATCH(C5,'Stato patrimoniale'!C:C,0)) -> NL0000226223 | C5: STMicroElectronics | D5: =INDEX('Stato patrimoniale'!J:J,MATCH(C5,'Stato patrimoniale'!C:C,0)) -> EUR
A6: =IF(INDEX('Stato patrimoniale'!L:L,MATCH(C6,'Stato patrimoniale'!C:C,0))<>0,INDEX('Stato patrimoniale'!L:L,MATCH(C6,'Stato patrimoniale'!C:C,0)),"") -> ISP.MI | B6: =INDEX('Stato patrimoniale'!K:K,MATCH(C6,'Stato patrimoniale'!C:C,0)) -> IT0000072618 | C6: Intesa San Paolo | D6: =INDEX('Stato patrimoniale'!J:J,MATCH(C6,'Stato patrimoniale'!C:C,0)) -> EUR
A7: =IF(INDEX('Stato patrimoniale'!L:L,MATCH(C7,'Stato patrimoniale'!C:C,0))<>0,INDEX('Stato patrimoniale'!L:L,MATCH(C7,'Stato patrimoniale'!C:C,0)),"") -> LDO.MI | B7: =INDEX('Stato patrimoniale'!K:K,MATCH(C7,'Stato patrimoniale'!C:C,0)) -> IT0003856405 | C7: Leonardo | D7: =INDEX('Stato patrimoniale'!J:J,MATCH(C7,'Stato patrimoniale'!C:C,0)) -> EUR
A8: =IF(INDEX('Stato patrimoniale'!L:L,MATCH(C8,'Stato patrimoniale'!C:C,0))<>0,INDEX('Stato patrimoniale'!L:L,MATCH(C8,'Stato patrimoniale'!C:C,0)),"") -> ENEL.MI | B8: =INDEX('Stato patrimoniale'!K:K,MATCH(C8,'Stato patrimoniale'!C:C,0)) -> IT0003128367 | C8: Enel | D8: =INDEX('Stato patrimoniale'!J:J,MATCH(C8,'Stato patrimoniale'!C:C,0)) -> EUR
A9: =IF(INDEX('Stato patrimoniale'!L:L,MATCH(C9,'Stato patrimoniale'!C:C,0))<>0,INDEX('Stato patrimoniale'!L:L,MATCH(C9,'Stato patrimoniale'!C:C,0)),"") -> ENI.MI | B9: =INDEX('Stato patrimoniale'!K:K,MATCH(C9,'Stato patrimoniale'!C:C,0)) -> IT0003132476 | C9: Eni | D9: =INDEX('Stato patrimoniale'!J:J,MATCH(C9,'Stato patrimoniale'!C:C,0)) -> EUR
A10: =IF(INDEX('Stato patrimoniale'!L:L,MATCH(C10,'Stato patrimoniale'!C:C,0))<>0,INDEX('Stato patrimoniale'!L:L,MATCH(C10,'Stato patrimoniale'!C:C,0)),"") -> AAPL | B10: =INDEX('Stato patrimoniale'!K:K,MATCH(C10,'Stato patrimoniale'!C:C,0)) -> US0378331005 | C10: Apple | D10: =INDEX('Stato patrimoniale'!J:J,MATCH(C10,'Stato patrimoniale'!C:C,0)) -> USD
A11: =IF(INDEX('Stato patrimoniale'!L:L,MATCH(C11,'Stato patrimoniale'!C:C,0))<>0,INDEX('Stato patrimoniale'!L:L,MATCH(C11,'Stato patrimoniale'!C:C,0)),"") -> AMZN | B11: =INDEX('Stato patrimoniale'!K:K,MATCH(C11,'Stato patrimoniale'!C:C,0)) -> US0231351067 | C11: Amazon | D11: =INDEX('Stato patrimoniale'!J:J,MATCH(C11,'Stato patrimoniale'!C:C,0)) -> USD
A12: =IF(INDEX('Stato patrimoniale'!L:L,MATCH(C12,'Stato patrimoniale'!C:C,0))<>0,INDEX('Stato patrimoniale'!L:L,MATCH(C12,'Stato patrimoniale'!C:C,0)),"") -> MSFT | B12: =INDEX('Stato patrimoniale'!K:K,MATCH(C12,'Stato patrimoniale'!C:C,0)) -> US5949181045 | C12: Microsoft | D12: =INDEX('Stato patrimoniale'!J:J,MATCH(C12,'Stato patrimoniale'!C:C,0)) -> USD
A13: =IF(INDEX('Stato patrimoniale'!L:L,MATCH(C13,'Stato patrimoniale'!C:C,0))<>0,INDEX('Stato patrimoniale'!L:L,MATCH(C13,'Stato patrimoniale'!C:C,0)),"") -> SWDA.MI | B13: =INDEX('Stato patrimoniale'!K:K,MATCH(C13,'Stato patrimoniale'!C:C,0)) -> IE00B4L5Y983 | C13: iShares Core MSCI World UCITS ETF USD (Acc) | D13: =INDEX('Stato patrimoniale'!J:J,MATCH(C13,'Stato patrimoniale'!C:C,0)) -> EUR
A14: =IF(INDEX('Stato patrimoniale'!L:L,MATCH(C14,'Stato patrimoniale'!C:C,0))<>0,INDEX('Stato patrimoniale'!L:L,MATCH(C14,'Stato patrimoniale'!C:C,0)),"") -> VFEM.MI | B14: =INDEX('Stato patrimoniale'!K:K,MATCH(C14,'Stato patrimoniale'!C:C,0)) -> IE00B3VVMM84 | C14: Vanguard FTSE Emerging Markets UCITS ETF (USD) Dis | D14: =INDEX('Stato patrimoniale'!J:J,MATCH(C14,'Stato patrimoniale'!C:C,0)) -> EUR
... A45: =IF(INDEX('Stato patrimoniale'!L:L,MATCH(C45,'Stato patrimoniale'!C:C,0))<>0,INDEX('Stato patrimoniale'!L:L,MATCH(C45,'Stato patrimoniale'!C:C,0)),"") | B45: =INDEX('Stato patrimoniale'!K:K,MATCH(C45,'Stato patrimoniale'!C:C,0)) -> IT0005696320 | C45: BTP-10MZ32 VAL CUM | D45: =INDEX('Stato patrimoniale'!J:J,MATCH(C45,'Stato patrimoniale'!C:C,0)) -> EUR
C46: 0

Sheet Transactions_Buy
A1: Ticker Symbol | B1: ISIN | C1: Security Name | D1: Class | E1: Currency Gross Amount | F1: Shares | G1: Value | H1: Exchange rate | I1: fees | J1: taxes | K1: Date | L1: Type | M1: Securities account | N1: Cash Account
A2: ='Stato patrimoniale'!L2 -> CNHI.VI | B2: ='Stato patrimoniale'!K2 -> NL0010545661 | C2: ='Stato patrimoniale'!C2 -> CNH Industrial | D2: ='Stato patrimoniale'!D2 -> A | E2: ='Stato patrimoniale'!J2 -> EUR | F2: ='Stato patrimoniale'!I2 -> 18 | G2: ='Stato patrimoniale'!W2 -> 249.534 | H2: ='Stato patrimoniale'!U2 -> 1 | I2: ='Stato patrimoniale'!V2 -> 0 | K2: ='Stato patrimoniale'!O2 -> 45133 | L2: Buy | M2: ='Stato patrimoniale'!Q2 -> Fineco-C | N2: =M2 -> Fineco-C
A3: ='Stato patrimoniale'!L3 -> UCG.MI | B3: ='Stato patrimoniale'!K3 -> IT0005239360 | C3: ='Stato patrimoniale'!C3 -> Unicredit | D3: ='Stato patrimoniale'!D3 -> A | E3: ='Stato patrimoniale'!J3 -> EUR | F3: ='Stato patrimoniale'!I3 -> 11 | G3: ='Stato patrimoniale'!W3 -> 246.598 | H3: ='Stato patrimoniale'!U3 -> 1 | I3: ='Stato patrimoniale'!V3 -> 0 | K3: ='Stato patrimoniale'!O3 -> 45132 | L3: Buy | M3: ='Stato patrimoniale'!Q3 -> Fineco-C | N3: =M3 -> Fineco-C
A4: ='Stato patrimoniale'!L4 -> PST.MI | B4: ='Stato patrimoniale'!K4 -> IT0003796171 | C4: ='Stato patrimoniale'!C4 -> Poste Italiane | D4: ='Stato patrimoniale'!D4 -> A | E4: ='Stato patrimoniale'!J4 -> EUR | F4: ='Stato patrimoniale'!I4 -> 25 | G4: ='Stato patrimoniale'!W4 -> 256.95 | H4: ='Stato patrimoniale'!U4 -> 1 | I4: ='Stato patrimoniale'!V4 -> 0 | K4: ='Stato patrimoniale'!O4 -> 45133 | L4: Buy | M4: ='Stato patrimoniale'!Q4 -> Fineco-C | N4: =M4 -> Fineco-C
A5: ='Stato patrimoniale'!L5 -> STMMI.MI | B5: ='Stato patrimoniale'!K5 -> NL0000226223 | C5: ='Stato patrimoniale'!C5 -> STMicroElectronics | D5: ='Stato patrimoniale'!D5 -> A | E5: ='Stato patrimoniale'!J5 -> EUR | F5: ='Stato patrimoniale'!I5 -> 5 | G5: ='Stato patrimoniale'!W5 -> 230.45 | H5: ='Stato patrimoniale'!U5 -> 1 | I5: ='Stato patrimoniale'!V5 -> 0 | K5: ='Stato patrimoniale'!O5 -> 45132 | L5: Buy | M5: ='Stato patrimoniale'!Q5 -> Fineco-C | N5: =M5 -> Fineco-C
A6: ='Stato patrimoniale'!L6 -> ISP.MI | B6: ='Stato patrimoniale'!K6 -> IT0000072618 | C6: ='Stato patrimoniale'!C6 -> Intesa San Paolo | D6: ='Stato patrimoniale'!D6 -> A | E6: ='Stato patrimoniale'!J6 -> EUR | F6: ='Stato patrimoniale'!I6 -> 100 | G6: ='Stato patrimoniale'!W6 -> 255.45 | H6: ='Stato patrimoniale'!U6 -> 1 | I6: ='Stato patrimoniale'!V6 -> 0 | K6: ='Stato patrimoniale'!O6 -> 45132 | L6: Buy | M6: ='Stato patrimoniale'!Q6 -> Fineco-C | N6: =M6 -> Fineco-C
A7: ='Stato patrimoniale'!L7 -> LDO.MI | B7: ='Stato patrimoniale'!K7 -> IT0003856405 | C7: ='Stato patrimoniale'!C7 -> Leonardo | D7: ='Stato patrimoniale'!D7 -> A | E7: ='Stato patrimoniale'!J7 -> EUR | F7: ='Stato patrimoniale'!I7 -> 21 | G7: ='Stato patrimoniale'!W7 -> 244.44 | H7: ='Stato patrimoniale'!U7 -> 1 | I7: ='Stato patrimoniale'!V7 -> 0 | K7: ='Stato patrimoniale'!O7 -> 45133 | L7: Buy | M7: ='Stato patrimoniale'!Q7 -> Fineco-C | N7: =M7 -> Fineco-C
A8: ='Stato patrimoniale'!L8 -> ENEL.MI | B8: ='Stato patrimoniale'!K8 -> IT0003128367 | C8: ='Stato patrimoniale'!C8 -> Enel | D8: ='Stato patrimoniale'!D8 -> A | E8: ='Stato patrimoniale'!J8 -> EUR | F8: ='Stato patrimoniale'!I8 -> 40 | G8: ='Stato patrimoniale'!W8 -> 252.52 | H8: ='Stato patrimoniale'!U8 -> 1 | I8: ='Stato patrimoniale'!V8 -> 0 | K8: ='Stato patrimoniale'!O8 -> 45133 | L8: Buy | M8: ='Stato patrimoniale'!Q8 -> Fineco-C | N8: =M8 -> Fineco-C
A9: ='Stato patrimoniale'!L9 -> ENI.MI | B9: ='Stato patrimoniale'!K9 -> IT0003132476 | C9: ='Stato patrimoniale'!C9 -> Eni | D9: ='Stato patrimoniale'!D9 -> A | E9: ='Stato patrimoniale'!J9 -> EUR | F9: ='Stato patrimoniale'!I9 -> 19 | G9: ='Stato patrimoniale'!W9 -> 264.993 | H9: ='Stato patrimoniale'!U9 -> 1 | I9: ='Stato patrimoniale'!V9 -> 0 | K9: ='Stato patrimoniale'!O9 -> 45132 | L9: Buy | M9: ='Stato patrimoniale'!Q9 -> Fineco-C | N9: =M9 -> Fineco-C
A10: ='Stato patrimoniale'!L10 -> AAPL | B10: ='Stato patrimoniale'!K10 -> US0378331005 | C10: ='Stato patrimoniale'!C10 -> Apple | D10: ='Stato patrimoniale'!D10 -> A | E10: ='Stato patrimoniale'!J10 -> USD | F10: ='Stato patrimoniale'!I10 -> 2 | G10: ='Stato patrimoniale'!W10 -> 282.06148 | H10: ='Stato patrimoniale'!U10 -> 0.864 | I10: ='Stato patrimoniale'!V10 -> 12.95 | K10: ='Stato patrimoniale'!O10 -> 44498 | L10: Buy | M10: ='Stato patrimoniale'!Q10 -> Fineco-C | N10: =M10 -> Fineco-C
A11: ='Stato patrimoniale'!L11 -> AMZN | B11: ='Stato patrimoniale'!K11 -> US0231351067 | C11: ='Stato patrimoniale'!C11 -> Amazon | D11: ='Stato patrimoniale'!D11 -> A | E11: ='Stato patrimoniale'!J11 -> USD | F11: ='Stato patrimoniale'!I11 -> 2 | G11: ='Stato patrimoniale'!W11 -> 217.78286 | H11: ='Stato patrimoniale'!U11 -> 0.9089 | I11: ='Stato patrimoniale'!V11 -> 12.95 | K11: ='Stato patrimoniale'!O11 -> 45044 | L11: Buy | M11: ='Stato patrimoniale'!Q11 -> Fineco-C | N11: =M11 -> Fineco-C
A12: ='Stato patrimoniale'!L12 -> MSFT | B12: ='Stato patrimoniale'!K12 -> US5949181045 | C12: ='Stato patrimoniale'!C12 -> Microsoft | D12: ='Stato patrimoniale'!D12 -> A | E12: ='Stato patrimoniale'!J12 -> USD | F12: ='Stato patrimoniale'!I12 -> 10 | G12: ='Stato patrimoniale'!W12 -> 1731.8 | H12: ='Stato patrimoniale'!U12 -> 1 | I12: ='Stato patrimoniale'!V12 -> 0 | K12: ='Stato patrimoniale'!O12 -> 42006 | L12: Buy | M12: ='Stato patrimoniale'!Q12 -> Fineco-C | N12: =M12 -> Fineco-C
A13: ='Stato patrimoniale'!L13 -> MSFT | B13: ='Stato patrimoniale'!K13 -> US5949181045 | C13: ='Stato patrimoniale'!C13 -> Microsoft | D13: ='Stato patrimoniale'!D13 -> A | E13: ='Stato patrimoniale'!J13 -> USD | F13: ='Stato patrimoniale'!I13 -> 17 | G13: ='Stato patrimoniale'!W13 -> 2944.06 | H13: ='Stato patrimoniale'!U13 -> 1 | I13: ='Stato patrimoniale'!V13 -> 0 | K13: ='Stato patrimoniale'!O13 -> 45279 | L13: Buy | M13: ='Stato patrimoniale'!Q13 -> Fineco-C | N13: =M13 -> Fineco-C
... A89: ='Stato patrimoniale'!L89 -> VWCE.MI | B89: ='Stato patrimoniale'!K89 -> IE00BK5BQT80 | C89: ='Stato patrimoniale'!C89 -> Vanguard FTSE All-World UCITS ETF (USD) Acc | D89: ='Stato patrimoniale'!D89 -> ETF | E89: ='Stato patrimoniale'!J89 -> EUR | F89: ='Stato patrimoniale'!I89 -> 7 | G89: ='Stato patrimoniale'!W89 -> 1094.04 | H89: ='Stato patrimoniale'!U89 -> 1 | I89: ='Stato patrimoniale'!V89 -> 2.95 | K89: ='Stato patrimoniale'!O89 -> 46147 | L89: Buy | M89: ='Stato patrimoniale'!Q89 -> Fineco | N89: =M89 -> Fineco
A90: ='Stato patrimoniale'!L90 -> 0 | B90: ='Stato patrimoniale'!K90 -> 0
B91: ='Stato patrimoniale'!K91 -> 0
B92: ='Stato patrimoniale'!K92 -> 0

Sheet Transaction_Sell
A1: Id | B1: Ticker Symbol | C1: ISIN | D1: Security Name | E1: Class | F1: Currency Gross Amount | G1: Shares | H1: Value | I1: Exchange rate | J1: fees | K1: taxes | L1: Date | M1: Type | N1: Securities account | O1: Cash Account
A2: {=_xlfn._xlws.FILTER('Stato patrimoniale'!A2:A10004,'Stato patrimoniale'!AG2:AG10004<>"")} -> 13 | B2: =IF(INDEX('Stato patrimoniale'!L:L,MATCH(A2,'Stato patrimoniale'!A:A,0))<>0,INDEX('Stato patrimoniale'!L:L,MATCH(A2,'Stato patrimoniale'!A:A,0)),"") -> CNHI.VI | C2: =INDEX('Stato patrimoniale'!K:K,MATCH(A2,'Stato patrimoniale'!A:A,0)) -> NL0010545661 | D2: =INDEX('Stato patrimoniale'!C:C,MATCH(A2,'Stato patrimoniale'!A:A,0)) -> CNH Industrial | E2: =INDEX('Stato patrimoniale'!D:D,MATCH(A2,'Stato patrimoniale'!A:A,0)) -> A | F2: =INDEX('Stato patrimoniale'!J:J,MATCH(A2,'Stato patrimoniale'!A:A,0)) -> EUR | G2: =INDEX('Stato patrimoniale'!I:I,MATCH(A2,'Stato patrimoniale'!A:A,0)) -> 18 | H2: =IF(E2="O",G2*INDEX('Stato patrimoniale'!AJ:AJ,MATCH(A2,'Stato patrimoniale'!A:A,0))/100,G2*INDEX('Stato patrimoniale'!AJ:AJ,MATCH(A2,'Stato patrimoniale'!A:A,0))) -> 164.34 | I2: =INDEX('Stato patrimoniale'!AM:AM,MATCH(A2,'Stato patrimoniale'!A:A,0)) -> 1 | J2: =INDEX('Stato patrimoniale'!AL:AL,MATCH(A2,'Stato patrimoniale'!A:A,0)) -> 2.95 | K2: =IF(INDEX('Stato patrimoniale'!AS:AS,MATCH(A2,'Stato patrimoniale'!A:A,0))>0,INDEX('Stato patrimoniale'!AS:AS,MATCH(A2,'Stato patrimoniale'!A:A,0)),0) -> 0 | L2: =INDEX('Stato patrimoniale'!AG:AG,MATCH(A2,'Stato patrimoniale'!A:A,0)) -> 45531 | M2: Sell | N2: =INDEX('Stato patrimoniale'!Q:Q,MATCH(A2,'Stato patrimoniale'!A:A,0)) -> Fineco-C | O2: =N2 -> Fineco-C
A3: 14 | B3: =IF(INDEX('Stato patrimoniale'!L:L,MATCH(A3,'Stato patrimoniale'!A:A,0))<>0,INDEX('Stato patrimoniale'!L:L,MATCH(A3,'Stato patrimoniale'!A:A,0)),"") -> UCG.MI | C3: =INDEX('Stato patrimoniale'!K:K,MATCH(A3,'Stato patrimoniale'!A:A,0)) -> IT0005239360 | D3: =INDEX('Stato patrimoniale'!C:C,MATCH(A3,'Stato patrimoniale'!A:A,0)) -> Unicredit | E3: =INDEX('Stato patrimoniale'!D:D,MATCH(A3,'Stato patrimoniale'!A:A,0)) -> A | F3: =INDEX('Stato patrimoniale'!J:J,MATCH(A3,'Stato patrimoniale'!A:A,0)) -> EUR | G3: =INDEX('Stato patrimoniale'!I:I,MATCH(A3,'Stato patrimoniale'!A:A,0)) -> 11 | H3: =IF(E3="O",G3*INDEX('Stato patrimoniale'!AJ:AJ,MATCH(A3,'Stato patrimoniale'!A:A,0))/100,G3*INDEX('Stato patrimoniale'!AJ:AJ,MATCH(A3,'Stato patrimoniale'!A:A,0))) -> 495 | I3: =INDEX('Stato patrimoniale'!AM:AM,MATCH(A3,'Stato patrimoniale'!A:A,0)) -> 1 | J3: =INDEX('Stato patrimoniale'!AL:AL,MATCH(A3,'Stato patrimoniale'!A:A,0)) -> 2.95 | K3: =IF(INDEX('Stato patrimoniale'!AS:AS,MATCH(A3,'Stato patrimoniale'!A:A,0))>0,INDEX('Stato patrimoniale'!AS:AS,MATCH(A3,'Stato patrimoniale'!A:A,0)),0) -> 63.81752 | L3: =INDEX('Stato patrimoniale'!AG:AG,MATCH(A3,'Stato patrimoniale'!A:A,0)) -> 45691 | M3: Sell | N3: =INDEX('Stato patrimoniale'!Q:Q,MATCH(A3,'Stato patrimoniale'!A:A,0)) -> Fineco-C | O3: =N3 -> Fineco-C
A4: 15 | B4: =IF(INDEX('Stato patrimoniale'!L:L,MATCH(A4,'Stato patrimoniale'!A:A,0))<>0,INDEX('Stato patrimoniale'!L:L,MATCH(A4,'Stato patrimoniale'!A:A,0)),"") -> PST.MI | C4: =INDEX('Stato patrimoniale'!K:K,MATCH(A4,'Stato patrimoniale'!A:A,0)) -> IT0003796171 | D4: =INDEX('Stato patrimoniale'!C:C,MATCH(A4,'Stato patrimoniale'!A:A,0)) -> Poste Italiane | E4: =INDEX('Stato patrimoniale'!D:D,MATCH(A4,'Stato patrimoniale'!A:A,0)) -> A | F4: =INDEX('Stato patrimoniale'!J:J,MATCH(A4,'Stato patrimoniale'!A:A,0)) -> EUR | G4: =INDEX('Stato patrimoniale'!I:I,MATCH(A4,'Stato patrimoniale'!A:A,0)) -> 25 | H4: =IF(E4="O",G4*INDEX('Stato patrimoniale'!AJ:AJ,MATCH(A4,'Stato patrimoniale'!A:A,0))/100,G4*INDEX('Stato patrimoniale'!AJ:AJ,MATCH(A4,'Stato patrimoniale'!A:A,0))) -> 514 | I4: =INDEX('Stato patrimoniale'!AM:AM,MATCH(A4,'Stato patrimoniale'!A:A,0)) -> 1 | J4: =INDEX('Stato patrimoniale'!AL:AL,MATCH(A4,'Stato patrimoniale'!A:A,0)) -> 2.95 | K4: =IF(INDEX('Stato patrimoniale'!AS:AS,MATCH(A4,'Stato patrimoniale'!A:A,0))>0,INDEX('Stato patrimoniale'!AS:AS,MATCH(A4,'Stato patrimoniale'!A:A,0)),0) -> 66.066 | L4: =INDEX('Stato patrimoniale'!AG:AG,MATCH(A4,'Stato patrimoniale'!A:A,0)) -> 45992 | M4: Sell | N4: =INDEX('Stato patrimoniale'!Q:Q,MATCH(A4,'Stato patrimoniale'!A:A,0)) -> Fineco-C | O4: =N4 -> Fineco-C
A5: 16 | B5: =IF(INDEX('Stato patrimoniale'!L:L,MATCH(A5,'Stato patrimoniale'!A:A,0))<>0,INDEX('Stato patrimoniale'!L:L,MATCH(A5,'Stato patrimoniale'!A:A,0)),"") -> STMMI.MI | C5: =INDEX('Stato patrimoniale'!K:K,MATCH(A5,'Stato patrimoniale'!A:A,0)) -> NL0000226223 | D5: =INDEX('Stato patrimoniale'!C:C,MATCH(A5,'Stato patrimoniale'!A:A,0)) -> STMicroElectronics | E5: =INDEX('Stato patrimoniale'!D:D,MATCH(A5,'Stato patrimoniale'!A:A,0)) -> A | F5: =INDEX('Stato patrimoniale'!J:J,MATCH(A5,'Stato patrimoniale'!A:A,0)) -> EUR | G5: =INDEX('Stato patrimoniale'!I:I,MATCH(A5,'Stato patrimoniale'!A:A,0)) -> 5 | H5: =IF(E5="O",G5*INDEX('Stato patrimoniale'!AJ:AJ,MATCH(A5,'Stato patrimoniale'!A:A,0))/100,G5*INDEX('Stato patrimoniale'!AJ:AJ,MATCH(A5,'Stato patrimoniale'!A:A,0))) -> 139 | I5: =INDEX('Stato patrimoniale'!AM:AM,MATCH(A5,'Stato patrimoniale'!A:A,0)) -> 1 | J5: =INDEX('Stato patrimoniale'!AL:AL,MATCH(A5,'Stato patrimoniale'!A:A,0)) -> 2.95 | K5: =IF(INDEX('Stato patrimoniale'!AS:AS,MATCH(A5,'Stato patrimoniale'!A:A,0))>0,INDEX('Stato patrimoniale'!AS:AS,MATCH(A5,'Stato patrimoniale'!A:A,0)),0) -> 0 | L5: =INDEX('Stato patrimoniale'!AG:AG,MATCH(A5,'Stato patrimoniale'!A:A,0)) -> 45531 | M5: Sell | N5: =INDEX('Stato patrimoniale'!Q:Q,MATCH(A5,'Stato patrimoniale'!A:A,0)) -> Fineco-C | O5: =N5 -> Fineco-C
A6: 17 | B6: =IF(INDEX('Stato patrimoniale'!L:L,MATCH(A6,'Stato patrimoniale'!A:A,0))<>0,INDEX('Stato patrimoniale'!L:L,MATCH(A6,'Stato patrimoniale'!A:A,0)),"") -> ISP.MI | C6: =INDEX('Stato patrimoniale'!K:K,MATCH(A6,'Stato patrimoniale'!A:A,0)) -> IT0000072618 | D6: =INDEX('Stato patrimoniale'!C:C,MATCH(A6,'Stato patrimoniale'!A:A,0)) -> Intesa San Paolo | E6: =INDEX('Stato patrimoniale'!D:D,MATCH(A6,'Stato patrimoniale'!A:A,0)) -> A | F6: =INDEX('Stato patrimoniale'!J:J,MATCH(A6,'Stato patrimoniale'!A:A,0)) -> EUR | G6: =INDEX('Stato patrimoniale'!I:I,MATCH(A6,'Stato patrimoniale'!A:A,0)) -> 100 | H6: =IF(E6="O",G6*INDEX('Stato patrimoniale'!AJ:AJ,MATCH(A6,'Stato patrimoniale'!A:A,0))/100,G6*INDEX('Stato patrimoniale'!AJ:AJ,MATCH(A6,'Stato patrimoniale'!A:A,0))) -> 510.9 | I6: =INDEX('Stato patrimoniale'!AM:AM,MATCH(A6,'Stato patrimoniale'!A:A,0)) -> 1 | J6: =INDEX('Stato patrimoniale'!AL:AL,MATCH(A6,'Stato patrimoniale'!A:A,0)) -> 2.95 | K6: =IF(INDEX('Stato patrimoniale'!AS:AS,MATCH(A6,'Stato patrimoniale'!A:A,0))>0,INDEX('Stato patrimoniale'!AS:AS,MATCH(A6,'Stato patrimoniale'!A:A,0)),0) -> 65.65 | L6: =INDEX('Stato patrimoniale'!AG:AG,MATCH(A6,'Stato patrimoniale'!A:A,0)) -> 45862 | M6: Sell | N6: =INDEX('Stato patrimoniale'!Q:Q,MATCH(A6,'Stato patrimoniale'!A:A,0)) -> Fineco-C | O6: =N6 -> Fineco-C
A7: 18 | B7: =IF(INDEX('Stato patrimoniale'!L:L,MATCH(A7,'Stato patrimoniale'!A:A,0))<>0,INDEX('Stato patrimoniale'!L:L,MATCH(A7,'Stato patrimoniale'!A:A,0)),"") -> LDO.MI | C7: =INDEX('Stato patrimoniale'!K:K,MATCH(A7,'Stato patrimoniale'!A:A,0)) -> IT0003856405 | D7: =INDEX('Stato patrimoniale'!C:C,MATCH(A7,'Stato patrimoniale'!A:A,0)) -> Leonardo | E7: =INDEX('Stato patrimoniale'!D:D,MATCH(A7,'Stato patrimoniale'!A:A,0)) -> A | F7: =INDEX('Stato patrimoniale'!J:J,MATCH(A7,'Stato patrimoniale'!A:A,0)) -> EUR | G7: =INDEX('Stato patrimoniale'!I:I,MATCH(A7,'Stato patrimoniale'!A:A,0)) -> 21 | H7: =IF(E7="O",G7*INDEX('Stato patrimoniale'!AJ:AJ,MATCH(A7,'Stato patrimoniale'!A:A,0))/100,G7*INDEX('Stato patrimoniale'!AJ:AJ,MATCH(A7,'Stato patrimoniale'!A:A,0))) -> 502.95 | I7: =INDEX('Stato patrimoniale'!AM:AM,MATCH(A7,'Stato patrimoniale'!A:A,0)) -> 1 | J7: =INDEX('Stato patrimoniale'!AL:AL,MATCH(A7,'Stato patrimoniale'!A:A,0)) -> 2.95 | K7: =IF(INDEX('Stato patrimoniale'!AS:AS,MATCH(A7,'Stato patrimoniale'!A:A,0))>0,INDEX('Stato patrimoniale'!AS:AS,MATCH(A7,'Stato patrimoniale'!A:A,0)),0) -> 66.4456 | L7: =INDEX('Stato patrimoniale'!AG:AG,MATCH(A7,'Stato patrimoniale'!A:A,0)) -> 45446 | M7: Sell | N7: =INDEX('Stato patrimoniale'!Q:Q,MATCH(A7,'Stato patrimoniale'!A:A,0)) -> Fineco-C | O7: =N7 -> Fineco-C
A8: 22 | B8: =IF(INDEX('Stato patrimoniale'!L:L,MATCH(A8,'Stato patrimoniale'!A:A,0))<>0,INDEX('Stato patrimoniale'!L:L,MATCH(A8,'Stato patrimoniale'!A:A,0)),"") -> AMZN | C8: =INDEX('Stato patrimoniale'!K:K,MATCH(A8,'Stato patrimoniale'!A:A,0)) -> US0231351067 | D8: =INDEX('Stato patrimoniale'!C:C,MATCH(A8,'Stato patrimoniale'!A:A,0)) -> Amazon | E8: =INDEX('Stato patrimoniale'!D:D,MATCH(A8,'Stato patrimoniale'!A:A,0)) -> A | F8: =INDEX('Stato patrimoniale'!J:J,MATCH(A8,'Stato patrimoniale'!A:A,0)) -> USD | G8: =INDEX('Stato patrimoniale'!I:I,MATCH(A8,'Stato patrimoniale'!A:A,0)) -> 2 | H8: =IF(E8="O",G8*INDEX('Stato patrimoniale'!AJ:AJ,MATCH(A8,'Stato patrimoniale'!A:A,0))/100,G8*INDEX('Stato patrimoniale'!AJ:AJ,MATCH(A8,'Stato patrimoniale'!A:A,0))) -> 457.0508 | I8: =INDEX('Stato patrimoniale'!AM:AM,MATCH(A8,'Stato patrimoniale'!A:A,0)) -> 0.8572 | J8: =INDEX('Stato patrimoniale'!AL:AL,MATCH(A8,'Stato patrimoniale'!A:A,0)) -> 10 | K8: =IF(INDEX('Stato patrimoniale'!AS:AS,MATCH(A8,'Stato patrimoniale'!A:A,0))>0,INDEX('Stato patrimoniale'!AS:AS,MATCH(A8,'Stato patrimoniale'!A:A,0)),0) -> 43.011563 | L8: =INDEX('Stato patrimoniale'!AG:AG,MATCH(A8,'Stato patrimoniale'!A:A,0)) -> 45992 | M8: Sell | N8: =INDEX('Stato patrimoniale'!Q:Q,MATCH(A8,'Stato patrimoniale'!A:A,0)) -> Fineco-C | O8: =N8 -> Fineco-C
A9: 32 | B9: =IF(INDEX('Stato patrimoniale'!L:L,MATCH(A9,'Stato patrimoniale'!A:A,0))<>0,INDEX('Stato patrimoniale'!L:L,MATCH(A9,'Stato patrimoniale'!A:A,0)),"") -> MSFT | C9: =INDEX('Stato patrimoniale'!K:K,MATCH(A9,'Stato patrimoniale'!A:A,0)) -> US5949181045 | D9: =INDEX('Stato patrimoniale'!C:C,MATCH(A9,'Stato patrimoniale'!A:A,0)) -> Microsoft | E9: =INDEX('Stato patrimoniale'!D:D,MATCH(A9,'Stato patrimoniale'!A:A,0)) -> A | F9: =INDEX('Stato patrimoniale'!J:J,MATCH(A9,'Stato patrimoniale'!A:A,0)) -> USD | G9: =INDEX('Stato patrimoniale'!I:I,MATCH(A9,'Stato patrimoniale'!A:A,0)) -> 10 | H9: =IF(E9="O",G9*INDEX('Stato patrimoniale'!AJ:AJ,MATCH(A9,'Stato patrimoniale'!A:A,0))/100,G9*INDEX('Stato patrimoniale'!AJ:AJ,MATCH(A9,'Stato patrimoniale'!A:A,0))) -> 3787 | I9: =INDEX('Stato patrimoniale'!AM:AM,MATCH(A9,'Stato patrimoniale'!A:A,0)) -> 0.9116 | J9: =INDEX('Stato patrimoniale'!AL:AL,MATCH(A9,'Stato patrimoniale'!A:A,0)) -> 23.53 | K9: =IF(INDEX('Stato patrimoniale'!AS:AS,MATCH(A9,'Stato patrimoniale'!A:A,0))>0,INDEX('Stato patrimoniale'!AS:AS,MATCH(A9,'Stato patrimoniale'!A:A,0)),0) -> 441.73461 | L9: =INDEX('Stato patrimoniale'!AG:AG,MATCH(A9,'Stato patrimoniale'!A:A,0)) -> 45301 | M9: Sell | N9: =INDEX('Stato patrimoniale'!Q:Q,MATCH(A9,'Stato patrimoniale'!A:A,0)) -> Fineco-C | O9: =N9 -> Fineco-C
A10: 54 | B10: =IF(INDEX('Stato patrimoniale'!L:L,MATCH(A10,'Stato patrimoniale'!A:A,0))<>0,INDEX('Stato patrimoniale'!L:L,MATCH(A10,'Stato patrimoniale'!A:A,0)),"") -> MSFT | C10: =INDEX('Stato patrimoniale'!K:K,MATCH(A10,'Stato patrimoniale'!A:A,0)) -> US5949181045 | D10: =INDEX('Stato patrimoniale'!C:C,MATCH(A10,'Stato patrimoniale'!A:A,0)) -> Microsoft | E10: =INDEX('Stato patrimoniale'!D:D,MATCH(A10,'Stato patrimoniale'!A:A,0)) -> A | F10: =INDEX('Stato patrimoniale'!J:J,MATCH(A10,'Stato patrimoniale'!A:A,0)) -> USD | G10: =INDEX('Stato patrimoniale'!I:I,MATCH(A10,'Stato patrimoniale'!A:A,0)) -> 10 | H10: =IF(E10="O",G10*INDEX('Stato patrimoniale'!AJ:AJ,MATCH(A10,'Stato patrimoniale'!A:A,0))/100,G10*INDEX('Stato patrimoniale'!AJ:AJ,MATCH(A10,'Stato patrimoniale'!A:A,0))) -> 4546 | I10: =INDEX('Stato patrimoniale'!AM:AM,MATCH(A10,'Stato patrimoniale'!A:A,0)) -> 0.9553 | J10: =INDEX('Stato patrimoniale'!AL:AL,MATCH(A10,'Stato patrimoniale'!A:A,0)) -> 27.28 | K10: =IF(INDEX('Stato patrimoniale'!AS:AS,MATCH(A10,'Stato patrimoniale'!A:A,0))>0,INDEX('Stato patrimoniale'!AS:AS,MATCH(A10,'Stato patrimoniale'!A:A,0)),0) -> 431.55264 | L10: =INDEX('Stato patrimoniale'!AG:AG,MATCH(A10,'Stato patrimoniale'!A:A,0)) -> 45638 | M10: Sell | N10: =INDEX('Stato patrimoniale'!Q:Q,MATCH(A10,'Stato patrimoniale'!A:A,0)) -> Fineco-C | O10: =N10 -> Fineco-C
A11: 3 | B11: =IF(INDEX('Stato patrimoniale'!L:L,MATCH(A11,'Stato patrimoniale'!A:A,0))<>0,INDEX('Stato patrimoniale'!L:L,MATCH(A11,'Stato patrimoniale'!A:A,0)),"") -> VFEM.MI | C11: =INDEX('Stato patrimoniale'!K:K,MATCH(A11,'Stato patrimoniale'!A:A,0)) -> IE00B3VVMM84 | D11: =INDEX('Stato patrimoniale'!C:C,MATCH(A11,'Stato patrimoniale'!A:A,0)) -> Vanguard FTSE Emerging Markets UCITS ETF (USD) Dis | E11: =INDEX('Stato patrimoniale'!D:D,MATCH(A11,'Stato patrimoniale'!A:A,0)) -> ETF | F11: =INDEX('Stato patrimoniale'!J:J,MATCH(A11,'Stato patrimoniale'!A:A,0)) -> EUR | G11: =INDEX('Stato patrimoniale'!I:I,MATCH(A11,'Stato patrimoniale'!A:A,0)) -> 10 | H11: =IF(E11="O",G11*INDEX('Stato patrimoniale'!AJ:AJ,MATCH(A11,'Stato patrimoniale'!A:A,0))/100,G11*INDEX('Stato patrimoniale'!AJ:AJ,MATCH(A11,'Stato patrimoniale'!A:A,0))) -> 639.6 | I11: =INDEX('Stato patrimoniale'!AM:AM,MATCH(A11,'Stato patrimoniale'!A:A,0)) -> 1 | J11: =INDEX('Stato patrimoniale'!AL:AL,MATCH(A11,'Stato patrimoniale'!A:A,0)) -> 2.95 | K11: =IF(INDEX('Stato patrimoniale'!AS:AS,MATCH(A11,'Stato patrimoniale'!A:A,0))>0,INDEX('Stato patrimoniale'!AS:AS,MATCH(A11,'Stato patrimoniale'!A:A,0)),0) -> 31.356 | L11: =INDEX('Stato patrimoniale'!AG:AG,MATCH(A11,'Stato patrimoniale'!A:A,0)) -> 45992 | M11: Sell | N11: =INDEX('Stato patrimoniale'!Q:Q,MATCH(A11,'Stato patrimoniale'!A:A,0)) -> Fineco-C | O11: =N11 -> Fineco-C
A12: 4 | B12: =IF(INDEX('Stato patrimoniale'!L:L,MATCH(A12,'Stato patrimoniale'!A:A,0))<>0,INDEX('Stato patrimoniale'!L:L,MATCH(A12,'Stato patrimoniale'!A:A,0)),"") -> INRG.MI | C12: =INDEX('Stato patrimoniale'!K:K,MATCH(A12,'Stato patrimoniale'!A:A,0)) -> IE00B1XNHC34 | D12: =INDEX('Stato patrimoniale'!C:C,MATCH(A12,'Stato patrimoniale'!A:A,0)) -> iShares Global Clean Energy UCITS ETF USD (Dist) | E12: =INDEX('Stato patrimoniale'!D:D,MATCH(A12,'Stato patrimoniale'!A:A,0)) -> ETF | F12: =INDEX('Stato patrimoniale'!J:J,MATCH(A12,'Stato patrimoniale'!A:A,0)) -> EUR | G12: =INDEX('Stato patrimoniale'!I:I,MATCH(A12,'Stato patrimoniale'!A:A,0)) -> 50 | H12: =IF(E12="O",G12*INDEX('Stato patrimoniale'!AJ:AJ,MATCH(A12,'Stato patrimoniale'!A:A,0))/100,G12*INDEX('Stato patrimoniale'!AJ:AJ,MATCH(A12,'Stato patrimoniale'!A:A,0))) -> 371.706 | I12: =INDEX('Stato patrimoniale'!AM:AM,MATCH(A12,'Stato patrimoniale'!A:A,0)) -> 1 | J12: =INDEX('Stato patrimoniale'!AL:AL,MATCH(A12,'Stato patrimoniale'!A:A,0)) -> 2.95 | K12: =IF(INDEX('Stato patrimoniale'!AS:AS,MATCH(A12,'Stato patrimoniale'!A:A,0))>0,INDEX('Stato patrimoniale'!AS:AS,MATCH(A12,'Stato patrimoniale'!A:A,0)),0) -> 0 | L12: =INDEX('Stato patrimoniale'!AG:AG,MATCH(A12,'Stato patrimoniale'!A:A,0)) -> 45531 | M12: Sell | N12: =INDEX('Stato patrimoniale'!Q:Q,MATCH(A12,'Stato patrimoniale'!A:A,0)) -> Fineco-C | O12: =N12 -> Fineco-C
A13: 5 | B13: =IF(INDEX('Stato patrimoniale'!L:L,MATCH(A13,'Stato patrimoniale'!A:A,0))<>0,INDEX('Stato patrimoniale'!L:L,MATCH(A13,'Stato patrimoniale'!A:A,0)),"") -> IUSA.MI | C13: =INDEX('Stato patrimoniale'!K:K,MATCH(A13,'Stato patrimoniale'!A:A,0)) -> IE0031442068 | D13: =INDEX('Stato patrimoniale'!C:C,MATCH(A13,'Stato patrimoniale'!A:A,0)) -> iShares Core S&P 500 UCITS ETF USD (Dist) | E13: =INDEX('Stato patrimoniale'!D:D,MATCH(A13,'Stato patrimoniale'!A:A,0)) -> ETF | F13: =INDEX('Stato patrimoniale'!J:J,MATCH(A13,'Stato patrimoniale'!A:A,0)) -> EUR | G13: =INDEX('Stato patrimoniale'!I:I,MATCH(A13,'Stato patrimoniale'!A:A,0)) -> 10 | H13: =IF(E13="O",G13*INDEX('Stato patrimoniale'!AJ:AJ,MATCH(A13,'Stato patrimoniale'!A:A,0))/100,G13*INDEX('Stato patrimoniale'!AJ:AJ,MATCH(A13,'Stato patrimoniale'!A:A,0))) -> 585.1 | I13: =INDEX('Stato patrimoniale'!AM:AM,MATCH(A13,'Stato patrimoniale'!A:A,0)) -> 1 | J13: =INDEX('Stato patrimoniale'!AL:AL,MATCH(A13,'Stato patrimoniale'!A:A,0)) -> 2.95 | K13: =IF(INDEX('Stato patrimoniale'!AS:AS,MATCH(A13,'Stato patrimoniale'!A:A,0))>0,INDEX('Stato patrimoniale'!AS:AS,MATCH(A13,'Stato patrimoniale'!A:A,0)),0) -> 44.954 | L13: =INDEX('Stato patrimoniale'!AG:AG,MATCH(A13,'Stato patrimoniale'!A:A,0)) -> 45992 | M13: Sell | N13: =INDEX('Stato patrimoniale'!Q:Q,MATCH(A13,'Stato patrimoniale'!A:A,0)) -> Fineco-C | O13: =N13 -> Fineco-C
A14: 6 | B14: =IF(INDEX('Stato patrimoniale'!L:L,MATCH(A14,'Stato patrimoniale'!A:A,0))<>0,INDEX('Stato patrimoniale'!L:L,MATCH(A14,'Stato patrimoniale'!A:A,0)),"") -> IUSA.MI | C14: =INDEX('Stato patrimoniale'!K:K,MATCH(A14,'Stato patrimoniale'!A:A,0)) -> IE0031442068 | D14: =INDEX('Stato patrimoniale'!C:C,MATCH(A14,'Stato patrimoniale'!A:A,0)) -> iShares Core S&P 500 UCITS ETF USD (Dist) | E14: =INDEX('Stato patrimoniale'!D:D,MATCH(A14,'Stato patrimoniale'!A:A,0)) -> ETF | F14: =INDEX('Stato patrimoniale'!J:J,MATCH(A14,'Stato patrimoniale'!A:A,0)) -> EUR | G14: =INDEX('Stato patrimoniale'!I:I,MATCH(A14,'Stato patrimoniale'!A:A,0)) -> 15 | H14: =IF(E14="O",G14*INDEX('Stato patrimoniale'!AJ:AJ,MATCH(A14,'Stato patrimoniale'!A:A,0))/100,G14*INDEX('Stato patrimoniale'!AJ:AJ,MATCH(A14,'Stato patrimoniale'!A:A,0))) -> 877.65 | I14: =INDEX('Stato patrimoniale'!AM:AM,MATCH(A14,'Stato patrimoniale'!A:A,0)) -> 1 | J14: =INDEX('Stato patrimoniale'!AL:AL,MATCH(A14,'Stato patrimoniale'!A:A,0)) -> 2.95 | K14: =IF(INDEX('Stato patrimoniale'!AS:AS,MATCH(A14,'Stato patrimoniale'!A:A,0))>0,INDEX('Stato patrimoniale'!AS:AS,MATCH(A14,'Stato patrimoniale'!A:A,0)),0) -> 67.925 | L14: =INDEX('Stato patrimoniale'!AG:AG,MATCH(A14,'Stato patrimoniale'!A:A,0)) -> 45992 | M14: Sell | N14: =INDEX('Stato patrimoniale'!Q:Q,MATCH(A14,'Stato patrimoniale'!A:A,0)) -> Fineco-C | O14: =N14 -> Fineco-C
... A20: 37 | B20: =IF(INDEX('Stato patrimoniale'!L:L,MATCH(A20,'Stato patrimoniale'!A:A,0))<>0,INDEX('Stato patrimoniale'!L:L,MATCH(A20,'Stato patrimoniale'!A:A,0)),"") | C20: =INDEX('Stato patrimoniale'!K:K,MATCH(A20,'Stato patrimoniale'!A:A,0)) -> IT0005584302 | D20: =INDEX('Stato patrimoniale'!C:C,MATCH(A20,'Stato patrimoniale'!A:A,0)) -> BTP-28GE26 3,2 | E20: =INDEX('Stato patrimoniale'!D:D,MATCH(A20,'Stato patrimoniale'!A:A,0)) -> O | F20: =INDEX('Stato patrimoniale'!J:J,MATCH(A20,'Stato patrimoniale'!A:A,0)) -> EUR | G20: =INDEX('Stato patrimoniale'!I:I,MATCH(A20,'Stato patrimoniale'!A:A,0)) -> 2000 | H20: =IF(E20="O",G20*INDEX('Stato patrimoniale'!AJ:AJ,MATCH(A20,'Stato patrimoniale'!A:A,0))/100,G20*INDEX('Stato patrimoniale'!AJ:AJ,MATCH(A20,'Stato patrimoniale'!A:A,0))) -> 1999.17 | I20: =INDEX('Stato patrimoniale'!AM:AM,MATCH(A20,'Stato patrimoniale'!A:A,0)) -> 1 | J20: =INDEX('Stato patrimoniale'!AL:AL,MATCH(A20,'Stato patrimoniale'!A:A,0)) -> 0 | K20: =IF(INDEX('Stato patrimoniale'!AS:AS,MATCH(A20,'Stato patrimoniale'!A:A,0))>0,INDEX('Stato patrimoniale'!AS:AS,MATCH(A20,'Stato patrimoniale'!A:A,0)),0) -> 0 | L20: =INDEX('Stato patrimoniale'!AG:AG,MATCH(A20,'Stato patrimoniale'!A:A,0)) -> 46050 | M20: Sell | N20: =INDEX('Stato patrimoniale'!Q:Q,MATCH(A20,'Stato patrimoniale'!A:A,0)) -> Fineco | O20: =N20 -> Fineco

Sheet Dividends
A1: Id | B1: Security Name | C1: Class | D1: Value | E1: taxes | F1: Date | G1: Type | H1: Securities account | I1: Cash Account
A2: {=Operazioni!A2:A158} -> 21 | B2: =INDEX('Stato patrimoniale'!C:C,MATCH(A2,'Stato patrimoniale'!A:A,0)) -> Apple | C2: =INDEX('Stato patrimoniale'!D:D,MATCH(A2,'Stato patrimoniale'!A:A,0)) -> A | D2: {=Operazioni!K2:K158} -> 0.2812 | E2: {=Operazioni!K2:K158-Operazioni!H2:H158} -> -0.0988 | F2: {=Operazioni!B2:B158} -> 44430 | G2: Dividend | H2: =INDEX('Stato patrimoniale'!Q:Q,MATCH(A2,'Stato patrimoniale'!A:A,0)) -> Fineco-C | I2: =H2 -> Fineco-C
A3: 23 | B3: =INDEX('Stato patrimoniale'!C:C,MATCH(A3,'Stato patrimoniale'!A:A,0)) -> Microsoft | C3: =INDEX('Stato patrimoniale'!D:D,MATCH(A3,'Stato patrimoniale'!A:A,0)) -> A | D3: 21.5266 | E3: -7.5634 | F3: 44452 | G3: Dividend | H3: =INDEX('Stato patrimoniale'!Q:Q,MATCH(A3,'Stato patrimoniale'!A:A,0)) -> Fineco-C | I3: =H3 -> Fineco-C
A4: 21 | B4: =INDEX('Stato patrimoniale'!C:C,MATCH(A4,'Stato patrimoniale'!A:A,0)) -> Apple | C4: =INDEX('Stato patrimoniale'!D:D,MATCH(A4,'Stato patrimoniale'!A:A,0)) -> A | D4: 0.2442 | E4: -0.0858 | F4: 44516 | G4: Dividend | H4: =INDEX('Stato patrimoniale'!Q:Q,MATCH(A4,'Stato patrimoniale'!A:A,0)) -> Fineco-C | I4: =H4 -> Fineco-C
A5: 23 | B5: =INDEX('Stato patrimoniale'!C:C,MATCH(A5,'Stato patrimoniale'!A:A,0)) -> Microsoft | C5: =INDEX('Stato patrimoniale'!D:D,MATCH(A5,'Stato patrimoniale'!A:A,0)) -> A | D5: 21.46 | E5: -7.54 | F5: 44545 | G5: Dividend | H5: =INDEX('Stato patrimoniale'!Q:Q,MATCH(A5,'Stato patrimoniale'!A:A,0)) -> Fineco-C | I5: =H5 -> Fineco-C
A6: 21 | B6: =INDEX('Stato patrimoniale'!C:C,MATCH(A6,'Stato patrimoniale'!A:A,0)) -> Apple | C6: =INDEX('Stato patrimoniale'!D:D,MATCH(A6,'Stato patrimoniale'!A:A,0)) -> A | D6: 0.2442 | E6: -0.0858 | F6: 44607 | G6: Dividend | H6: =INDEX('Stato patrimoniale'!Q:Q,MATCH(A6,'Stato patrimoniale'!A:A,0)) -> Fineco-C | I6: =H6 -> Fineco-C
A7: 23 | B7: =INDEX('Stato patrimoniale'!C:C,MATCH(A7,'Stato patrimoniale'!A:A,0)) -> Microsoft | C7: =INDEX('Stato patrimoniale'!D:D,MATCH(A7,'Stato patrimoniale'!A:A,0)) -> A | D7: 27.528 | E7: -9.672 | F7: 44637 | G7: Dividend | H7: =INDEX('Stato patrimoniale'!Q:Q,MATCH(A7,'Stato patrimoniale'!A:A,0)) -> Fineco-C | I7: =H7 -> Fineco-C
A8: 21 | B8: =INDEX('Stato patrimoniale'!C:C,MATCH(A8,'Stato patrimoniale'!A:A,0)) -> Apple | C8: =INDEX('Stato patrimoniale'!D:D,MATCH(A8,'Stato patrimoniale'!A:A,0)) -> A | D8: 0.2738 | E8: -0.0962 | F8: 44697 | G8: Dividend | H8: =INDEX('Stato patrimoniale'!Q:Q,MATCH(A8,'Stato patrimoniale'!A:A,0)) -> Fineco-C | I8: =H8 -> Fineco-C
A9: 23 | B9: =INDEX('Stato patrimoniale'!C:C,MATCH(A9,'Stato patrimoniale'!A:A,0)) -> Microsoft | C9: =INDEX('Stato patrimoniale'!D:D,MATCH(A9,'Stato patrimoniale'!A:A,0)) -> A | D9: 29.1042 | E9: -10.2258 | F9: 44726 | G9: Dividend | H9: =INDEX('Stato patrimoniale'!Q:Q,MATCH(A9,'Stato patrimoniale'!A:A,0)) -> Fineco-C | I9: =H9 -> Fineco-C
A10: 21 | B10: =INDEX('Stato patrimoniale'!C:C,MATCH(A10,'Stato patrimoniale'!A:A,0)) -> Apple | C10: =INDEX('Stato patrimoniale'!D:D,MATCH(A10,'Stato patrimoniale'!A:A,0)) -> A | D10: 0.2812 | E10: -0.0988 | F10: 44789 | G10: Dividend | H10: =INDEX('Stato patrimoniale'!Q:Q,MATCH(A10,'Stato patrimoniale'!A:A,0)) -> Fineco-C | I10: =H10 -> Fineco-C
A11: 23 | B11: =INDEX('Stato patrimoniale'!C:C,MATCH(A11,'Stato patrimoniale'!A:A,0)) -> Microsoft | C11: =INDEX('Stato patrimoniale'!D:D,MATCH(A11,'Stato patrimoniale'!A:A,0)) -> A | D11: 29.896 | E11: -10.504 | F11: 44817 | G11: Dividend | H11: =INDEX('Stato patrimoniale'!Q:Q,MATCH(A11,'Stato patrimoniale'!A:A,0)) -> Fineco-C | I11: =H11 -> Fineco-C
A12: 21 | B12: =INDEX('Stato patrimoniale'!C:C,MATCH(A12,'Stato patrimoniale'!A:A,0)) -> Apple | C12: =INDEX('Stato patrimoniale'!D:D,MATCH(A12,'Stato patrimoniale'!A:A,0)) -> A | D12: 0.2738 | E12: -0.0962 | F12: 44825 | G12: Dividend | H12: =INDEX('Stato patrimoniale'!Q:Q,MATCH(A12,'Stato patrimoniale'!A:A,0)) -> Fineco-C | I12: =H12 -> Fineco-C
A13: 21 | B13: =INDEX('Stato patrimoniale'!C:C,MATCH(A13,'Stato patrimoniale'!A:A,0)) -> Apple | C13: =INDEX('Stato patrimoniale'!D:D,MATCH(A13,'Stato patrimoniale'!A:A,0)) -> A | D13: 0.2812 | E13: -0.0988 | F13: 44879 | G13: Dividend | H13: =INDEX('Stato patrimoniale'!Q:Q,MATCH(A13,'Stato patrimoniale'!A:A,0)) -> Fineco-C | I13: =H13 -> Fineco-C
A14: 23 | B14: =INDEX('Stato patrimoniale'!C:C,MATCH(A14,'Stato patrimoniale'!A:A,0)) -> Microsoft | C14: =INDEX('Stato patrimoniale'!D:D,MATCH(A14,'Stato patrimoniale'!A:A,0)) -> A | D14: 31.4056 | E14: -11.0344 | F14: 44910 | G14: Dividend | H14: =INDEX('Stato patrimoniale'!Q:Q,MATCH(A14,'Stato patrimoniale'!A:A,0)) -> Fineco-C | I14: =H14 -> Fineco-C
... A158: 57 | B158: =INDEX('Stato patrimoniale'!C:C,MATCH(A158,'Stato patrimoniale'!A:A,0)) -> BTP-PIU 25FB33 CUM | C158: =INDEX('Stato patrimoniale'!D:D,MATCH(A158,'Stato patrimoniale'!A:A,0)) -> O | D158: 12.46875 | E158: -1.78125 | F158: 46167 | G158: Dividend | H158: =INDEX('Stato patrimoniale'!Q:Q,MATCH(A158,'Stato patrimoniale'!A:A,0)) -> Fineco | I158: =H158 -> Fineco

Sheet Per stock
A1: Titoli in portafoglio | P1: Titoli venduti
A2: Tipo | B2: Percentuale Portafoglio | C2: Costo totale | D2: Valore totale | E2: Delta | F2: Delta percentuale | P2: Tipo | Q2: Costo totale | R2: Ricavo totale | S2: Plusvalenza | T2: Rendimento medio
A3: {=_xlfn.UNIQUE('Stato patrimoniale'!C2:C106)} -> CNH Industrial | B3: =D3/SUM($D$3:$D$40) -> 0 | C3: =SUMIFS('Stato patrimoniale'!W:W,'Stato patrimoniale'!$AG:$AG,"",'Stato patrimoniale'!$C:$C,$A3,'Stato patrimoniale'!$B:$B,1) -> 0 | D3: =SUMIFS('Stato patrimoniale'!AD:AD,'Stato patrimoniale'!$AG:$AG,"",'Stato patrimoniale'!$C:$C,$A3,'Stato patrimoniale'!$B:$B,1) -> 0 | E3: =D3-C3 -> 0 | F3: =IF(C3=0,"",E3/C3) | P3: {=_xlfn.UNIQUE('Stato patrimoniale'!C2:C106)} -> CNH Industrial | Q3: =SUMIFS('Stato patrimoniale'!W:W,'Stato patrimoniale'!$AG:$AG,">0",'Stato patrimoniale'!$C:$C,$P3,'Stato patrimoniale'!$B:$B,1) -> 249.534 | R3: =SUMIFS('Stato patrimoniale'!AP:AP,'Stato patrimoniale'!$AG:$AG,">0",'Stato patrimoniale'!$C:$C,$P3,'Stato patrimoniale'!$B:$B,1) -> 167.1916 | S3: =R3-Q3 -> -82.3424 | T3: =IF(Q3=0,"",S3/Q3) -> -0.32998469
A4: Unicredit | B4: =D4/SUM($D$3:$D$40) -> 0 | C4: =SUMIFS('Stato patrimoniale'!W:W,'Stato patrimoniale'!$AG:$AG,"",'Stato patrimoniale'!$C:$C,$A4,'Stato patrimoniale'!$B:$B,1) -> 0 | D4: =SUMIFS('Stato patrimoniale'!AD:AD,'Stato patrimoniale'!$AG:$AG,"",'Stato patrimoniale'!$C:$C,$A4,'Stato patrimoniale'!$B:$B,1) -> 0 | E4: =D4-C4 -> 0 | F4: =IF(C4=0,"",E4/C4) | P4: Unicredit | Q4: =SUMIFS('Stato patrimoniale'!W:W,'Stato patrimoniale'!$AG:$AG,">0",'Stato patrimoniale'!$C:$C,$P4,'Stato patrimoniale'!$B:$B,1) -> 246.598 | R4: =SUMIFS('Stato patrimoniale'!AP:AP,'Stato patrimoniale'!$AG:$AG,">0",'Stato patrimoniale'!$C:$C,$P4,'Stato patrimoniale'!$B:$B,1) -> 514.2648 | S4: =R4-Q4 -> 267.6668 | T4: =IF(Q4=0,"",S4/Q4) -> 1.0854378
A5: Poste Italiane | B5: =D5/SUM($D$3:$D$40) -> 0 | C5: =SUMIFS('Stato patrimoniale'!W:W,'Stato patrimoniale'!$AG:$AG,"",'Stato patrimoniale'!$C:$C,$A5,'Stato patrimoniale'!$B:$B,1) -> 0 | D5: =SUMIFS('Stato patrimoniale'!AD:AD,'Stato patrimoniale'!$AG:$AG,"",'Stato patrimoniale'!$C:$C,$A5,'Stato patrimoniale'!$B:$B,1) -> 0 | E5: =D5-C5 -> 0 | F5: =IF(C5=0,"",E5/C5) | P5: Poste Italiane | Q5: =SUMIFS('Stato patrimoniale'!W:W,'Stato patrimoniale'!$AG:$AG,">0",'Stato patrimoniale'!$C:$C,$P5,'Stato patrimoniale'!$B:$B,1) -> 256.95 | R5: =SUMIFS('Stato patrimoniale'!AP:AP,'Stato patrimoniale'!$AG:$AG,">0",'Stato patrimoniale'!$C:$C,$P5,'Stato patrimoniale'!$B:$B,1) -> 545.8374 | S5: =R5-Q5 -> 288.8874 | T5: =IF(Q5=0,"",S5/Q5) -> 1.1242942
A6: STMicroElectronics | B6: =D6/SUM($D$3:$D$40) -> 0 | C6: =SUMIFS('Stato patrimoniale'!W:W,'Stato patrimoniale'!$AG:$AG,"",'Stato patrimoniale'!$C:$C,$A6,'Stato patrimoniale'!$B:$B,1) -> 0 | D6: =SUMIFS('Stato patrimoniale'!AD:AD,'Stato patrimoniale'!$AG:$AG,"",'Stato patrimoniale'!$C:$C,$A6,'Stato patrimoniale'!$B:$B,1) -> 0 | E6: =D6-C6 -> 0 | F6: =IF(C6=0,"",E6/C6) | P6: STMicroElectronics | Q6: =SUMIFS('Stato patrimoniale'!W:W,'Stato patrimoniale'!$AG:$AG,">0",'Stato patrimoniale'!$C:$C,$P6,'Stato patrimoniale'!$B:$B,1) -> 230.45 | R6: =SUMIFS('Stato patrimoniale'!AP:AP,'Stato patrimoniale'!$AG:$AG,">0",'Stato patrimoniale'!$C:$C,$P6,'Stato patrimoniale'!$B:$B,1) -> 136.8492 | S6: =R6-Q6 -> -93.6008 | T6: =IF(Q6=0,"",S6/Q6) -> -0.40616533
A7: Intesa San Paolo | B7: =D7/SUM($D$3:$D$40) -> 0 | C7: =SUMIFS('Stato patrimoniale'!W:W,'Stato patrimoniale'!$AG:$AG,"",'Stato patrimoniale'!$C:$C,$A7,'Stato patrimoniale'!$B:$B,1) -> 0 | D7: =SUMIFS('Stato patrimoniale'!AD:AD,'Stato patrimoniale'!$AG:$AG,"",'Stato patrimoniale'!$C:$C,$A7,'Stato patrimoniale'!$B:$B,1) -> 0 | E7: =D7-C7 -> 0 | F7: =IF(C7=0,"",E7/C7) | P7: Intesa San Paolo | Q7: =SUMIFS('Stato patrimoniale'!W:W,'Stato patrimoniale'!$AG:$AG,">0",'Stato patrimoniale'!$C:$C,$P7,'Stato patrimoniale'!$B:$B,1) -> 255.45 | R7: =SUMIFS('Stato patrimoniale'!AP:AP,'Stato patrimoniale'!$AG:$AG,">0",'Stato patrimoniale'!$C:$C,$P7,'Stato patrimoniale'!$B:$B,1) -> 555.088 | S7: =R7-Q7 -> 299.638 | T7: =IF(Q7=0,"",S7/Q7) -> 1.172981
A8: Leonardo | B8: =D8/SUM($D$3:$D$40) -> 0 | C8: =SUMIFS('Stato patrimoniale'!W:W,'Stato patrimoniale'!$AG:$AG,"",'Stato patrimoniale'!$C:$C,$A8,'Stato patrimoniale'!$B:$B,1) -> 0 | D8: =SUMIFS('Stato patrimoniale'!AD:AD,'Stato patrimoniale'!$AG:$AG,"",'Stato patrimoniale'!$C:$C,$A8,'Stato patrimoniale'!$B:$B,1) -> 0 | E8: =D8-C8 -> 0 | F8: =IF(C8=0,"",E8/C8) | P8: Leonardo | Q8: =SUMIFS('Stato patrimoniale'!W:W,'Stato patrimoniale'!$AG:$AG,">0",'Stato patrimoniale'!$C:$C,$P8,'Stato patrimoniale'!$B:$B,1) -> 244.44 | R8: =SUMIFS('Stato patrimoniale'!AP:AP,'Stato patrimoniale'!$AG:$AG,">0",'Stato patrimoniale'!$C:$C,$P8,'Stato patrimoniale'!$B:$B,1) -> 500 | S8: =R8-Q8 -> 255.56 | T8: =IF(Q8=0,"",S8/Q8) -> 1.0454917
A9: Enel | B9: =D9/SUM($D$3:$D$40) -> 0.0025008868 | C9: =SUMIFS('Stato patrimoniale'!W:W,'Stato patrimoniale'!$AG:$AG,"",'Stato patrimoniale'!$C:$C,$A9,'Stato patrimoniale'!$B:$B,1) -> 252.52 | D9: =SUMIFS('Stato patrimoniale'!AD:AD,'Stato patrimoniale'!$AG:$AG,"",'Stato patrimoniale'!$C:$C,$A9,'Stato patrimoniale'!$B:$B,1) -> 429.112 | E9: =D9-C9 -> 176.592 | F9: =IF(C9=0,"",E9/C9) -> 0.69931887 | P9: Enel | Q9: =SUMIFS('Stato patrimoniale'!W:W,'Stato patrimoniale'!$AG:$AG,">0",'Stato patrimoniale'!$C:$C,$P9,'Stato patrimoniale'!$B:$B,1) -> 0 | R9: =SUMIFS('Stato patrimoniale'!AP:AP,'Stato patrimoniale'!$AG:$AG,">0",'Stato patrimoniale'!$C:$C,$P9,'Stato patrimoniale'!$B:$B,1) -> 0 | S9: =R9-Q9 -> 0 | T9: =IF(Q9=0,"",S9/Q9)
A10: Eni | B10: =D10/SUM($D$3:$D$40) -> 0.002794842 | C10: =SUMIFS('Stato patrimoniale'!W:W,'Stato patrimoniale'!$AG:$AG,"",'Stato patrimoniale'!$C:$C,$A10,'Stato patrimoniale'!$B:$B,1) -> 264.993 | D10: =SUMIFS('Stato patrimoniale'!AD:AD,'Stato patrimoniale'!$AG:$AG,"",'Stato patrimoniale'!$C:$C,$A10,'Stato patrimoniale'!$B:$B,1) -> 479.55 | E10: =D10-C10 -> 214.557 | F10: =IF(C10=0,"",E10/C10) -> 0.80967045 | P10: Eni | Q10: =SUMIFS('Stato patrimoniale'!W:W,'Stato patrimoniale'!$AG:$AG,">0",'Stato patrimoniale'!$C:$C,$P10,'Stato patrimoniale'!$B:$B,1) -> 0 | R10: =SUMIFS('Stato patrimoniale'!AP:AP,'Stato patrimoniale'!$AG:$AG,">0",'Stato patrimoniale'!$C:$C,$P10,'Stato patrimoniale'!$B:$B,1) -> 0 | S10: =R10-Q10 -> 0 | T10: =IF(Q10=0,"",S10/Q10)
A11: Apple | B11: =D11/SUM($D$3:$D$40) -> 0.0031284283 | C11: =SUMIFS('Stato patrimoniale'!W:W,'Stato patrimoniale'!$AG:$AG,"",'Stato patrimoniale'!$C:$C,$A11,'Stato patrimoniale'!$B:$B,1) -> 282.06148 | D11: =SUMIFS('Stato patrimoniale'!AD:AD,'Stato patrimoniale'!$AG:$AG,"",'Stato patrimoniale'!$C:$C,$A11,'Stato patrimoniale'!$B:$B,1) -> 536.78804 | E11: =D11-C11 -> 254.72656 | F11: =IF(C11=0,"",E11/C11) -> 0.9030888 | P11: Apple | Q11: =SUMIFS('Stato patrimoniale'!W:W,'Stato patrimoniale'!$AG:$AG,">0",'Stato patrimoniale'!$C:$C,$P11,'Stato patrimoniale'!$B:$B,1) -> 0 | R11: =SUMIFS('Stato patrimoniale'!AP:AP,'Stato patrimoniale'!$AG:$AG,">0",'Stato patrimoniale'!$C:$C,$P11,'Stato patrimoniale'!$B:$B,1) -> 0 | S11: =R11-Q11 -> 0 | T11: =IF(Q11=0,"",S11/Q11)
A12: Amazon | B12: =D12/SUM($D$3:$D$40) -> 0 | C12: =SUMIFS('Stato patrimoniale'!W:W,'Stato patrimoniale'!$AG:$AG,"",'Stato patrimoniale'!$C:$C,$A12,'Stato patrimoniale'!$B:$B,1) -> 0 | D12: =SUMIFS('Stato patrimoniale'!AD:AD,'Stato patrimoniale'!$AG:$AG,"",'Stato patrimoniale'!$C:$C,$A12,'Stato patrimoniale'!$B:$B,1) -> 0 | E12: =D12-C12 -> 0 | F12: =IF(C12=0,"",E12/C12) | P12: Amazon | Q12: =SUMIFS('Stato patrimoniale'!W:W,'Stato patrimoniale'!$AG:$AG,">0",'Stato patrimoniale'!$C:$C,$P12,'Stato patrimoniale'!$B:$B,1) -> 217.78286 | R12: =SUMIFS('Stato patrimoniale'!AP:AP,'Stato patrimoniale'!$AG:$AG,">0",'Stato patrimoniale'!$C:$C,$P12,'Stato patrimoniale'!$B:$B,1) -> 383.21195 | S12: =R12-Q12 -> 165.42909 | T12: =IF(Q12=0,"",S12/Q12) -> 0.75960566
A13: Microsoft | B13: =D13/SUM($D$3:$D$40) -> 0.21344936 | C13: =SUMIFS('Stato patrimoniale'!W:W,'Stato patrimoniale'!$AG:$AG,"",'Stato patrimoniale'!$C:$C,$A13,'Stato patrimoniale'!$B:$B,1) -> 25000.028 | D13: =SUMIFS('Stato patrimoniale'!AD:AD,'Stato patrimoniale'!$AG:$AG,"",'Stato patrimoniale'!$C:$C,$A13,'Stato patrimoniale'!$B:$B,1) -> 36624.481 | E13: =D13-C13 -> 11624.453 | F13: =IF(C13=0,"",E13/C13) -> 0.46497762 | P13: Microsoft | Q13: =SUMIFS('Stato patrimoniale'!W:W,'Stato patrimoniale'!$AG:$AG,">0",'Stato patrimoniale'!$C:$C,$P13,'Stato patrimoniale'!$B:$B,1) -> 3463.6 | R13: =SUMIFS('Stato patrimoniale'!AP:AP,'Stato patrimoniale'!$AG:$AG,">0",'Stato patrimoniale'!$C:$C,$P13,'Stato patrimoniale'!$B:$B,1) -> 7747.5125 | S13: =R13-Q13 -> 4283.9125 | T13: =IF(Q13=0,"",S13/Q13) -> 1.2368381
A14: iShares Core MSCI World UCITS ETF USD (Acc) | B14: =D14/SUM($D$3:$D$40) -> 0.009338753 | C14: =SUMIFS('Stato patrimoniale'!W:W,'Stato patrimoniale'!$AG:$AG,"",'Stato patrimoniale'!$C:$C,$A14,'Stato patrimoniale'!$B:$B,1) -> 1000.94 | D14: =SUMIFS('Stato patrimoniale'!AD:AD,'Stato patrimoniale'!$AG:$AG,"",'Stato patrimoniale'!$C:$C,$A14,'Stato patrimoniale'!$B:$B,1) -> 1602.38 | E14: =D14-C14 -> 601.44 | F14: =IF(C14=0,"",E14/C14) -> 0.60087518 | P14: iShares Core MSCI World UCITS ETF USD (Acc) | Q14: =SUMIFS('Stato patrimoniale'!W:W,'Stato patrimoniale'!$AG:$AG,">0",'Stato patrimoniale'!$C:$C,$P14,'Stato patrimoniale'!$B:$B,1) -> 0 | R14: =SUMIFS('Stato patrimoniale'!AP:AP,'Stato patrimoniale'!$AG:$AG,">0",'Stato patrimoniale'!$C:$C,$P14,'Stato patrimoniale'!$B:$B,1) -> 0 | S14: =R14-Q14 -> 0 | T14: =IF(Q14=0,"",S14/Q14)
A15: Vanguard FTSE Emerging Markets UCITS ETF (USD) Dis | B15: =D15/SUM($D$3:$D$40) -> 0 | C15: =SUMIFS('Stato patrimoniale'!W:W,'Stato patrimoniale'!$AG:$AG,"",'Stato patrimoniale'!$C:$C,$A15,'Stato patrimoniale'!$B:$B,1) -> 0 | D15: =SUMIFS('Stato patrimoniale'!AD:AD,'Stato patrimoniale'!$AG:$AG,"",'Stato patrimoniale'!$C:$C,$A15,'Stato patrimoniale'!$B:$B,1) -> 0 | E15: =D15-C15 -> 0 | F15: =IF(C15=0,"",E15/C15) | P15: Vanguard FTSE Emerging Markets UCITS ETF (USD) Dis | Q15: =SUMIFS('Stato patrimoniale'!W:W,'Stato patrimoniale'!$AG:$AG,">0",'Stato patrimoniale'!$C:$C,$P15,'Stato patrimoniale'!$B:$B,1) -> 516.05 | R15: =SUMIFS('Stato patrimoniale'!AP:AP,'Stato patrimoniale'!$AG:$AG,">0",'Stato patrimoniale'!$C:$C,$P15,'Stato patrimoniale'!$B:$B,1) -> 661.588 | S15: =R15-Q15 -> 145.538 | T15: =IF(Q15=0,"",S15/Q15) -> 0.28202306
... A46: BTP-10MZ32 VAL CUM | B46: =D46/SUM($D$3:$D$40) -> 0.034968308 | C46: =SUMIFS('Stato patrimoniale'!W:W,'Stato patrimoniale'!$AG:$AG,"",'Stato patrimoniale'!$C:$C,$A46,'Stato patrimoniale'!$B:$B,1) -> 6000 | D46: =SUMIFS('Stato patrimoniale'!AD:AD,'Stato patrimoniale'!$AG:$AG,"",'Stato patrimoniale'!$C:$C,$A46,'Stato patrimoniale'!$B:$B,1) -> 6000 | E46: =D46-C46 -> 1.1351479e-05 | F46: =IF(C46=0,"",E46/C46) -> 1.8919131e-09 | P46: BTP-10MZ32 VAL CUM | Q46: =SUMIFS('Stato patrimoniale'!W:W,'Stato patrimoniale'!$AG:$AG,">0",'Stato patrimoniale'!$C:$C,$P46,'Stato patrimoniale'!$B:$B,1) -> 0 | R46: =SUMIFS('Stato patrimoniale'!AP:AP,'Stato patrimoniale'!$AG:$AG,">0",'Stato patrimoniale'!$C:$C,$P46,'Stato patrimoniale'!$B:$B,1) -> 0 | S46: =R46-Q46 -> 0 | T46: =IF(Q46=0,"",S46/Q46)
A47: 0 | P47: 0

Sheet Per tipo
A1: Titoli in portafoglio | O1: Titoli venduti
A2: Tipo | B2: Costo totale | C2: Valore totale | D2: Delta | E2: Delta percentuale | O2: Tipo | P2: Costo totale | Q2: Ricavo totale | R2: Plusvalenza | S2: Rendimento medio
A3: ETF | B3: =SUMIFS('Stato patrimoniale'!W:W,'Stato patrimoniale'!$AG:$AG,"",'Stato patrimoniale'!$D:$D,$A3,'Stato patrimoniale'!$B:$B,1) -> 124479.93 | C3: =SUMIFS('Stato patrimoniale'!AD:AD,'Stato patrimoniale'!$AG:$AG,"",'Stato patrimoniale'!$D:$D,$A3,'Stato patrimoniale'!$B:$B,1) -> 143874.44 | D3: =C3-B3 -> 19394.509 | E3: =IF(B3=0,"",D3/B3) -> 0.1558043 | O3: ETF | P3: =SUMIFS('Stato patrimoniale'!W:W,'Stato patrimoniale'!$AG:$AG,">0",'Stato patrimoniale'!$D:$D,$O3,'Stato patrimoniale'!$B:$B,1) -> 3116.6 | Q3: =SUMIFS('Stato patrimoniale'!AP:AP,'Stato patrimoniale'!$AG:$AG,">0",'Stato patrimoniale'!$D:$D,$O3,'Stato patrimoniale'!$B:$B,1) -> 4806.2737 | R3: =Q3-P3 -> 1689.6737 | S3: =IF(P3=0,"",R3/P3) -> 0.5421529
A4: A | B4: =SUMIFS('Stato patrimoniale'!W:W,'Stato patrimoniale'!$AG:$AG,"",'Stato patrimoniale'!$D:$D,$A4,'Stato patrimoniale'!$B:$B,1) -> 25799.602 | C4: =SUMIFS('Stato patrimoniale'!AD:AD,'Stato patrimoniale'!$AG:$AG,"",'Stato patrimoniale'!$D:$D,$A4,'Stato patrimoniale'!$B:$B,1) -> 38069.931 | D4: =C4-B4 -> 12270.329 | E4: =IF(B4=0,"",D4/B4) -> 0.47560148 | O4: A | P4: =SUMIFS('Stato patrimoniale'!W:W,'Stato patrimoniale'!$AG:$AG,">0",'Stato patrimoniale'!$D:$D,$O4,'Stato patrimoniale'!$B:$B,1) -> 5164.8049 | Q4: =SUMIFS('Stato patrimoniale'!AP:AP,'Stato patrimoniale'!$AG:$AG,">0",'Stato patrimoniale'!$D:$D,$O4,'Stato patrimoniale'!$B:$B,1) -> 10549.955 | R4: =Q4-P4 -> 5385.1506 | S4: =IF(P4=0,"",R4/P4) -> 1.0426629
A5: O | B5: =SUMIFS('Stato patrimoniale'!W:W,'Stato patrimoniale'!$AG:$AG,"",'Stato patrimoniale'!$D:$D,$A5,'Stato patrimoniale'!$B:$B,1) -> 41923.084 | C5: =SUMIFS('Stato patrimoniale'!AD:AD,'Stato patrimoniale'!$AG:$AG,"",'Stato patrimoniale'!$D:$D,$A5,'Stato patrimoniale'!$B:$B,1) -> 44097.953 | D5: =C5-B5 -> 2174.8689 | E5: =IF(B5=0,"",D5/B5) -> 0.051877599 | O5: O | P5: =SUMIFS('Stato patrimoniale'!W:W,'Stato patrimoniale'!$AG:$AG,">0",'Stato patrimoniale'!$D:$D,$O5,'Stato patrimoniale'!$B:$B,1) -> 16243.571 | Q5: =SUMIFS('Stato patrimoniale'!AP:AP,'Stato patrimoniale'!$AG:$AG,">0",'Stato patrimoniale'!$D:$D,$O5,'Stato patrimoniale'!$B:$B,1) -> 17019.3 | R5: =Q5-P5 -> 775.72834 | S5: =IF(P5=0,"",R5/P5) -> 0.047756021
A6: CC | B6: =SUMIFS('Stato patrimoniale'!W:W,'Stato patrimoniale'!$AG:$AG,"",'Stato patrimoniale'!$D:$D,$A6,'Stato patrimoniale'!$B:$B,1) -> 0 | C6: =SUMIFS('Stato patrimoniale'!AD:AD,'Stato patrimoniale'!$AG:$AG,"",'Stato patrimoniale'!$D:$D,$A6,'Stato patrimoniale'!$B:$B,1) -> 0 | D6: =C6-B6 -> 0 | E6: =IF(B6=0,"",D6/B6) | O6: CC | P6: =SUMIFS('Stato patrimoniale'!W:W,'Stato patrimoniale'!$AG:$AG,">0",'Stato patrimoniale'!$D:$D,$O6,'Stato patrimoniale'!$B:$B,1) -> 0 | Q6: =SUMIFS('Stato patrimoniale'!AP:AP,'Stato patrimoniale'!$AG:$AG,">0",'Stato patrimoniale'!$D:$D,$O6,'Stato patrimoniale'!$B:$B,1) -> 0 | R6: =Q6-P6 -> 0 | S6: =IF(P6=0,"",R6/P6)
A7: CD | B7: =SUMIFS('Stato patrimoniale'!W:W,'Stato patrimoniale'!$AG:$AG,"",'Stato patrimoniale'!$D:$D,$A7,'Stato patrimoniale'!$B:$B,1) -> 0 | C7: =SUMIFS('Stato patrimoniale'!AD:AD,'Stato patrimoniale'!$AG:$AG,"",'Stato patrimoniale'!$D:$D,$A7,'Stato patrimoniale'!$B:$B,1) -> 0 | D7: =C7-B7 -> 0 | E7: =IF(B7=0,"",D7/B7) | O7: CD | P7: =SUMIFS('Stato patrimoniale'!W:W,'Stato patrimoniale'!$AG:$AG,">0",'Stato patrimoniale'!$D:$D,$O7,'Stato patrimoniale'!$B:$B,1) -> 0 | Q7: =SUMIFS('Stato patrimoniale'!AP:AP,'Stato patrimoniale'!$AG:$AG,">0",'Stato patrimoniale'!$D:$D,$O7,'Stato patrimoniale'!$B:$B,1) -> 0 | R7: =Q7-P7 -> 0 | S7: =IF(P7=0,"",R7/P7)
A8: CR | B8: =SUMIFS('Stato patrimoniale'!W:W,'Stato patrimoniale'!$AG:$AG,"",'Stato patrimoniale'!$D:$D,$A8,'Stato patrimoniale'!$B:$B,1) -> 0 | C8: =SUMIFS('Stato patrimoniale'!AD:AD,'Stato patrimoniale'!$AG:$AG,"",'Stato patrimoniale'!$D:$D,$A8,'Stato patrimoniale'!$B:$B,1) -> 0 | D8: =C8-B8 -> 0 | E8: =IF(B8=0,"",D8/B8) | O8: CR | P8: =SUMIFS('Stato patrimoniale'!W:W,'Stato patrimoniale'!$AG:$AG,">0",'Stato patrimoniale'!$D:$D,$O8,'Stato patrimoniale'!$B:$B,1) -> 0 | Q8: =SUMIFS('Stato patrimoniale'!AP:AP,'Stato patrimoniale'!$AG:$AG,">0",'Stato patrimoniale'!$D:$D,$O8,'Stato patrimoniale'!$B:$B,1) -> 0 | R8: =Q8-P8 -> 0 | S8: =IF(P8=0,"",R8/P8)

Sheet Per classe
A1: Titoli in portafoglio | O1: Titoli venduti
A2: Classe | B2: Costo totale | C2: Valore totale | D2: Delta | E2: Delta percentuale | O2: Classe | P2: Costo totale | Q2: Ricavo totale | R2: Plusvalenza | S2: Rendimento medio
A3: Azioni | B3: =SUMIFS('Stato patrimoniale'!W:W,'Stato patrimoniale'!$AG:$AG,"",'Stato patrimoniale'!$E:$E,$A3,'Stato patrimoniale'!$B:$B,1) -> 86692.558 | C3: =SUMIFS('Stato patrimoniale'!AD:AD,'Stato patrimoniale'!$AG:$AG,"",'Stato patrimoniale'!$E:$E,$A3,'Stato patrimoniale'!$B:$B,1) -> 115362.39 | D3: =C3-B3 -> 28669.833 | E3: =IF(B3=0,"",D3/B3) -> 0.33070697 | O3: Azioni | P3: =SUMIFS('Stato patrimoniale'!W:W,'Stato patrimoniale'!$AG:$AG,">0",'Stato patrimoniale'!$E:$E,$O3,'Stato patrimoniale'!$B:$B,1) -> 8281.4049 | Q3: =SUMIFS('Stato patrimoniale'!AP:AP,'Stato patrimoniale'!$AG:$AG,">0",'Stato patrimoniale'!$E:$E,$O3,'Stato patrimoniale'!$B:$B,1) -> 15356.229 | R3: =Q3-P3 -> 7074.8243 | S3: =IF(P3=0,"",R3/P3) -> 0.85430243
A4: Obblig | B4: =SUMIFS('Stato patrimoniale'!W:W,'Stato patrimoniale'!$AG:$AG,"",'Stato patrimoniale'!$E:$E,$A4,'Stato patrimoniale'!$B:$B,1) -> 102006.95 | C4: =SUMIFS('Stato patrimoniale'!AD:AD,'Stato patrimoniale'!$AG:$AG,"",'Stato patrimoniale'!$E:$E,$A4,'Stato patrimoniale'!$B:$B,1) -> 105086.74 | D4: =C4-B4 -> 3079.7834 | E4: =IF(B4=0,"",D4/B4) -> 0.030191897 | O4: Obblig | P4: =SUMIFS('Stato patrimoniale'!W:W,'Stato patrimoniale'!$AG:$AG,">0",'Stato patrimoniale'!$E:$E,$O4,'Stato patrimoniale'!$B:$B,1) -> 16243.571 | Q4: =SUMIFS('Stato patrimoniale'!AP:AP,'Stato patrimoniale'!$AG:$AG,">0",'Stato patrimoniale'!$E:$E,$O4,'Stato patrimoniale'!$B:$B,1) -> 17019.3 | R4: =Q4-P4 -> 775.72834 | S4: =IF(P4=0,"",R4/P4) -> 0.047756021
A5: Oro | B5: =SUMIFS('Stato patrimoniale'!W:W,'Stato patrimoniale'!$AG:$AG,"",'Stato patrimoniale'!$E:$E,$A5,'Stato patrimoniale'!$B:$B,1) -> 3503.11 | C5: =SUMIFS('Stato patrimoniale'!AD:AD,'Stato patrimoniale'!$AG:$AG,"",'Stato patrimoniale'!$E:$E,$A5,'Stato patrimoniale'!$B:$B,1) -> 5593.2 | D5: =C5-B5 -> 2090.09 | E5: =IF(B5=0,"",D5/B5) -> 0.59663842 | O5: Oro | P5: =SUMIFS('Stato patrimoniale'!W:W,'Stato patrimoniale'!$AG:$AG,">0",'Stato patrimoniale'!$E:$E,$O5,'Stato patrimoniale'!$B:$B,1) -> 0 | Q5: =SUMIFS('Stato patrimoniale'!AP:AP,'Stato patrimoniale'!$AG:$AG,">0",'Stato patrimoniale'!$E:$E,$O5,'Stato patrimoniale'!$B:$B,1) -> 0 | R5: =Q5-P5 -> 0 | S5: =IF(P5=0,"",R5/P5)
A6: Liquidi | B6: =SUMIFS('Stato patrimoniale'!W:W,'Stato patrimoniale'!$AG:$AG,"",'Stato patrimoniale'!$E:$E,$A6,'Stato patrimoniale'!$B:$B,1) -> 0 | C6: =SUMIFS('Stato patrimoniale'!AD:AD,'Stato patrimoniale'!$AG:$AG,"",'Stato patrimoniale'!$E:$E,$A6,'Stato patrimoniale'!$B:$B,1) -> 0 | D6: =C6-B6 -> 0 | E6: =IF(B6=0,"",D6/B6) | O6: Liquidi | P6: =SUMIFS('Stato patrimoniale'!W:W,'Stato patrimoniale'!$AG:$AG,">0",'Stato patrimoniale'!$E:$E,$O6,'Stato patrimoniale'!$B:$B,1) -> 0 | Q6: =SUMIFS('Stato patrimoniale'!AP:AP,'Stato patrimoniale'!$AG:$AG,">0",'Stato patrimoniale'!$E:$E,$O6,'Stato patrimoniale'!$B:$B,1) -> 0 | R6: =Q6-P6 -> 0 | S6: =IF(P6=0,"",R6/P6)

Sheet Per valuta
A1: Titoli in portafoglio | O1: Titoli venduti
A2: Valuta | B2: Costo totale | C2: Valore totale | D2: Delta | E2: Delta percentuale | O2: Valuta | P2: Costo totale | Q2: Ricavo totale | R2: Plusvalenza | S2: Rendimento medio
A3: EUR | B3: =SUMIFS('Stato patrimoniale'!W:W,'Stato patrimoniale'!$AG:$AG,"",'Stato patrimoniale'!$J:$J,$A3,'Stato patrimoniale'!$B:$B,1) -> 166920.53 | C3: =SUMIFS('Stato patrimoniale'!AD:AD,'Stato patrimoniale'!$AG:$AG,"",'Stato patrimoniale'!$J:$J,$A3,'Stato patrimoniale'!$B:$B,1) -> 188881.06 | D3: =C3-B3 -> 21960.527 | E3: =IF(B3=0,"",D3/B3) -> 0.13156277 | O3: EUR | P3: =SUMIFS('Stato patrimoniale'!W:W,'Stato patrimoniale'!$AG:$AG,">0",'Stato patrimoniale'!$J:$J,$O3,'Stato patrimoniale'!$B:$B,1) -> 11631.811 | Q3: =SUMIFS('Stato patrimoniale'!AP:AP,'Stato patrimoniale'!$AG:$AG,">0",'Stato patrimoniale'!$J:$J,$O3,'Stato patrimoniale'!$B:$B,1) -> 14674.451 | R3: =Q3-P3 -> 3042.6399 | S3: =IF(P3=0,"",R3/P3) -> 0.26157921
A4: USD | B4: =SUMIFS('Stato patrimoniale'!W:W,'Stato patrimoniale'!$AG:$AG,"",'Stato patrimoniale'!$J:$J,$A4,'Stato patrimoniale'!$B:$B,1) -> 25282.089 | C4: =SUMIFS('Stato patrimoniale'!AD:AD,'Stato patrimoniale'!$AG:$AG,"",'Stato patrimoniale'!$J:$J,$A4,'Stato patrimoniale'!$B:$B,1) -> 37161.269 | D4: =C4-B4 -> 11879.18 | E4: =IF(B4=0,"",D4/B4) -> 0.46986544 | O4: USD | P4: =SUMIFS('Stato patrimoniale'!W:W,'Stato patrimoniale'!$AG:$AG,">0",'Stato patrimoniale'!$J:$J,$O4,'Stato patrimoniale'!$B:$B,1) -> 12893.165 | Q4: =SUMIFS('Stato patrimoniale'!AP:AP,'Stato patrimoniale'!$AG:$AG,">0",'Stato patrimoniale'!$J:$J,$O4,'Stato patrimoniale'!$B:$B,1) -> 17701.078 | R4: =Q4-P4 -> 4807.9127 | S4: =IF(P4=0,"",R4/P4) -> 0.37290399
A5: CHF | B5: =SUMIFS('Stato patrimoniale'!W:W,'Stato patrimoniale'!$AG:$AG,"",'Stato patrimoniale'!$J:$J,$A5,'Stato patrimoniale'!$B:$B,1) -> 0 | C5: =SUMIFS('Stato patrimoniale'!AD:AD,'Stato patrimoniale'!$AG:$AG,"",'Stato patrimoniale'!$J:$J,$A5,'Stato patrimoniale'!$B:$B,1) -> 0 | D5: =C5-B5 -> 0 | E5: =IF(B5=0,"",D5/B5) | O5: CHF | P5: =SUMIFS('Stato patrimoniale'!W:W,'Stato patrimoniale'!$AG:$AG,">0",'Stato patrimoniale'!$J:$J,$O5,'Stato patrimoniale'!$B:$B,1) -> 0 | Q5: =SUMIFS('Stato patrimoniale'!AP:AP,'Stato patrimoniale'!$AG:$AG,">0",'Stato patrimoniale'!$J:$J,$O5,'Stato patrimoniale'!$B:$B,1) -> 0 | R5: =Q5-P5 -> 0 | S5: =IF(P5=0,"",R5/P5)
A6: GBP | B6: =SUMIFS('Stato patrimoniale'!W:W,'Stato patrimoniale'!$AG:$AG,"",'Stato patrimoniale'!$J:$J,$A6,'Stato patrimoniale'!$B:$B,1) -> 0 | C6: =SUMIFS('Stato patrimoniale'!AD:AD,'Stato patrimoniale'!$AG:$AG,"",'Stato patrimoniale'!$J:$J,$A6,'Stato patrimoniale'!$B:$B,1) -> 0 | D6: =C6-B6 -> 0 | E6: =IF(B6=0,"",D6/B6) | O6: GBP | P6: =SUMIFS('Stato patrimoniale'!W:W,'Stato patrimoniale'!$AG:$AG,">0",'Stato patrimoniale'!$J:$J,$O6,'Stato patrimoniale'!$B:$B,1) -> 0 | Q6: =SUMIFS('Stato patrimoniale'!AP:AP,'Stato patrimoniale'!$AG:$AG,">0",'Stato patrimoniale'!$J:$J,$O6,'Stato patrimoniale'!$B:$B,1) -> 0 | R6: =Q6-P6 -> 0 | S6: =IF(P6=0,"",R6/P6)
A7: SEK | B7: =SUMIFS('Stato patrimoniale'!W:W,'Stato patrimoniale'!$AG:$AG,"",'Stato patrimoniale'!$J:$J,$A7,'Stato patrimoniale'!$B:$B,1) -> 0 | C7: =SUMIFS('Stato patrimoniale'!AD:AD,'Stato patrimoniale'!$AG:$AG,"",'Stato patrimoniale'!$J:$J,$A7,'Stato patrimoniale'!$B:$B,1) -> 0 | D7: =C7-B7 -> 0 | E7: =IF(B7=0,"",D7/B7) | O7: SEK | P7: =SUMIFS('Stato patrimoniale'!W:W,'Stato patrimoniale'!$AG:$AG,">0",'Stato patrimoniale'!$J:$J,$O7,'Stato patrimoniale'!$B:$B,1) -> 0 | Q7: =SUMIFS('Stato patrimoniale'!AP:AP,'Stato patrimoniale'!$AG:$AG,">0",'Stato patrimoniale'!$J:$J,$O7,'Stato patrimoniale'!$B:$B,1) -> 0 | R7: =Q7-P7 -> 0 | S7: =IF(P7=0,"",R7/P7)

Sheet Per Intermediario
A1: Titoli in portafoglio | O1: Titoli venduti
A2: Intermediario | B2: Costo totale | C2: Valore totale | D2: Delta | E2: Delta percentuale | O2: Intermediario | P2: Costo totale | Q2: Ricavo totale | R2: Plusvalenza | S2: Rendimento medio
A3: Fineco | B3: =SUMIFS('Stato patrimoniale'!W:W,'Stato patrimoniale'!$AG:$AG,"",'Stato patrimoniale'!$Y:$Y,$A3,'Stato patrimoniale'!$B:$B,1) -> 136764.01 | C3: =SUMIFS('Stato patrimoniale'!AD:AD,'Stato patrimoniale'!$AG:$AG,"",'Stato patrimoniale'!$Y:$Y,$A3,'Stato patrimoniale'!$B:$B,1) -> 147895.87 | D3: =C3-B3 -> 11131.86 | E3: =IF(B3=0,"",D3/B3) -> 0.08139466 | O3: Fineco | P3: =SUMIFS('Stato patrimoniale'!W:W,'Stato patrimoniale'!$AG:$AG,">0",'Stato patrimoniale'!$AI:$AI,$O3,'Stato patrimoniale'!$B:$B,1) -> 2228.1829 | Q3: =SUMIFS('Stato patrimoniale'!AP:AP,'Stato patrimoniale'!$AG:$AG,">0",'Stato patrimoniale'!$AI:$AI,$O3,'Stato patrimoniale'!$B:$B,1) -> 2489.7707 | R3: =Q3-P3 -> 261.58784 | S3: =IF(P3=0,"",R3/P3) -> 0.11739963
A4: Fineco-C | B4: =SUMIFS('Stato patrimoniale'!W:W,'Stato patrimoniale'!$AG:$AG,"",'Stato patrimoniale'!$Y:$Y,$A4,'Stato patrimoniale'!$B:$B,1) -> 39431.855 | C4: =SUMIFS('Stato patrimoniale'!AD:AD,'Stato patrimoniale'!$AG:$AG,"",'Stato patrimoniale'!$Y:$Y,$A4,'Stato patrimoniale'!$B:$B,1) -> 61446.295 | D4: =C4-B4 -> 22014.44 | E4: =IF(B4=0,"",D4/B4) -> 0.55829075 | O4: Fineco-C | P4: =SUMIFS('Stato patrimoniale'!W:W,'Stato patrimoniale'!$AG:$AG,">0",'Stato patrimoniale'!$AI:$AI,$O4,'Stato patrimoniale'!$B:$B,1) -> 22296.793 | Q4: =SUMIFS('Stato patrimoniale'!AP:AP,'Stato patrimoniale'!$AG:$AG,">0",'Stato patrimoniale'!$AI:$AI,$O4,'Stato patrimoniale'!$B:$B,1) -> 29885.758 | R4: =Q4-P4 -> 7588.9648 | S4: =IF(P4=0,"",R4/P4) -> 0.34036126
A5: Directa | B5: =SUMIFS('Stato patrimoniale'!W:W,'Stato patrimoniale'!$AG:$AG,"",'Stato patrimoniale'!$Y:$Y,$A5,'Stato patrimoniale'!$B:$B,1) -> 16006.76 | C5: =SUMIFS('Stato patrimoniale'!AD:AD,'Stato patrimoniale'!$AG:$AG,"",'Stato patrimoniale'!$Y:$Y,$A5,'Stato patrimoniale'!$B:$B,1) -> 16700.167 | D5: =C5-B5 -> 693.40703 | E5: =IF(B5=0,"",D5/B5) -> 0.043319637 | O5: Directa | P5: =SUMIFS('Stato patrimoniale'!W:W,'Stato patrimoniale'!$AG:$AG,">0",'Stato patrimoniale'!$AI:$AI,$O5,'Stato patrimoniale'!$B:$B,1) -> 0 | Q5: =SUMIFS('Stato patrimoniale'!AP:AP,'Stato patrimoniale'!$AG:$AG,">0",'Stato patrimoniale'!$AI:$AI,$O5,'Stato patrimoniale'!$B:$B,1) -> 0 | R5: =Q5-P5 -> 0 | S5: =IF(P5=0,"",R5/P5)
A6: Sella | B6: =SUMIFS('Stato patrimoniale'!W:W,'Stato patrimoniale'!$AG:$AG,"",'Stato patrimoniale'!$Y:$Y,$A6,'Stato patrimoniale'!$B:$B,1) -> 0 | C6: =SUMIFS('Stato patrimoniale'!AD:AD,'Stato patrimoniale'!$AG:$AG,"",'Stato patrimoniale'!$Y:$Y,$A6,'Stato patrimoniale'!$B:$B,1) -> 0 | D6: =C6-B6 -> 0 | E6: =IF(B6=0,"",D6/B6) | O6: Sella | P6: =SUMIFS('Stato patrimoniale'!W:W,'Stato patrimoniale'!$AG:$AG,">0",'Stato patrimoniale'!$AI:$AI,$O6,'Stato patrimoniale'!$B:$B,1) -> 0 | Q6: =SUMIFS('Stato patrimoniale'!AP:AP,'Stato patrimoniale'!$AG:$AG,">0",'Stato patrimoniale'!$AI:$AI,$O6,'Stato patrimoniale'!$B:$B,1) -> 0 | R6: =Q6-P6 -> 0 | S6: =IF(P6=0,"",R6/P6)
A7: crypto.com | B7: =SUMIFS('Stato patrimoniale'!W:W,'Stato patrimoniale'!$AG:$AG,"",'Stato patrimoniale'!$Y:$Y,$A7,'Stato patrimoniale'!$B:$B,1) -> 0 | C7: =SUMIFS('Stato patrimoniale'!AD:AD,'Stato patrimoniale'!$AG:$AG,"",'Stato patrimoniale'!$Y:$Y,$A7,'Stato patrimoniale'!$B:$B,1) -> 0 | D7: =C7-B7 -> 0 | E7: =IF(B7=0,"",D7/B7) | O7: crypto.com | P7: =SUMIFS('Stato patrimoniale'!W:W,'Stato patrimoniale'!$AG:$AG,">0",'Stato patrimoniale'!$AI:$AI,$O7,'Stato patrimoniale'!$B:$B,1) -> 0 | Q7: =SUMIFS('Stato patrimoniale'!AP:AP,'Stato patrimoniale'!$AG:$AG,">0",'Stato patrimoniale'!$AI:$AI,$O7,'Stato patrimoniale'!$B:$B,1) -> 0 | R7: =Q7-P7 -> 0 | S7: =IF(P7=0,"",R7/P7)
A8: BBVA | B8: =SUMIFS('Stato patrimoniale'!W:W,'Stato patrimoniale'!$AG:$AG,"",'Stato patrimoniale'!$Y:$Y,$A8,'Stato patrimoniale'!$B:$B,1) -> 0 | C8: =SUMIFS('Stato patrimoniale'!AD:AD,'Stato patrimoniale'!$AG:$AG,"",'Stato patrimoniale'!$Y:$Y,$A8,'Stato patrimoniale'!$B:$B,1) -> 0 | D8: =C8-B8 -> 0 | E8: =IF(B8=0,"",D8/B8) | O8: BBVA | P8: =SUMIFS('Stato patrimoniale'!W:W,'Stato patrimoniale'!$AG:$AG,">0",'Stato patrimoniale'!$AI:$AI,$O8,'Stato patrimoniale'!$B:$B,1) -> 0 | Q8: =SUMIFS('Stato patrimoniale'!AP:AP,'Stato patrimoniale'!$AG:$AG,">0",'Stato patrimoniale'!$AI:$AI,$O8,'Stato patrimoniale'!$B:$B,1) -> 0 | R8: =Q8-P8 -> 0 | S8: =IF(P8=0,"",R8/P8)
A9: N26 | B9: =SUMIFS('Stato patrimoniale'!W:W,'Stato patrimoniale'!$AG:$AG,"",'Stato patrimoniale'!$Y:$Y,$A9,'Stato patrimoniale'!$B:$B,1) -> 0 | C9: =SUMIFS('Stato patrimoniale'!AD:AD,'Stato patrimoniale'!$AG:$AG,"",'Stato patrimoniale'!$Y:$Y,$A9,'Stato patrimoniale'!$B:$B,1) -> 0 | D9: =C9-B9 -> 0 | E9: =IF(B9=0,"",D9/B9) | O9: N26 | P9: =SUMIFS('Stato patrimoniale'!W:W,'Stato patrimoniale'!$AG:$AG,">0",'Stato patrimoniale'!$AI:$AI,$O9,'Stato patrimoniale'!$B:$B,1) -> 0 | Q9: =SUMIFS('Stato patrimoniale'!AP:AP,'Stato patrimoniale'!$AG:$AG,">0",'Stato patrimoniale'!$AI:$AI,$O9,'Stato patrimoniale'!$B:$B,1) -> 0 | R9: =Q9-P9 -> 0 | S9: =IF(P9=0,"",R9/P9)
A10: Arancio | B10: =SUMIFS('Stato patrimoniale'!W:W,'Stato patrimoniale'!$AG:$AG,"",'Stato patrimoniale'!$Y:$Y,$A10,'Stato patrimoniale'!$B:$B,1) -> 0 | C10: =SUMIFS('Stato patrimoniale'!AD:AD,'Stato patrimoniale'!$AG:$AG,"",'Stato patrimoniale'!$Y:$Y,$A10,'Stato patrimoniale'!$B:$B,1) -> 0 | D10: =C10-B10 -> 0 | E10: =IF(B10=0,"",D10/B10) | O10: Arancio | P10: =SUMIFS('Stato patrimoniale'!W:W,'Stato patrimoniale'!$AG:$AG,">0",'Stato patrimoniale'!$AI:$AI,$O10,'Stato patrimoniale'!$B:$B,1) -> 0 | Q10: =SUMIFS('Stato patrimoniale'!AP:AP,'Stato patrimoniale'!$AG:$AG,">0",'Stato patrimoniale'!$AI:$AI,$O10,'Stato patrimoniale'!$B:$B,1) -> 0 | R10: =Q10-P10 -> 0 | S10: =IF(P10=0,"",R10/P10)

Sheet Per Area
A1: Titoli in portafoglio | O1: Titoli venduti
A2: Area | B2: Costo totale | C2: Valore totale | D2: Delta | E2: Delta percentuale | O2: Area | P2: Costo totale | Q2: Ricavo totale | R2: Plusvalenza | S2: Rendimento medio
A3: Mondo | B3: =SUMIFS('Stato patrimoniale'!W:W,'Stato patrimoniale'!$AG:$AG,"",'Stato patrimoniale'!$F:$F,$A3,'Stato patrimoniale'!$B:$B,1) -> 39076.926 | C3: =SUMIFS('Stato patrimoniale'!AD:AD,'Stato patrimoniale'!$AG:$AG,"",'Stato patrimoniale'!$F:$F,$A3,'Stato patrimoniale'!$B:$B,1) -> 52019.2 | D3: =C3-B3 -> 12942.274 | E3: =IF(B3=0,"",D3/B3) -> 0.33119991 | O3: Mondo | P3: =SUMIFS('Stato patrimoniale'!W:W,'Stato patrimoniale'!$AG:$AG,">0",'Stato patrimoniale'!$F:$F,$O3,'Stato patrimoniale'!$B:$B,1) -> 1052.9 | Q3: =SUMIFS('Stato patrimoniale'!AP:AP,'Stato patrimoniale'!$AG:$AG,">0",'Stato patrimoniale'!$F:$F,$O3,'Stato patrimoniale'!$B:$B,1) -> 1505.4829 | R3: =Q3-P3 -> 452.58292 | S3: =IF(P3=0,"",R3/P3) -> 0.42984416
A4: Mondo sviluppato | B4: =SUMIFS('Stato patrimoniale'!W:W,'Stato patrimoniale'!$AG:$AG,"",'Stato patrimoniale'!$F:$F,$A4,'Stato patrimoniale'!$B:$B,1) -> 1000.94 | C4: =SUMIFS('Stato patrimoniale'!AD:AD,'Stato patrimoniale'!$AG:$AG,"",'Stato patrimoniale'!$F:$F,$A4,'Stato patrimoniale'!$B:$B,1) -> 1602.38 | D4: =C4-B4 -> 601.44 | E4: =IF(B4=0,"",D4/B4) -> 0.60087518 | O4: Mondo sviluppato | P4: =SUMIFS('Stato patrimoniale'!W:W,'Stato patrimoniale'!$AG:$AG,">0",'Stato patrimoniale'!$F:$F,$O4,'Stato patrimoniale'!$B:$B,1) -> 0 | Q4: =SUMIFS('Stato patrimoniale'!AP:AP,'Stato patrimoniale'!$AG:$AG,">0",'Stato patrimoniale'!$F:$F,$O4,'Stato patrimoniale'!$B:$B,1) -> 0 | R4: =Q4-P4 -> 0 | S4: =IF(P4=0,"",R4/P4)
A5: Mondo ex-US | B5: =SUMIFS('Stato patrimoniale'!W:W,'Stato patrimoniale'!$AG:$AG,"",'Stato patrimoniale'!$F:$F,$A5,'Stato patrimoniale'!$B:$B,1) -> 10014.14 | C5: =SUMIFS('Stato patrimoniale'!AD:AD,'Stato patrimoniale'!$AG:$AG,"",'Stato patrimoniale'!$F:$F,$A5,'Stato patrimoniale'!$B:$B,1) -> 11291.64 | D5: =C5-B5 -> 1277.5 | E5: =IF(B5=0,"",D5/B5) -> 0.12756962 | O5: Mondo ex-US | P5: =SUMIFS('Stato patrimoniale'!W:W,'Stato patrimoniale'!$AG:$AG,">0",'Stato patrimoniale'!$F:$F,$O5,'Stato patrimoniale'!$B:$B,1) -> 0 | Q5: =SUMIFS('Stato patrimoniale'!AP:AP,'Stato patrimoniale'!$AG:$AG,">0",'Stato patrimoniale'!$F:$F,$O5,'Stato patrimoniale'!$B:$B,1) -> 0 | R5: =Q5-P5 -> 0 | S5: =IF(P5=0,"",R5/P5)
A6: Paesi emergenti | B6: =SUMIFS('Stato patrimoniale'!W:W,'Stato patrimoniale'!$AG:$AG,"",'Stato patrimoniale'!$F:$F,$A6,'Stato patrimoniale'!$B:$B,1) -> 0 | C6: =SUMIFS('Stato patrimoniale'!AD:AD,'Stato patrimoniale'!$AG:$AG,"",'Stato patrimoniale'!$F:$F,$A6,'Stato patrimoniale'!$B:$B,1) -> 0 | D6: =C6-B6 -> 0 | E6: =IF(B6=0,"",D6/B6) | O6: Paesi emergenti | P6: =SUMIFS('Stato patrimoniale'!W:W,'Stato patrimoniale'!$AG:$AG,">0",'Stato patrimoniale'!$F:$F,$O6,'Stato patrimoniale'!$B:$B,1) -> 516.05 | Q6: =SUMIFS('Stato patrimoniale'!AP:AP,'Stato patrimoniale'!$AG:$AG,">0",'Stato patrimoniale'!$F:$F,$O6,'Stato patrimoniale'!$B:$B,1) -> 661.588 | R6: =Q6-P6 -> 145.538 | S6: =IF(P6=0,"",R6/P6) -> 0.28202306
A7: US | B7: =SUMIFS('Stato patrimoniale'!W:W,'Stato patrimoniale'!$AG:$AG,"",'Stato patrimoniale'!$F:$F,$A7,'Stato patrimoniale'!$B:$B,1) -> 28785.199 | C7: =SUMIFS('Stato patrimoniale'!AD:AD,'Stato patrimoniale'!$AG:$AG,"",'Stato patrimoniale'!$F:$F,$A7,'Stato patrimoniale'!$B:$B,1) -> 42754.469 | D7: =C7-B7 -> 13969.27 | E7: =IF(B7=0,"",D7/B7) -> 0.48529349 | O7: US | P7: =SUMIFS('Stato patrimoniale'!W:W,'Stato patrimoniale'!$AG:$AG,">0",'Stato patrimoniale'!$F:$F,$O7,'Stato patrimoniale'!$B:$B,1) -> 14440.815 | Q7: =SUMIFS('Stato patrimoniale'!AP:AP,'Stato patrimoniale'!$AG:$AG,">0",'Stato patrimoniale'!$F:$F,$O7,'Stato patrimoniale'!$B:$B,1) -> 20340.281 | R7: =Q7-P7 -> 5899.4655 | S7: =IF(P7=0,"",R7/P7) -> 0.40852718
A8: EU | B8: =SUMIFS('Stato patrimoniale'!W:W,'Stato patrimoniale'!$AG:$AG,"",'Stato patrimoniale'!$F:$F,$A8,'Stato patrimoniale'!$B:$B,1) -> 74703.019 | C8: =SUMIFS('Stato patrimoniale'!AD:AD,'Stato patrimoniale'!$AG:$AG,"",'Stato patrimoniale'!$F:$F,$A8,'Stato patrimoniale'!$B:$B,1) -> 77463.398 | D8: =C8-B8 -> 2760.3795 | E8: =IF(B8=0,"",D8/B8) -> 0.036951379 | O8: EU | P8: =SUMIFS('Stato patrimoniale'!W:W,'Stato patrimoniale'!$AG:$AG,">0",'Stato patrimoniale'!$F:$F,$O8,'Stato patrimoniale'!$B:$B,1) -> 0 | Q8: =SUMIFS('Stato patrimoniale'!AP:AP,'Stato patrimoniale'!$AG:$AG,">0",'Stato patrimoniale'!$F:$F,$O8,'Stato patrimoniale'!$B:$B,1) -> 0 | R8: =Q8-P8 -> 0 | S8: =IF(P8=0,"",R8/P8)
A9: UK | B9: =SUMIFS('Stato patrimoniale'!W:W,'Stato patrimoniale'!$AG:$AG,"",'Stato patrimoniale'!$F:$F,$A9,'Stato patrimoniale'!$B:$B,1) -> 0 | C9: =SUMIFS('Stato patrimoniale'!AD:AD,'Stato patrimoniale'!$AG:$AG,"",'Stato patrimoniale'!$F:$F,$A9,'Stato patrimoniale'!$B:$B,1) -> 0 | D9: =C9-B9 -> 0 | E9: =IF(B9=0,"",D9/B9) | O9: UK | P9: =SUMIFS('Stato patrimoniale'!W:W,'Stato patrimoniale'!$AG:$AG,">0",'Stato patrimoniale'!$F:$F,$O9,'Stato patrimoniale'!$B:$B,1) -> 0 | Q9: =SUMIFS('Stato patrimoniale'!AP:AP,'Stato patrimoniale'!$AG:$AG,">0",'Stato patrimoniale'!$F:$F,$O9,'Stato patrimoniale'!$B:$B,1) -> 0 | R9: =Q9-P9 -> 0 | S9: =IF(P9=0,"",R9/P9)
A10: Cina | B10: =SUMIFS('Stato patrimoniale'!W:W,'Stato patrimoniale'!$AG:$AG,"",'Stato patrimoniale'!$F:$F,$A10,'Stato patrimoniale'!$B:$B,1) -> 0 | C10: =SUMIFS('Stato patrimoniale'!AD:AD,'Stato patrimoniale'!$AG:$AG,"",'Stato patrimoniale'!$F:$F,$A10,'Stato patrimoniale'!$B:$B,1) -> 0 | D10: =C10-B10 -> 0 | E10: =IF(B10=0,"",D10/B10) | O10: Cina | P10: =SUMIFS('Stato patrimoniale'!W:W,'Stato patrimoniale'!$AG:$AG,">0",'Stato patrimoniale'!$F:$F,$O10,'Stato patrimoniale'!$B:$B,1) -> 0 | Q10: =SUMIFS('Stato patrimoniale'!AP:AP,'Stato patrimoniale'!$AG:$AG,">0",'Stato patrimoniale'!$F:$F,$O10,'Stato patrimoniale'!$B:$B,1) -> 0 | R10: =Q10-P10 -> 0 | S10: =IF(P10=0,"",R10/P10)
